Workbook

Sheet Guide Sheet
A1: PyPSA Model Notebook
A2: Todo va en minúsculas y separado por un guión bajo
B3: p_nom | C3: MW
B4: Demandas | C4: MWh
B5: capital_cost | C5: euros
B6: marginal_cost | C6: euros
B7: ramp_limit_up
B8: ramp_limit_down
B9: e_nom | C9: MWh
B10: e_initial
B11: e_min_pu
B12: e_max_pu

Sheet carriers
A1: name | B1: overwrite
A2: AC | B2: true
A3: water | B3: true
A4: wind | B4: true
A5: gas | B5: true
A6: solar_pv | B6: true
A7: solar_csp | B7: true
A8: solar_rooftop | B8: true
A9: grid_import | B9: true
A10: biomass | B10: true
A11: hydrogen | B11: true
A12: load_shedding | B12: true
... A19: extragenerator | B19: true

Sheet buses_2busSRES
A1: name | B1: carrier | C1: overwrite | D1: x | E1: y
A2: ES_electricity_market_bus | B2: AC | C2: true | D2: -3.7038 | E2: 40.4168
A3: ES_water_bus | B3: water | C3: true | D3: -3.7038 | E3: 40.4168
A4: ES_gas_bus | B4: gas | C4: true | D4: -3.7038 | E4: 40.4168
A5: ES_hydrogen_bus | B5: hydrogen | C5: true | D5: -3.7038 | E5: 40.4168
A6: ES_SRES_excedentes_bus | B6: AC | C6: true | D6: -3.7038 | E6: 40.4168
A7: ES_SRES_electrolyzer_bus | B7: hydrogen | C7: true | D7: -3.7038 | E7: 40.4168
A8: PT_electricity_market_bus | B8: AC | C8: true | D8: -9.1393 | E8: 38.7223
A9: PT_water_bus | B9: water | C9: true | D9: -9.1393 | E9: 38.7223
A10: PT_gas_bus | B10: gas | C10: true | D10: -9.1393 | E10: 38.7223
A11: PT_hydrogen_bus | B11: hydrogen | C11: true | D11: -9.1393 | E11: 38.7223
A12: PT_SRES_excedentes_bus | B12: AC | C12: true | D12: -9.1393 | E12: 38.7223
A13: PT_SRES_electrolyzer_bus | B13: hydrogen | C13: true | D13: -9.1393 | E13: 38.7223
... A19: EU_hydrogen_bus | B19: hydrogen | C19: true | D19: 6.3522 | E19: 50.8566

Sheet generators_2busSRES
A1: name | B1: bus | C1: p_nom | D1: marginal_cost | E1: carrier | F1: overwrite
A2: ES_solar_pv | B2: ES_electricity_market_bus | C2: 83000 | D2: 0 | E2: solar_pv | F2: true
A3: ES_solar_csp | B3: ES_electricity_market_bus | C3: 4805 | D3: 0 | E3: solar_csp | F3: true
A4: ES_wind | B4: ES_electricity_market_bus | C4: 91799.794 | D4: 0 | E4: wind | F4: true
A5: ES_biomass | B5: ES_electricity_market_bus | C5: =2462.66 -> 2462.66 | D5: 2 | E5: biomass | F5: true
A6: ES_gas | B6: ES_gas_bus | C6: =10000000000000 -> 10000000000000 | D6: 0 | E6: gas | F6: true
A7: ES_water | B7: ES_electricity_market_bus | C7: 3117.9191 | D7: 0 | E7: water | F7: true
A8: ES_reservoir | B8: ES_electricity_market_bus | C8: 11536.3 | D8: 10 | E8: reservoir | F8: true
A9: ES_extragenerator | B9: ES_electricity_market_bus | C9: 8980 | D9: 8 | E9: extragenerator | F9: true
A10: ES_SRES_excedentes | B10: ES_SRES_excedentes_bus | C10: 32600 | D10: 0 | E10: sres_excedentes | F10: true
A11: ES_SRES_electrolyzer | B11: ES_SRES_electrolyzer_bus | C11: =(37999*2)-C10 -> 43398 | D11: 0 | E11: sres_electrolyzer | F11: true
A12: PT_solar_pv | B12: PT_electricity_market_bus | C12: 14378.2 | D12: 0 | E12: solar_pv | F12: true
A13: PT_wind_onshore | B13: PT_electricity_market_bus | C13: 11643.6 | D13: 0 | E13: wind_onshore | F13: true
A14: PT_wind_offshore | B14: PT_electricity_market_bus | C14: 646 | D14: 0 | E14: wind_offshore | F14: true
A15: PT_biomass | B15: PT_electricity_market_bus | C15: 1607 | D15: 2 | E15: biomass | F15: true
A16: PT_gas | B16: PT_gas_bus | C16: =10000000000000 -> 10000000000000 | D16: 0 | E16: gas | F16: true
A17: PT_water | B17: PT_electricity_market_bus | C17: =508.3+278 -> 786.3 | D17: 0 | E17: water | F17: true
A18: PT_reservoir | B18: PT_electricity_market_bus | C18: 3135.5 | D18: 10 | E18: reservoir | F18: true
A19: PT_extragenerator | B19: PT_electricity_market_bus | C19: 2557 | D19: 8 | E19: extragenerator | F19: true
A20: PT_SRES_excedentes | B20: PT_SRES_excedentes_bus | C20: 13478 | D20: 0 | E20: sres_excedentes | F20: true
A21: PT_SRES_electrolyzer | B21: PT_SRES_electrolyzer_bus | C21: =22506.9-C20 -> 9028.9 | D21: 0 | E21: sres_electrolyzer | F21: true
A22: ES_load_shedding | B22: ES_electricity_market_bus | C22: 10000000 | D22: 10000 | E22: load_shedding | F22: true
A23: PT_load_shedding | B23: PT_electricity_market_bus | C23: 10000000 | D23: 10000 | E23: load_shedding | F23: true
A24: FR_load_shedding | B24: FR_electricity_market_bus | C24: 10000000 | D24: 10000 | E24: load_shedding | F24: true
A25: ES_load_shedding_h2 | B25: ES_hydrogen_bus | C25: 10000000 | D25: 2500 | E25: load_shedding | F25: true
A26: PT_load_shedding_h2 | B26: PT_hydrogen_bus | C26: 10000000 | D26: 2500 | E26: load_shedding | F26: true
A27: FR_load_shedding_h2 | B27: FR_hydrogen_bus | C27: 10000000 | D27: 2500 | E27: load_shedding | F27: true
A28: FRS_load_shedding_h2 | B28: FRS_hydrogen_bus | C28: 10000000 | D28: 2500 | E28: load_shedding | F28: true
A29: FRSW_load_shedding_h2 | B29: FRSW_hydrogen_bus | C29: 10000000 | D29: 2500 | E29: load_shedding | F29: true
A30: FR_electricity_generator | B30: FR_electricity_market_bus | C30: 5000 | D30: 15.63 | E30: AC | F30: true
A31: FR_hydrogen_generator_FRSW | B31: FRSW_hydrogen_bus | C31: 1553.6723 | D31: 0 | E31: hydrogen | F31: true
A32: FR_hydrogen_generator_FRH2 | B32: FR_hydrogen_bus | C32: 6779.661 | D32: 0 | E32: hydrogen | F32: true
A33: FR_hydrogen_generator_FRh2_plus | B33: FR_hydrogen_bus | C33: 6779.661 | D33: 0 | E33: hydrogen | F33: true
A34: MA_h2lowband | B34: MA_hydrogen_bus | C34: 1517.8 | D34: 0 | E34: hydrogen | F34: true
A35: MA_h2highband | B35: MA_hydrogen_bus | C35: =3000-C34 -> 1482.2 | D35: =73.7 -> 73.7 | E35: hydrogen | F35: true
A36: EU_hydrogen_generator | B36: EU_hydrogen_bus | C36: 10116.525 | D36: 0 | E36: hydrogen | F36: true

Sheet links_2busSRES
A1: name | B1: bus0 | C1: bus1 | D1: p_nom | E1: p_min_pu | F1: efficiency | G1: marginal_cost | H1: carrier | I1: overwrite
A2: ES_CCGT | B2: ES_gas_bus | C2: ES_electricity_market_bus | D2: 28766.678 | F2: 1 | G2: 146.19 | H2: gas | I2: true
A3: ES_turbina | B3: ES_water_bus | C3: ES_electricity_market_bus | D3: 13603.98 | F3: 1 | G3: 0 | H3: water | I3: true
A4: ES_pump | B4: ES_electricity_market_bus | C4: ES_water_bus | D4: 13320.75 | F4: 1 | G4: 0 | H4: AC | I4: true
A5: ES_electrolyzer | B5: ES_electricity_market_bus | C5: ES_hydrogen_bus | D5: 15500 | F5: 1 | G5: 0 | H5: hydrogen | I5: true
A6: ES_SRES_electrolyzer | B6: ES_SRES_electrolyzer_bus | C6: ES_hydrogen_bus | D6: =32600 -> 32600 | F6: 0.7 | G6: 0.1 | H6: hydrogen | I6: true
A7: ES_SRES_excedentes | B7: ES_SRES_excedentes_bus | C7: ES_electricity_market_bus | D7: 100000 | F7: 1 | G7: 0 | H7: AC | I7: true
A8: PT_CCGT | B8: PT_gas_bus | C8: PT_electricity_market_bus | D8: =1357+468.996 -> 1825.996 | F8: 1 | G8: 146.19 | H8: gas | I8: true
A9: PT_turbina | B9: PT_water_bus | C9: PT_electricity_market_bus | D9: 4613 | F9: 1 | G9: 0 | H9: water | I9: true
A10: PT_pump | B10: PT_electricity_market_bus | C10: PT_water_bus | D10: 3837 | F10: 1 | G10: 0 | H10: AC | I10: true
A11: PT_electrolyzer | B11: PT_electricity_market_bus | C11: PT_hydrogen_bus | D11: 0 | F11: 0.7 | G11: 0 | H11: hydrogen | I11: true
A12: PT_SRES_electrolyzer | B12: PT_SRES_electrolyzer_bus | C12: PT_hydrogen_bus | D12: =13478 -> 13478 | F12: 0.7 | G12: 0 | H12: hydrogen | I12: true
A13: PT_SRES_excedentes | B13: PT_SRES_excedentes_bus | C13: PT_electricity_market_bus | D13: 100000 | F13: 1 | G13: 0 | H13: AC | I13: true
A14: ES_PT_interconexion_electricidad | B14: ES_electricity_market_bus | C14: PT_electricity_market_bus | D14: 4200 | F14: 1 | G14: 2 | H14: AC | I14: true
A15: ES_PT_interconexion_hidrogeno | B15: ES_hydrogen_bus | C15: PT_hydrogen_bus | D15: 2860.1695 | F15: 1 | G15: 0.01 | H15: hydrogen | I15: true
A16: PT_ES_interconexion_electricidad | B16: PT_electricity_market_bus | C16: ES_electricity_market_bus | D16: 3500 | F16: 1 | G16: 2 | H16: AC | I16: true
A17: PT_ES_interconexion_hidrogeno | B17: PT_hydrogen_bus | C17: ES_hydrogen_bus | D17: 2860.1695 | F17: 1 | G17: 0 | H17: hydrogen | I17: true
A18: ES_FR_interconexion_electricidad | B18: ES_electricity_market_bus | C18: FR_electricity_market_bus | D18: 5001 | F18: 1 | G18: 2 | H18: AC | I18: true
A19: FR_ES_interconexion_electricidad | B19: FR_electricity_market_bus | C19: ES_electricity_market_bus | D19: 5001 | F19: 1 | G19: 2 | H19: AC | I19: true
A20: ES_FR_interconexion_hidrogeno_IrunLarrau | B20: ES_hydrogen_bus | C20: FRSW_hydrogen_bus | D20: 5014.1243 | F20: 1 | G20: 0.01 | H20: hydrogen | I20: true
A21: ES_FR_interconexion_hidrogeno_BarMar | B21: ES_hydrogen_bus | C21: FRS_hydrogen_bus | D21: 7627.1186 | F21: 1 | G21: 0.01 | H21: hydrogen | I21: true
A22: FR_ES_interconexion_hidrogeno_BarMar | B22: FRS_hydrogen_bus | C22: ES_hydrogen_bus | D22: 7627.1186 | F22: 1 | G22: 0.01 | H22: hydrogen | I22: true
A23: FR_FR_interconexion_hidrogeno_SWtoS | B23: FRSW_hydrogen_bus | C23: FRS_hydrogen_bus | D23: 1553.6723 | F23: 1 | G23: 0.01 | H23: hydrogen | I23: true
A24: FR_FR_interconexion_hidrogeno_StoFRh2 | B24: FRS_hydrogen_bus | C24: FR_hydrogen_bus | D24: 6780.661 | F24: 1 | G24: 0.01 | H24: hydrogen | I24: true
A25: FR_FR_interconexion_hidrogeno_FRh2toS | B25: FR_hydrogen_bus | C25: FRS_hydrogen_bus | D25: 6780.661 | F25: 1 | G25: 0.01 | H25: hydrogen | I25: true
A26: MA_ES_interconexion_hidrogeno | B26: MA_hydrogen_bus | C26: ES_hydrogen_bus | D26: 3742.94 | E26: 0.4 | F26: 1 | G26: 0.01 | H26: hydrogen | I26: true
A27: EU_FR_hidrogeno | B27: EU_hydrogen_bus | C27: FR_hydrogen_bus | D27: 10000 | F27: 1 | G27: 0.001 | H27: hydrogen | I27: true
A28: FR_EU_hidrogeno | B28: FR_hydrogen_bus | C28: EU_hydrogen_bus | D28: 10116.525 | F28: 1 | G28: 0.001 | H28: hydrogen | I28: true

Sheet loads
A1: name | B1: bus | C1: carrier | D1: overwrite
A2: ES_demand_2040 | B2: ES_electricity_market_bus | C2: AC | D2: true
A3: ES_hydrogen_demand | B3: ES_hydrogen_bus | C3: hydrogen | D3: true
A4: PT_demand_2040 | B4: PT_electricity_market_bus | C4: AC | D4: true
A5: PT_hydrogen_demand | B5: PT_hydrogen_bus | C5: hydrogen | D5: true
A6: FR_demand_2040 | B6: FR_electricity_market_bus | C6: AC | D6: true
A7: FR_hydrogen_demand | B7: FR_hydrogen_bus | C7: hydrogen | D7: true
A8: EU_hydrogen_demand | B8: EU_hydrogen_bus | C8: hydrogen | D8: true

Sheet run_of_river_inflow
A1: hora | B1: ES_hydraulic_profile | C1: PT_hydraulic_profile | D1: FR_hydraulic_profile
A2: =0 -> 0 | B2: 0.25493919 | C2: 0.46568963 | D2: 0.50275862
A3: =A2+1 -> 1 | B3: 0.25493919 | C3: 0.81843675 | D3: 0.50275862
A4: =A3+1 -> 2 | B4: 0.25493919 | C4: 0.46568963 | D4: 0.50275862
A5: =A4+1 -> 3 | B5: 0.25493919 | C5: 0.81843675 | D5: 0.50275862
A6: =A5+1 -> 4 | B6: 0.25493919 | C6: 0.46568963 | D6: 0.50275862
A7: =A6+1 -> 5 | B7: 0.25493919 | C7: 0.81843675 | D7: 0.50275862
A8: =A7+1 -> 6 | B8: 0.25493919 | C8: 0.46568963 | D8: 0.50275862
A9: =A8+1 -> 7 | B9: 0.25493919 | C9: 0.46568963 | D9: 0.50275862
A10: =A9+1 -> 8 | B10: 0.25493919 | C10: 0.81843675 | D10: 0.50275862
A11: =A10+1 -> 9 | B11: 0.25493919 | C11: 0.6612232 | D11: 0.50275862
A12: =A11+1 -> 10 | B12: 0.25493919 | C12: 0.46568963 | D12: 0.50275862
A13: =A12+1 -> 11 | B13: 0.25493919 | C13: 0.46568963 | D13: 0.50275862
A14: =A13+1 -> 12 | B14: 0.25493919 | C14: 0.46568963 | D14: 0.50275862
... A169: =A168+1 -> 167 | B169: 0.25493919 | C169: 0.81843675 | D169: 0.50275862

Sheet store
A1: name | B1: bus | C1: e_nom | D1: e_initial | E1: e_min_pu | F1: e_max_pu | G1: cyclic_state_of_charge | H1: marginal_cost | I1: carrier | J1: overwrite
A2: ES_embalse | B2: ES_water_bus | C2: =20414989 -> 20414989 | D2: =C2*F2 -> 18373490 | E2: 0.2 | F2: 0.9 | G2: false | H2: 1 | I2: water | J2: true
A3: PT_embalse | B3: PT_water_bus | C3: =3307600 -> 3307600 | D3: =C3*F3 -> 2976840 | E3: 0.2 | F3: 0.9 | G3: false | H3: 1 | I3: water | J3: true

Sheet storage_units
A1: name | B1: bus | C1: p_nom | D1: max_hours | E1: efficiency_store | F1: efficiency_dispatch | G1: capital_cost | H1: cyclic_state_of_charge | I1: marginal_cost | J1: carrier | K1: overwrite
A2: ES_electricity_market_battery | B2: ES_electricity_market_bus | C2: =26698 -> 26698 | D2: 2 | E2: 0.89658206 | F2: 0.89658206 | H2: false | I2: 0.1 | J2: AC | K2: true
A3: ES_hydrogen_market_battery | B3: ES_hydrogen_bus | C3: 2583 | D3: 591.56 | E3: 1 | F3: 1 | H3: false | I3: 1 | J3: hydrogen | K3: true
A4: PT_electricity_market_battery | B4: PT_electricity_market_bus | C4: =3000 -> 3000 | D4: 4 | E4: 0.92 | F4: 0.92 | H4: false | I4: 0.1 | J4: AC | K4: true
A5: FRSW_hydrogen_market_battery | B5: FRSW_hydrogen_bus | C5: 330 | D5: 1609.0909 | E5: 1 | F5: 1 | H5: false | I5: 1 | J5: hydrogen | K5: true
A6: FRS_hydrogen_market_battery | B6: FRS_hydrogen_bus | C6: 1240 | D6: 479.83871 | E6: 1 | F6: 1 | H6: false | I6: 1 | J6: hydrogen | K6: true

Sheet demands
A1: ES_demand_2040 | B1: ES_hydrogen_demand | C1: PT_demand_2040 | D1: PT_hydrogen_demand | E1: FR_demand_2040 | F1: FR_hydrogen_demand | G1: EU_hydrogen_demand
A2: 38627.656 | B2: 11835.473 | C2: 9779.8592 | D2: 1194.7295 | E2: 0 | F2: 6779.661 | G2: 10116.525
A3: 42028.284 | B3: 11835.473 | C3: 8281.423 | D3: 1194.7295 | E3: 0 | F3: 6779.661 | G3: 10116.525
A4: 41474.456 | B4: 11835.473 | C4: 7831.94 | D4: 1194.7295 | E4: 0 | F4: 6779.661 | G4: 10116.525
A5: 41617.486 | B5: 11835.473 | C5: 10008.773 | D5: 1194.7295 | E5: 0 | F5: 6779.661 | G5: 10116.525
A6: 40803.821 | B6: 11851.183 | C6: 8961.4193 | D6: 1194.7295 | E6: 0 | F6: 6779.661 | G6: 10116.525
A7: 37447.756 | B7: 11882.603 | C7: 8637.9358 | D7: 1292.686 | E7: 0 | F7: 6779.661 | G7: 10116.525
A8: 36103.774 | B8: 11898.313 | C8: 7383.2223 | D8: 1390.6425 | E8: 0 | F8: 6779.661 | G8: 10116.525
A9: 39057.199 | B9: 11914.023 | C9: 7502.5396 | D9: 1483.4434 | E9: 0 | F9: 6779.661 | G9: 10116.525
A10: 39793.092 | B10: 11914.023 | C10: 7534.8562 | D10: 1581.3998 | E10: 0 | F10: 6779.661 | G10: 10116.525
A11: 38571.938 | B11: 11914.023 | C11: 8215.5817 | D11: 1581.3998 | E11: 0 | F11: 6779.661 | G11: 10116.525
A12: 37154.668 | B12: 11914.023 | C12: 10254.134 | D12: 1632.9559 | E12: 578.16101 | F12: 6779.661 | G12: 10116.525
A13: 37945.551 | B13: 11898.313 | C13: 11911.796 | D13: 1632.9559 | E13: 5000 | F13: 6779.661 | G13: 10116.525
... A169: 50085.064 | B169: 11999.059 | C169: 8903.6357 | D169: 1455.3989 | E169: 5000 | F169: 6779.661 | G169: 10116.525

Sheet profiles
A1: ES_solar_pv_profile | B1: ES_solar_csp_profile | C1: ES_wind_profile | D1: ES_biomass_profile | E1: ES_ccgt_profile | F1: ES_turbine_profile | G1: ES_pump_profile | H1: ES_reservoir_profile | I1: ES_electrolyzer_profile | J1: ES_excedentes_profile | K1: ES_generacionh2SRES | L1: PT_solar_pv_profile | M1: PT_wind_onshore_profile | N1: PT_wind_offshore_profile | O1: PT_biomass_profile | P1: PT_ccgt_profile | Q1: PT_turbine_profile | R1: PT_pump_profile | S1: PT_reservoir_profile | T1: PT_electrolyzer_profile | U1: PT_excedentes_profile | V1: PT_generacionh2SRES | W1: MA_hydrogen_profile_high | X1: MA_hydrogen_profile_low | Y1: FR00_generation | Z1: FRh2_generation | AA1: FRh2_generation+ | AB1: FRh2SW_generation | AC1: ES_extragenerator | AD1: PT_extragenerator | AE1: FR_irunlarrao | AF1: FR_precioFRh2 | AG1: EU_precio | AH1: EU_generation
A2: 0 | B2: 0 | C2: 0.27513822 | D2: 0.26900019 | E2: 0.257 | F2: 0.23203283 | G2: 0 | H2: 0.68245451 | I2: 0.32071055 | J2: 0 | K2: 0.22770449 | L2: 0 | M2: 0.119 | N2: 0.132 | O2: 0.5376117 | P2: 0.84 | Q2: 1 | R2: 0 | S2: 0.82634349 | T2: 0.1045903 | U2: 0 | V2: 0.07425911 | W2: 0.71590848 | X2: =1 -> 1 | Y2: 1 | Z2: 0 | AA2: 1 | AB2: 0.78759999 | AC2: 0 | AD2: 0 | AE2: 0 | AF2: ='Datos Modificaciones Bus Europa'!G4 -> 147.6721 | AG2: ='Datos Modificaciones Bus Europa'!F4 -> 144.7479 | AH2: 1
A3: 0 | B3: 0 | C3: 0.29443188 | D3: 0.26699991 | E3: 0.257 | F3: 0.23203283 | G3: 0.46792369 | H3: 0.68245451 | I3: 0.34319991 | J3: 0 | K3: 0.24367193 | L3: 0 | M3: 0.125 | N3: 0.118 | O3: 0.53382203 | P3: 0.84 | Q3: 1 | R3: 0 | S3: 0.82634349 | T3: 0.096099792 | U3: 0 | V3: 0.068230853 | W3: 0.71590848 | X3: =1 -> 1 | Y3: 1 | Z3: 0 | AA3: 1 | AB3: 0.78759999 | AC3: 0 | AD3: 0 | AE3: 0 | AF3: ='Datos Modificaciones Bus Europa'!G5 -> 12.1402 | AG3: ='Datos Modificaciones Bus Europa'!F5 -> 11.8998 | AH3: 1
A4: 0 | B4: 0 | C4: 0.29945538 | D4: 0.26500004 | E4: 0.257 | F4: 0.23203283 | G4: 0.17940284 | H4: 0.68245451 | I4: 0.34905549 | J4: 0 | K4: 0.2478294 | L4: 0 | M4: 0.137 | N4: 0.11 | O4: 0.53300436 | P4: 0.84 | Q4: 1 | R4: 0 | S4: 0.82634349 | T4: 0.090471212 | U4: 0 | V4: 0.064234561 | W4: 0.71590848 | X4: =1 -> 1 | Y4: 1 | Z4: 0 | AA4: 1 | AB4: 0.78759999 | AC4: 0 | AD4: 0 | AE4: 0 | AF4: ='Datos Modificaciones Bus Europa'!G6 -> 12.1402 | AG4: ='Datos Modificaciones Bus Europa'!F6 -> 11.8998 | AH4: 1
A5: 0 | B5: 0 | C5: 0.30697123 | D5: 0.2749998 | E5: 0.257 | F5: 0.23203283 | G5: 0.11157777 | H5: 0.68245451 | I5: 0.35781623 | J5: 0 | K5: 0.25404952 | L5: 0 | M5: 0.153 | N5: 0.105 | O5: 0.53906596 | P5: 0.84 | Q5: 1 | R5: 0 | S5: 0.82634349 | T5: 0.085199585 | U5: 0 | V5: 0.060491705 | W5: 0.71590848 | X5: =1 -> 1 | Y5: 1 | Z5: 0 | AA5: 1 | AB5: 0.78759999 | AC5: 0 | AD5: 0 | AE5: 0 | AF5: ='Datos Modificaciones Bus Europa'!G7 -> 12.1402 | AG5: ='Datos Modificaciones Bus Europa'!F7 -> 11.8998 | AH5: 1
A6: 0 | B6: 0 | C6: 0.32181368 | D6: 0.27899994 | E6: 0.257 | F6: 0.23203283 | G6: 0.52852217 | H6: 0.68245451 | I6: 0.37511709 | J6: 0 | K6: 0.26633313 | L6: 0 | M6: 0.167 | N6: 0.101 | O6: 0.54218046 | P6: 0.84 | Q6: 1 | R6: 0 | S6: 0.82634349 | T6: 0.081436637 | U6: 0 | V6: 0.057820013 | W6: 0.71590848 | X6: =1 -> 1 | Y6: 1 | Z6: 0 | AA6: 1 | AB6: 0.78759999 | AC6: 0 | AD6: 0 | AE6: 0 | AF6: ='Datos Modificaciones Bus Europa'!G8 -> 10.1202 | AG6: ='Datos Modificaciones Bus Europa'!F8 -> 9.9198 | AH6: 1
A7: 0 | B7: 0 | C7: 0.32374316 | D7: 0.29099998 | E7: 0.257 | F7: 0.23203283 | G7: 0.78248972 | H7: 0.68245451 | I7: 0.37736613 | J7: 0 | K7: 0.26792996 | L7: 0 | M7: 0.178 | N7: 0.097 | O7: 0.55440075 | P7: 0.84 | Q7: 1 | R7: 0 | S7: 0.82634349 | T7: 0.079330835 | U7: 0 | V7: 0.056324893 | W7: 0.71590848 | X7: =1 -> 1 | Y7: 1 | Z7: 0 | AA7: 1 | AB7: 0.78759999 | AC7: 0 | AD7: 0 | AE7: 0 | AF7: ='Datos Modificaciones Bus Europa'!G9 -> 10.1202 | AG7: ='Datos Modificaciones Bus Europa'!F9 -> 9.9198 | AH7: 1
A8: 0 | B8: 0 | C8: 0.3027346 | D8: 0.32799981 | E8: 0.257 | F8: 0.23203283 | G8: 0.6529081 | H8: 0.68245451 | I8: 0.35287785 | J8: 0 | K8: 0.25054328 | L8: 0 | M8: 0.183 | N8: 0.092 | O8: 0.56481269 | P8: 0.84 | Q8: 1 | R8: 0 | S8: 0.82634349 | T8: 0.076747292 | U8: 0 | V8: 0.054490577 | W8: 0.71590848 | X8: =1 -> 1 | Y8: 1 | Z8: 0 | AA8: 1 | AB8: 0.78759999 | AC8: 0 | AD8: 0 | AE8: 0 | AF8: ='Datos Modificaciones Bus Europa'!G10 -> 10.1202 | AG8: ='Datos Modificaciones Bus Europa'!F10 -> 9.9198 | AH8: 1
A9: 0 | B9: 0 | C9: 0.24533329 | D9: 0.35799989 | E9: 0.257 | F9: 0.23203283 | G9: 0 | H9: 0.68245451 | I9: 0.2859689 | J9: 0 | K9: 0.20303792 | L9: 0 | M9: 0.183 | N9: 0.091 | O9: 0.56885128 | P9: 0.84 | Q9: 1 | R9: 0 | S9: 0.82634349 | T9: 0.077074863 | U9: 0 | V9: 0.054723153 | W9: 0.71590848 | X9: =1 -> 1 | Y9: 1 | Z9: 0 | AA9: 1 | AB9: 0.78759999 | AC9: 0 | AD9: 0 | AE9: 0 | AF9: ='Datos Modificaciones Bus Europa'!G11 -> 12.1402 | AG9: ='Datos Modificaciones Bus Europa'!F11 -> 11.8998 | AH9: 1
A10: 0 | B10: 0 | C10: 0.19145564 | D10: 0.37100006 | E10: 0.257 | F10: 0.23203283 | G10: 0 | H10: 0.68245451 | I10: 0.22869706 | J10: 0 | K10: 0.16237491 | L10: 0 | M10: 0.172 | N10: 0.089 | O10: 0.56735719 | P10: 0.84 | Q10: 1 | R10: 0 | S10: 0.82634349 | T10: 0.077029604 | U10: 0 | V10: 0.054691019 | W10: 0.71590848 | X10: =1 -> 1 | Y10: 1 | Z10: 0 | AA10: 1 | AB10: 0.78759999 | AC10: 0 | AD10: 0 | AE10: 0 | AF10: ='Datos Modificaciones Bus Europa'!G12 -> 12.1402 | AG10: ='Datos Modificaciones Bus Europa'!F12 -> 11.8998 | AH10: 1
A11: 0.122 | B11: 0.071 | C11: 0.1646723 | D11: 0.39099998 | E11: 0.257 | F11: 0.23203283 | G11: 0.30477425 | H11: 0.68245451 | I11: 0.3395939 | J11: 0 | K11: 0.24111167 | L11: 0.074 | M11: 0.134 | N11: 0.089 | O11: 0.5672626 | P11: 0.84 | Q11: 1 | R11: 0 | S11: 0.82634349 | T11: 0.12732067 | U11: 0 | V11: 0.08694803 | W11: 0.71590848 | X11: =1 -> 1 | Y11: 1 | Z11: 0 | AA11: 1 | AB11: 0.78759999 | AC11: 0 | AD11: 0 | AE11: 0 | AF11: ='Datos Modificaciones Bus Europa'!G13 -> 12.1402 | AG11: ='Datos Modificaciones Bus Europa'!F13 -> 11.8998 | AH11: 1
A12: 0.313 | B12: 0.188 | C12: 0.15553496 | D12: 0.39899986 | E12: 0.257 | F12: 0 | G12: 0.78248972 | H12: 0.68245451 | I12: 0.54153374 | J12: 0 | K12: 0.38448896 | L12: 0.265 | M12: 0.072 | N12: 0.085 | O12: 0.57141879 | P12: 0.84 | Q12: 1 | R12: 0 | S12: 0.82634349 | T12: 0.26103302 | U12: 0 | V12: 0.12303024 | W12: 0.71590848 | X12: =1 -> 1 | Y12: 0 | Z12: 0 | AA12: 1 | AB12: 0.58085181 | AC12: 0.36858103 | AD12: 0.1990454 | AE12: 0.12987701 | AF12: ='Datos Modificaciones Bus Europa'!G14 -> 0.16448571 | AG12: ='Datos Modificaciones Bus Europa'!F14 -> 0.16122857 | AH12: 1
A13: 0.379 | B13: 0.31 | C13: 0.16481443 | D13: 0.40499988 | E13: 0.257 | F13: 0 | G13: 0.78248972 | H13: 0.68245451 | I13: 0.67041506 | J13: 0 | K13: 0.47599469 | L13: 0.442 | M13: 0.038 | N13: 0.082 | O13: 0.56903049 | P13: 0.84 | Q13: 0.7552577 | R13: 0 | S13: 0.82634349 | T13: 0.39263199 | U13: 0 | V13: 0.15528725 | W13: 0.71590848 | X13: =1 -> 1 | Y13: 0 | Z13: 0 | AA13: 1 | AB13: 0.3687478 | AC13: 0.60054407 | AD13: 0.60361206 | AE13: 0.18916563 | AF13: ='Datos Modificaciones Bus Europa'!G15 -> 0.16448571 | AG13: ='Datos Modificaciones Bus Europa'!F15 -> 0.16122857 | AH13: 1
... A168: 0 | B168: 0 | C168: 0.73354012 | D168: 0.37299993 | E168: 0.257 | F168: 0.6971194 | G168: 1 | H168: 0.68245451 | I168: 0.85503957 | J168: 0 | K168: 0.29351151 | L168: 0 | M168: 0.277 | N168: 0.448 | O168: 0.63864406 | P168: 0.84 | Q168: 1 | R168: 1 | S168: 0.82634349 | T168: 0.30058807 | U168: 0 | V168: 0.1079833 | W168: 1 | X168: =1 -> 1 | Y168: 0 | Z168: 0 | AA168: 1 | AB168: 0.36998878 | AC168: 0 | AD168: 0 | AE168: 0 | AF168: ='Datos Modificaciones Bus Europa'!G170 -> 0.16448571 | AG168: ='Datos Modificaciones Bus Europa'!F170 -> 0.16122857 | AH168: 1
A169: 0 | B169: 0 | C169: 0.75291925 | D169: 0.36900019 | E169: 0.257 | F169: 0 | G169: 1 | H169: 0.68245451 | I169: 0.87762856 | J169: 0 | K169: 0.62311628 | L169: 0 | M169: 0.349 | N169: 0.509 | O169: 0.63848289 | P169: 0.84 | Q169: 0.30094783 | R169: 0 | S169: 0.82634349 | T169: 0.34166486 | U169: 0 | V169: 0.1079833 | W169: 1 | X169: 1 | Y169: 0 | Z169: 0 | AA169: 1 | AB169: 0.36998878 | AC169: 0 | AD169: 0 | AE169: 0 | AF169: ='Datos Modificaciones Bus Europa'!G171 -> 0.16448571 | AG169: ='Datos Modificaciones Bus Europa'!F171 -> 0.16122857 | AH169: 1

Sheet Datos Modificaciones Bus Europa
F2: 10% más barato | G2: 10% aumento es el límite | I2: Precio del Run inicial | K2: Importaciones y Exportaciones en Francia | AD2: Modelo Objetivo | AG2: Modelo Objetivo | AH2: Generador 2
B3: Hora | C3: Generación 2 FRh2 | D3: Demanda FRh2 | E3: Demanda EUh2 | F3: M.Cost Gen EUh2 | G3: M.Cost FRh2 gen+ | I3: FR_hydrogen_bus | K3: FRh2-FRh2S | L3: FRh2S-FRh2 | M3: FRh2-LUh2 | N3: LUh2-FRh2 | O3: FRh2S-FRh2SW | P3: FRh2SW-FRh2S | Q3: BEh2-FRh2 | R3: FRh2-BEh2 | S3: BEh2-FRh2N | T3: FRh2N-BEh2 | U3: DEh2-FRh2 | V3: FRh2-DEh2 | W3: FRh2-FRh2S | X3: FRh2S-FRh2 | Y3: FRh2SW-FRh2S | Z3: Ammonia_FRN-FRh2N | AA3: Ammonia_FRSW-FRh2SW | AB3: FRh2-e-liquids | AD3: Line Flow FRh2-FRh2S | AE3: FRh2-FRh2S | AF3: FRh2S-FRh2 | AG3: Demanda 1 | AH3: Demanda 2
B4: =1 -> 1 | C4: =AH4 -> 10116.525 | D4: =AG4 -> 6779.661 | E4: =AH4 -> 10116.525 | F4: =0.99*I4 -> 144.7479 | G4: =1.01*I4 -> 147.6721 | I4: 146.21 | K4: 0 | L4: 6779.661 | M4: 1447.7401 | N4: 0 | O4: 0 | P4: 1553.6723 | Q4: 0 | R4: 1271.1864 | S4: 0 | T4: 847.5 | U4: 0 | V4: 7397.5989 | W4: 0 | X4: 6779.661 | Y4: 1553.6723 | Z4: 847.5 | AA4: 735.835 | AB4: 461.65552 | AD4: -6779.661 | AE4: =IF(AD4<0,0,AD4) -> 0 | AF4: =IF(AD4>0,0,-AD4) -> 6779.661 | AG4: 6779.661 | AH4: =M4+R4+V4 -> 10116.525
B5: =B4+1 -> 2 | C5: =AH5 -> 10116.525 | D5: =AG5 -> 6779.661 | E5: =AH5 -> 10116.525 | F5: =0.99*I5 -> 11.8998 | G5: =1.01*I5 -> 12.1402 | I5: 12.02 | K5: 0 | L5: 6779.661 | M5: 1447.7401 | N5: 0 | O5: 0 | P5: 1553.6723 | Q5: 0 | R5: 1271.1864 | S5: 0 | T5: 847.5 | U5: 0 | V5: 7397.5989 | W5: 0 | X5: 6779.661 | Y5: 1553.6723 | Z5: 847.5 | AA5: 735.835 | AB5: 461.65552 | AD5: -6779.661 | AE5: =IF(AD5<0,0,AD5) -> 0 | AF5: =IF(AD5>0,0,-AD5) -> 6779.661 | AG5: 6779.661 | AH5: =M5+R5+V5 -> 10116.525
B6: =B5+1 -> 3 | C6: =AH6 -> 10116.525 | D6: =AG6 -> 6779.661 | E6: =AH6 -> 10116.525 | F6: =0.99*I6 -> 11.8998 | G6: =1.01*I6 -> 12.1402 | I6: 12.02 | K6: 0 | L6: 6779.661 | M6: 1447.7401 | N6: 0 | O6: 0 | P6: 1553.6723 | Q6: 0 | R6: 1271.1864 | S6: 0 | T6: 847.5 | U6: 0 | V6: 7397.5989 | W6: 0 | X6: 6779.661 | Y6: 1553.6723 | Z6: 847.5 | AA6: 735.835 | AB6: 461.65552 | AD6: -6779.661 | AE6: =IF(AD6<0,0,AD6) -> 0 | AF6: =IF(AD6>0,0,-AD6) -> 6779.661 | AG6: 6779.661 | AH6: =M6+R6+V6 -> 10116.525
B7: =B6+1 -> 4 | C7: =AH7 -> 10116.525 | D7: =AG7 -> 6779.661 | E7: =AH7 -> 10116.525 | F7: =0.99*I7 -> 11.8998 | G7: =1.01*I7 -> 12.1402 | I7: 12.02 | K7: 0 | L7: 6779.661 | M7: 1447.7401 | N7: 0 | O7: 0 | P7: 1553.6723 | Q7: 0 | R7: 1271.1864 | S7: 0 | T7: 847.5 | U7: 0 | V7: 7397.5989 | W7: 0 | X7: 6779.661 | Y7: 1553.6723 | Z7: 847.5 | AA7: 735.835 | AB7: 461.65552 | AD7: -6779.661 | AE7: =IF(AD7<0,0,AD7) -> 0 | AF7: =IF(AD7>0,0,-AD7) -> 6779.661 | AG7: 6779.661 | AH7: =M7+R7+V7 -> 10116.525
B8: =B7+1 -> 5 | C8: =AH8 -> 10116.525 | D8: =AG8 -> 6779.661 | E8: =AH8 -> 10116.525 | F8: =0.99*I8 -> 9.9198 | G8: =1.01*I8 -> 10.1202 | I8: 10.02 | K8: 0 | L8: 6779.661 | M8: 1447.7401 | N8: 0 | O8: 0 | P8: 1553.6723 | Q8: 0 | R8: 1271.1864 | S8: 0 | T8: 847.5 | U8: 0 | V8: 7397.5989 | W8: 0 | X8: 6779.661 | Y8: 1553.6723 | Z8: 847.5 | AA8: 735.835 | AB8: 453.37765 | AD8: -6779.661 | AE8: =IF(AD8<0,0,AD8) -> 0 | AF8: =IF(AD8>0,0,-AD8) -> 6779.661 | AG8: 6779.661 | AH8: =M8+R8+V8 -> 10116.525
B9: =B8+1 -> 6 | C9: =AH9 -> 10116.525 | D9: =AG9 -> 6779.661 | E9: =AH9 -> 10116.525 | F9: =0.99*I9 -> 9.9198 | G9: =1.01*I9 -> 10.1202 | I9: 10.02 | K9: 0 | L9: 6779.661 | M9: 1447.7401 | N9: 0 | O9: 0 | P9: 1553.6723 | Q9: 0 | R9: 1271.1864 | S9: 0 | T9: 847.5 | U9: 0 | V9: 7397.5989 | W9: 0 | X9: 6779.661 | Y9: 1553.6723 | Z9: 847.5 | AA9: 735.835 | AB9: 436.8219 | AD9: -6779.661 | AE9: =IF(AD9<0,0,AD9) -> 0 | AF9: =IF(AD9>0,0,-AD9) -> 6779.661 | AG9: 6779.661 | AH9: =M9+R9+V9 -> 10116.525
B10: =B9+1 -> 7 | C10: =AH10 -> 10116.525 | D10: =AG10 -> 6779.661 | E10: =AH10 -> 10116.525 | F10: =0.99*I10 -> 9.9198 | G10: =1.01*I10 -> 10.1202 | I10: 10.02 | K10: 0 | L10: 6779.661 | M10: 1447.7401 | N10: 0 | O10: 0 | P10: 1553.6723 | Q10: 0 | R10: 1271.1864 | S10: 0 | T10: 847.5 | U10: 0 | V10: 7397.5989 | W10: 0 | X10: 6779.661 | Y10: 1553.6723 | Z10: 847.5 | AA10: 735.835 | AB10: 428.54402 | AD10: -6779.661 | AE10: =IF(AD10<0,0,AD10) -> 0 | AF10: =IF(AD10>0,0,-AD10) -> 6779.661 | AG10: 6779.661 | AH10: =M10+R10+V10 -> 10116.525
B11: =B10+1 -> 8 | C11: =AH11 -> 10116.525 | D11: =AG11 -> 6779.661 | E11: =AH11 -> 10116.525 | F11: =0.99*I11 -> 11.8998 | G11: =1.01*I11 -> 12.1402 | I11: 12.02 | K11: 0 | L11: 6779.661 | M11: 1447.7401 | N11: 0 | O11: 0 | P11: 1553.6723 | Q11: 0 | R11: 1271.1864 | S11: 0 | T11: 847.5 | U11: 0 | V11: 7397.5989 | W11: 0 | X11: 6779.661 | Y11: 1553.6723 | Z11: 847.5 | AA11: 735.835 | AB11: 420.26615 | AD11: -6779.661 | AE11: =IF(AD11<0,0,AD11) -> 0 | AF11: =IF(AD11>0,0,-AD11) -> 6779.661 | AG11: 6779.661 | AH11: =M11+R11+V11 -> 10116.525
B12: =B11+1 -> 9 | C12: =AH12 -> 10116.525 | D12: =AG12 -> 6779.661 | E12: =AH12 -> 10116.525 | F12: =0.99*I12 -> 11.8998 | G12: =1.01*I12 -> 12.1402 | I12: 12.02 | K12: 0 | L12: 6779.661 | M12: 1447.7401 | N12: 0 | O12: 0 | P12: 1553.6723 | Q12: 0 | R12: 1271.1864 | S12: 0 | T12: 847.5 | U12: 0 | V12: 7397.5989 | W12: 0 | X12: 6779.661 | Y12: 1553.6723 | Z12: 847.5 | AA12: 735.835 | AB12: 420.26615 | AD12: -6779.661 | AE12: =IF(AD12<0,0,AD12) -> 0 | AF12: =IF(AD12>0,0,-AD12) -> 6779.661 | AG12: 6779.661 | AH12: =M12+R12+V12 -> 10116.525
B13: =B12+1 -> 10 | C13: =AH13 -> 10116.525 | D13: =AG13 -> 6779.661 | E13: =AH13 -> 10116.525 | F13: =0.99*I13 -> 11.8998 | G13: =1.01*I13 -> 12.1402 | I13: 12.02 | K13: 0 | L13: 6779.661 | M13: 1447.7401 | N13: 0 | O13: 0 | P13: 1553.6723 | Q13: 0 | R13: 1271.1864 | S13: 0 | T13: 847.5 | U13: 0 | V13: 7397.5989 | W13: 0 | X13: 6779.661 | Y13: 1553.6723 | Z13: 847.5 | AA13: 735.835 | AB13: 420.26615 | AD13: -6779.661 | AE13: =IF(AD13<0,0,AD13) -> 0 | AF13: =IF(AD13>0,0,-AD13) -> 6779.661 | AG13: 6779.661 | AH13: =M13+R13+V13 -> 10116.525
B14: =B13+1 -> 11 | C14: =AH14 -> 10116.525 | D14: =AG14 -> 6779.661 | E14: =AH14 -> 10116.525 | F14: =0.99*I14 -> 0.16122857 | G14: =1.01*I14 -> 0.16448571 | I14: 0.16285714 | K14: 0 | L14: 6779.661 | M14: 1447.7401 | N14: 0 | O14: 0 | P14: 1553.6723 | Q14: 0 | R14: 1271.1864 | S14: 0 | T14: 847.5 | U14: 0 | V14: 7397.5989 | W14: 0 | X14: 6779.661 | Y14: 1553.6723 | Z14: 847.5 | AA14: 735.835 | AB14: 420.26615 | AD14: -6779.661 | AE14: =IF(AD14<0,0,AD14) -> 0 | AF14: =IF(AD14>0,0,-AD14) -> 6779.661 | AG14: 6779.661 | AH14: =M14+R14+V14 -> 10116.525
B15: =B14+1 -> 12 | C15: =AH15 -> 10116.525 | D15: =AG15 -> 6779.661 | E15: =AH15 -> 10116.525 | F15: =0.99*I15 -> 0.16122857 | G15: =1.01*I15 -> 0.16448571 | I15: 0.16285714 | K15: 0 | L15: 6779.661 | M15: 1447.7401 | N15: 0 | O15: 0 | P15: 1521.4124 | Q15: 0 | R15: 1271.1864 | S15: 0 | T15: 847.5 | U15: 0 | V15: 7397.5989 | W15: 0 | X15: 6779.661 | Y15: 1521.4124 | Z15: 847.5 | AA15: 735.835 | AB15: 428.54402 | AD15: -6779.661 | AE15: =IF(AD15<0,0,AD15) -> 0 | AF15: =IF(AD15>0,0,-AD15) -> 6779.661 | AG15: 6779.661 | AH15: =M15+R15+V15 -> 10116.525
B16: =B15+1 -> 13 | C16: =AH16 -> 10116.525 | D16: =AG16 -> 6779.661 | E16: =AH16 -> 10116.525 | F16: =0.99*I16 -> 0.16122857 | G16: =1.01*I16 -> 0.16448571 | I16: 0.16285714 | K16: 0 | L16: 6779.661 | M16: 1447.7401 | N16: 0 | O16: 0 | P16: 504.93229 | Q16: 0 | R16: 1271.1864 | S16: 0 | T16: 847.5 | U16: 0 | V16: 7397.5989 | W16: 0 | X16: 6779.661 | Y16: 504.93229 | Z16: 847.5 | AA16: 735.835 | AB16: 436.8219 | AD16: -6779.661 | AE16: =IF(AD16<0,0,AD16) -> 0 | AF16: =IF(AD16>0,0,-AD16) -> 6779.661 | AG16: 6779.661 | AH16: =M16+R16+V16 -> 10116.525
... B171: =B170+1 -> 168 | C171: =AH171 -> 10116.525 | D171: =AG171 -> 6779.661 | E171: =AH171 -> 10116.525 | F171: =0.99*I171 -> 0.16122857 | G171: =1.01*I171 -> 0.16448571 | I171: 0.16285714 | K171: 0 | L171: 6779.661 | M171: 1447.7401 | N171: 0 | O171: 0 | P171: 244.84131 | Q171: 0 | R171: 1271.1864 | S171: 0 | T171: 847.5 | U171: 0 | V171: 7397.5989 | W171: 0 | X171: 6779.661 | Y171: 244.84131 | Z171: 847.5 | AA171: 735.835 | AB171: 463.24924 | AD171: -6779.661 | AE171: =IF(AD171<0,0,AD171) -> 0 | AF171: =IF(AD171>0,0,-AD171) -> 6779.661 | AG171: 6779.661 | AH171: =M171+R171+V171 -> 10116.525

Sheet Obtencion de Datos
A1: Capacidades Instaladas | D1: ESPAÑA | I1: PORTUGAL | L1: FRANCIA | P1: Solar ES-PT | AF1: Wind | AV1: Biomasa | BC1: Nuclear | BF1: SRES: e-market o h2 | BT1: Exportaciones desde FR00 a EU00 | CA1: Esto será la demanda que pondré en el nodo EU00. Son las exportaciones del resto de europa | CL1: Importaciones desde EU00 a FR00 | CS1: Esto será la generación que tiene que tener el nodo EU00. Son las exportaciones del resto de europa | DD1: Demandas Electricidad | DM1: Demandas Hidrógeno | DW1: Exportaciones EUh2 | EO1: Load EUh2 | EP1: Generador EUh2 | ER1: CCGT | EY1: Perfil Turbina | FF1: Perfil Pump | FV1: FRh2SW | GC1: SRES Electrolyzer | GI1: WS071 | GO1: 1492.3021
A2: Capacidades Instaladas | D2: ES00 Gas CCGT present 1 | E2: 24559.65 | F2: 21481.309 | G2: =F2/E2 -> 0.8746586 | I2: PT00 Gas CCGT present 1 | J2: 1357 | L2: FR00 Gas CCGT new | M2: 414 | P2: Horas | Q2: ES00 Solar PV Utility | R2: Perfil | S2: ES00 Solar CSP | T2: Perfil | U2: ES00RETE Solar PV Rooftop | V2: Perfil | W2: PT00 Solar PV Utility | X2: Perfil | Y2: PT00RETE Solar PV Rooftop | Z2: Perfil | AA2: FR00 Solar PV Utility | AB2: Perfil | AC2: FR00RETE Solar PV Rooftop | AD2: Perfil | AF2: Horas | AG2: ES00 Wind Onshore | AH2: ES00 Wind Offshore Radial | AI2: ES00 Wind Offshore Hub Ready | AJ2: Perfil On | AK2: Perfil Off | AL2: Perfil Hub | AM2: PT00 Wind Offshore Radial | AN2: PT00 Wind Onshore | AO2: Perfil Off | AP2: Perfil On | AQ2: FR00 Wind Onshore | AR2: FR00 Wind Offshore Radial | AS2: Perfil On | AT2: Perfil Of | AV2: ES00 Other RES | AW2: Perfil | AX2: PT00 Other RES | AY2: Perfil | AZ2: FR00 Other RES | BA2: Perfil | BC2: FR00 Nuclear | BD2: Perfil | BF2: ES00_SRES_P2G | BG2: ES00_SRES_RES_Solar | BH2: ES00_SRES_RES_Wind_Onshore | BI2: Perfil SRES to h2 | BJ2: Perfil SRES emarket | BK2: PT00_SRES_RES_Solar | BL2: PT00_SRES_RES_Wind_Offshore | BM2: PT00_SRES_RES_Wind_Onshore | BN2: PT00_SRES_P2G | BO2: Perfil SRES to h2 | BP2: Perfil SRES emarket | BQ2: FR00-FRh2-P2G_emarket - generation | BR2: FR00-FRh2SW-P2G_emarket - generation | BT2: FR00-IE00 | BU2: FR00-IE00 | BV2: FR00-ITN1 | BW2: FR00-ITN1 | BX2: FR00-LUF1 | BY2: FR00-ITN1 | BZ2: FR00-UK00 | CA2: FR00-ITN1 | CB2: BE00-FR00 | CC2: FR00-ITN1 | CD2: CH00-FR00 | CE2: FR00-ITN1 | CF2: DE00-FR00 | CG2: FR00-ITN1 | CH2: FR00-FR00RETE | CI2: FR00-ITN1 | CJ2: Exportaciones FR00 | CL2: FR00-IE00 | CM2: FR00-IE00 | CN2: FR00-ITN1 | CO2: FR00-ITN1 | CP2: FR00-LUF1 | CQ2: FR00-ITN1 | CR2: FR00-UK00 | CS2: FR00-ITN1 | CT2: BE00-FR00 | CU2: FR00-ITN1 | CV2: CH00-FR00 | CW2: FR00-ITN1 | CX2: DE00-FR00 | CY2: FR00-ITN1 | CZ2: FR00-FR00RETE | DA2: FR00-ITN1 | DB2: Importaciones FR00 | DD2: ES00 Native Demand [MW_e] | DE2: ES00 Fixed Demand [MW_e] | DF2: ES00RETE Native Demand [MW_e] | DG2: ES00_demand | DH2: PT00 Native Demand | DI2: FR00 Native Demand [MW_e] | DJ2: Native Demand FR00RETE | DK2: FR00_demand | DM2: ESh2 H2 Heat Demand [GJ] | DN2: ESh2 Native Demand [MW_H2] | DO2: ESh2 Demand | DP2: PTh2 Native Demand | DQ2: FRh2 Native Demand | DR2: FRh2-e-liquids | DS2: FRh2_demand | DT2: FRh2S Native Demand [MW_H2] | DU2: FRh2SW Native Demand [MW_H2] | DW2: FRh2-FRh2S | DX2: FRh2S-FRh2 | DY2: FRh2-LUh2 | DZ2: LUh2-FRh2 | EA2: FRh2S-FRh2SW | EB2: FRh2SW-FRh2S | EC2: BEh2-FRh2 | ED2: FRh2-BEh2 | EE2: BEh2-FRh2N | EF2: FRh2N-BEh2 | EG2: DEh2-FRh2 | EH2: FRh2-DEh2 | EI2: FRh2-FRh2S | EJ2: FRh2S-FRh2 | EK2: FRh2SW-FRh2S | EL2: Ammonia_FRN-FRh2N | EM2: Ammonia_FRSW-FRh2SW | EN2: FRh2-e-liquids | EO2: Exportaciones EUh2 | EP2: Importaciones EU a FRh2 | ER2: Others non Renewables | ES2: Generado TYNDP CCGT ES | ET2: Perfil Gas ES | EU2: PT00 Gas CCGT present 1 | EV2: Others non-renewable [MW_e] | EW2: Perfil Gas PT | EY2: ES00 PS Closed | EZ2: ES00 PS Open | FA2: Perfil ES | FB2: Pump Storage - Open Loop (turbine) [MW_e] | FC2: Perfil PT | FF2: ES00 PS Open Pump | FG2: ES00 PS Closed Pump | FH2: Perfil ES | FI2: Pump Storage - Open Loop (pump) [MW_e] | FJ2: Perfil PT | FL2: Reservoir | FM2: Perfil ES | FN2: PT00 Reservoir | FO2: Perfil PT | FQ2: Pondage | FR2: PT00 Run of River | FS2: Perfil | FT2: Suma RoR y Pondage | FV2: FRh2SW Generation | FW2: FRh2SW-FRh2S | FX2: Load FRh2SW_storage | FY2: Generation FRh2SW Storage | FZ2: Perfil | GA2: Irún Larrao | GC2: Modelo Objetivo | GD2: Perfil ES | GE2: Modelo Objetivo | GF2: Perfil PT | GH2: 10455.164 | GI2: 1409.6684 | GK2: ES_ccgt_profile | GL2: PT_ccgt_profile | GN2: ESh2-MA | GR2: ES | GS2: PT
A3: ES Solar PV Utility | B3: 83000 | D3: ES00 Other nonRES 1 | E3: 4207.028 | I3: PT00 Other nonRES 1 | J3: 468.996 | L3: FR00 Nuclear | M3: 69619.971 | P3: 1 | Q3: 0 | R3: 0 | S3: 0 | T3: 0 | U3: 0 | V3: 0 | W3: 0 | X3: 0 | Y3: 0 | Z3: 0 | AA3: 0 | AB3: 0 | AC3: 0 | AD3: 0 | AF3: 1 | AG3: 24474.945 | AH3: 1267.3 | AI3: 275.5 | AJ3: 0.275 | AK3: 0.551 | AL3: 0.551 | AM3: 85.272 | AN3: 1385.5884 | AO3: 0.132 | AP3: 0.119 | AQ3: 15208.6 | AR3: 13568.55 | AS3: 0.341 | AT3: 0.578 | AV3: 662.456 | AW3: 0.26900019 | AX3: 863.942 | AY3: 0.5376117 | AZ3: 1121.478 | BA3: 0.57843924 | BC3: 51358.995 | BD3: 0.73770492 | BF3: 10455.164 | BG3: 0 | BH3: 0 | BI3: 0.32071055 | BJ3: 0 | BK3: 0 | BL3: 0 | BM3: 0 | BN3: 1409.668 | BO3: 0.1045903 | BP3: 0 | BQ3: 7668 | BR3: 648.91952 | BT3: -700 | BU3: 0 | BV3: 4485 | BW3: 4485 | BX3: 0 | BY3: 0 | BZ3: -5000 | CA3: 0 | CB3: -716.91477 | CC3: 0 | CD3: -4000 | CE3: 0 | CF3: 4800 | CG3: 4800 | CH3: 14492.933 | CI3: 14492.933 | CJ3: 23777.933 | CL3: -700 | CM3: 700 | CN3: 4485 | CO3: 0 | CP3: 0 | CQ3: 0 | CR3: -5000 | CS3: 5000 | CT3: -716.91477 | CU3: 716.91477 | CV3: -4000 | CW3: 4000 | CX3: 4800 | CY3: 0 | CZ3: 14492.933 | DA3: 0 | DB3: 10416.915 | DD3: 29610.763 | DE3: 2130.936 | DF3: 1169.3201 | DG3: 32911.019 | DH3: 7726.718 | DI3: 52192.411 | DJ3: 6163 | DK3: 58355.411 | DM3: 719.888 | DN3: 10493.066 | DO3: 11212.954 | DP3: 1194.7295 | DQ3: 2899.4801 | DR3: 461.65552 | DS3: 3361.1356 | DT3: 161.08223 | DU3: 161.08223 | DW3: 0 | DX3: 6779.661 | DY3: 1447.7401 | DZ3: 0 | EA3: 0 | EB3: 1553.6723 | EC3: 0 | ED3: 1271.1864 | EE3: 0 | EF3: 847.5 | EG3: 0 | EH3: 7397.5989 | EI3: 0 | EJ3: 6779.661 | EK3: 1553.6723 | EL3: 847.5 | EM3: 735.835 | EN3: 461.65552 | EO3: 10964.025 | EP3: 0 | ER3: 0 | ES3: 0 | ET3: =(ES3+ER3)/($E$2+$E$3) -> 0 | EU3: 0 | EV3: 0 | EW3: =(EU3+EV3)/($J$2+$J$3) -> 0 | EY3: 0 | EZ3: 3156.57 | FA3: =(EY3+EZ3)/($E$12+$E$14) -> 0.23203283 | FB3: 4613 | FC3: =FB3/$J$10 -> 1 | FF3: 0 | FG3: 0 | FH3: =(FF3+FG3)/($E$13+$E$15) -> 0 | FI3: 0 | FJ3: =FI3/$J$11 -> 0 | FL3: 7873 | FM3: =FL3/$E$11 -> 0.68245451 | FN3: 2591 | FO3: =FN3/$J$9 -> 0.82634349 | FQ3: 0 | FR3: 367.01 | FS3: =(FQ3+FR3)/($J$8+$J$12) -> 0.46568963 | FT3: =FQ3+FR3 -> 367.01 | FV3: =FW3+FX3-FY3-GA3 -> 1223.6723 | FW3: 1553.6723 | FX3: 0 | FY3: 330 | FZ3: =FV3/1553.6723 -> 0.78759999 | GA3: 0 | GC3: 7423.1664 | GD3: =GC3/32600 -> 0.22770449 | GE3: 1000.8643 | GF3: =GE3/13478 -> 0.07425911 | GH3: 11188.317 | GI3: 1295.2331 | GK3: 0.257 | GL3: 0.84 | GM3: =-GN3 -> 2618.1494 | GN3: -2618.1494 | GO3: =GM3-1517.77579117 -> 1100.3736 | GP3: =GO3/1492.3021 -> 0.73736651 | GR3: WS071 | GS3: WS071 | GV3: 3776.591 | GW3: 1100.3736 | GX3: =MAX(GW:GW) -> 1537.0311 | GY3: =GW3/GX3 -> 0.71590848
A4: ES Solar CSP | B4: 4805 | D4: ES00 Wind Onshore | E4: 88999.8 | F4: 78853.823 | G4: =F4/E4 -> 0.886 | I4: PT00 Wind Onshore | J4: 11643.6 | L4: FR00 Other nonRES 1 | M4: 1390 | P4: 2 | Q4: 0 | R4: 0 | S4: 0 | T4: 0 | U4: 0 | V4: 0 | W4: 0 | X4: 0 | Y4: 0 | Z4: 0 | AA4: 0 | AB4: 0 | AC4: 0 | AD4: 0 | AF4: 2 | AG4: 26165.941 | AH4: 1400.7 | AI4: 304.5 | AJ4: 0.294 | AK4: 0.609 | AL4: 0.609 | AM4: 76.228 | AN4: 1455.45 | AO4: 0.118 | AP4: 0.125 | AQ4: 16591.2 | AR4: 16127.325 | AS4: 0.372 | AT4: 0.687 | AV4: 657.53 | AW4: 0.26699991 | AX4: 857.852 | AY4: 0.53382203 | AZ4: 1121.478 | BA4: 0.57843924 | BC4: 51358.995 | BD4: 0.73770492 | BF4: 11188.317 | BG4: 0 | BH4: 0 | BI4: 0.34319991 | BJ4: 0 | BK4: 0 | BL4: 0 | BM4: 0 | BN4: 1295.233 | BO4: 0.096099792 | BP4: 0 | BQ4: 7668 | BR4: 648.91952 | BT4: -700 | BU4: 0 | BV4: 4485 | BW4: 4485 | BX4: 0 | BY4: 0 | BZ4: -5000 | CA4: 0 | CB4: 0 | CC4: 0 | CD4: -4000 | CE4: 0 | CF4: 4800 | CG4: 4800 | CH4: 10757.922 | CI4: 10757.922 | CJ4: 20042.922 | CL4: -700 | CM4: 700 | CN4: 4485 | CO4: 0 | CP4: 0 | CQ4: 0 | CR4: -5000 | CS4: 5000 | CT4: 0 | CU4: 0 | CV4: -4000 | CW4: 4000 | CX4: 4800 | CY4: 0 | CZ4: 10757.922 | DA4: 0 | DB4: 9700 | DD4: 28009.474 | DE4: 2090.089 | DF4: 888.6679 | DG4: 30988.231 | DH4: 7402.483 | DI4: 51263.411 | DJ4: 6232 | DK4: 57495.411 | DM4: 744.829 | DN4: 10493.066 | DO4: 11237.895 | DP4: 1194.7295 | DQ4: 2899.4801 | DR4: 461.65552 | DS4: 3361.1356 | DT4: 161.08223 | DU4: 161.08223 | DW4: 0 | DX4: 6779.661 | DY4: 1447.7401 | DZ4: 0 | EA4: 0 | EB4: 1553.6723 | EC4: 0 | ED4: 1271.1864 | EE4: 0 | EF4: 847.5 | EG4: 0 | EH4: 7397.5989 | EI4: 0 | EJ4: 6779.661 | EK4: 1553.6723 | EL4: 847.5 | EM4: 735.835 | EN4: 461.65552 | EO4: 10964.025 | EP4: 0 | ER4: 0 | ES4: 0 | ET4: =(ES4+ER4)/($E$2+$E$3) -> 0 | EU4: 0 | EV4: 0 | EW4: =(EU4+EV4)/($J$2+$J$3) -> 0 | EY4: 0 | EZ4: 3156.57 | FA4: =(EY4+EZ4)/($E$12+$E$14) -> 0.23203283 | FB4: 4613 | FC4: =FB4/$J$10 -> 1 | FF4: 0 | FG4: 6233.0945 | FH4: =(FF4+FG4)/($E$13+$E$15) -> 0.46792369 | FI4: 0 | FJ4: =FI4/$J$11 -> 0 | FL4: 7873 | FM4: =FL4/$E$11 -> 0.68245451 | FN4: 2591 | FO4: =FN4/$J$9 -> 0.82634349 | FQ4: 278 | FR4: 367.01 | FS4: =(FQ4+FR4)/($J$8+$J$12) -> 0.81843675 | FT4: =FQ4+FR4 -> 645.01 | FV4: =FW4+FX4-FY4-GA4 -> 1223.6723 | FW4: 1553.6723 | FX4: 0 | FY4: 330 | FZ4: =FV4/1553.6723 -> 0.78759999 | GA4: 0 | GC4: 7943.7051 | GD4: =GC4/32600 -> 0.24367193 | GE4: 919.61543 | GF4: =GE4/13478 -> 0.068230853 | GH4: 11379.209 | GI4: 1219.3706 | GK4: 0.257 | GL4: 0.84 | GM4: =-GN4 -> 2618.1494 | GN4: -2618.1494 | GO4: =GM4-1517.77579117 -> 1100.3736 | GP4: =GO4/1492.3021 -> 0.73736651 | GR4: 10455.164 | GS4: 1409.6684 | GV4: 3776.591 | GW4: 1100.3736 | GX4: =MAX(GW:GW) -> 1537.0311 | GY4: =GW4/GX4 -> 0.71590848
A5: ES Solar Rooftop | B5: 30000 | D5: ES00 Solar PV Utility | E5: 83000 | I5: PT00 Solar PV Utility | J5: 14378.2 | L5: FR00 Wind Onshore | M5: 44600 | P5: 3 | Q5: 0 | R5: 0 | S5: 0 | T5: 0 | U5: 0 | V5: 0 | W5: 0 | X5: 0 | Y5: 0 | Z5: 0 | AA5: 0 | AB5: 0 | AC5: 0 | AD5: 0 | AF5: 3 | AG5: 26610.94 | AH5: 1465.1 | AI5: 318.5 | AJ5: 0.299 | AK5: 0.637 | AL5: 0.637 | AM5: 71.06 | AN5: 1595.1732 | AO5: 0.11 | AP5: 0.137 | AQ5: 18375.2 | AR5: 17653.2 | AS5: 0.412 | AT5: 0.752 | AV5: 652.605 | AW5: 0.26500004 | AX5: 856.538 | AY5: 0.53300436 | AZ5: 1121.478 | BA5: 0.57843924 | BC5: 51358.995 | BD5: 0.73770492 | BF5: 11379.209 | BG5: 0 | BH5: 0 | BI5: 0.34905549 | BJ5: 0 | BK5: 0 | BL5: 0 | BM5: 0 | BN5: 1219.371 | BO5: 0.090471212 | BP5: 0 | BQ5: 7668 | BR5: 648.91952 | BT5: -700 | BU5: 0 | BV5: 4485 | BW5: 4485 | BX5: 0 | BY5: 0 | BZ5: -5000 | CA5: 0 | CB5: -2222.619 | CC5: 0 | CD5: -4000 | CE5: 0 | CF5: 4800 | CG5: 4800 | CH5: 10279.41 | CI5: 10279.41 | CJ5: 19564.41 | CL5: -700 | CM5: 700 | CN5: 4485 | CO5: 0 | CP5: 0 | CQ5: 0 | CR5: -5000 | CS5: 5000 | CT5: -2222.619 | CU5: 2222.619 | CV5: -4000 | CW5: 4000 | CX5: 4800 | CY5: 0 | CZ5: 10279.41 | DA5: 0 | DB5: 11922.619 | DD5: 26842.165 | DE5: 2042.995 | DF5: 1460.145 | DG5: 30345.305 | DH5: 7034.883 | DI5: 49580.411 | DJ5: 6311 | DK5: 55891.411 | DM5: 804.373 | DN5: 10493.066 | DO5: 11297.439 | DP5: 1194.7295 | DQ5: 2899.4801 | DR5: 461.65552 | DS5: 3361.1356 | DT5: 161.08223 | DU5: 161.08223 | DW5: 0 | DX5: 6779.661 | DY5: 1447.7401 | DZ5: 0 | EA5: 0 | EB5: 1553.6723 | EC5: 0 | ED5: 1271.1864 | EE5: 0 | EF5: 847.5 | EG5: 0 | EH5: 7397.5989 | EI5: 0 | EJ5: 6779.661 | EK5: 1553.6723 | EL5: 847.5 | EM5: 735.835 | EN5: 461.65552 | EO5: 10964.025 | EP5: 0 | ER5: 0 | ES5: 0 | ET5: =(ES5+ER5)/($E$2+$E$3) -> 0 | EU5: 0 | EV5: 0 | EW5: =(EU5+EV5)/($J$2+$J$3) -> 0 | EY5: 0 | EZ5: 3156.57 | FA5: =(EY5+EZ5)/($E$12+$E$14) -> 0.23203283 | FB5: 4613 | FC5: =FB5/$J$10 -> 1 | FF5: 0 | FG5: 2389.7804 | FH5: =(FF5+FG5)/($E$13+$E$15) -> 0.17940284 | FI5: 0 | FJ5: =FI5/$J$11 -> 0 | FL5: 7873 | FM5: =FL5/$E$11 -> 0.68245451 | FN5: 2591 | FO5: =FN5/$J$9 -> 0.82634349 | FQ5: 0 | FR5: 367.01 | FS5: =(FQ5+FR5)/($J$8+$J$12) -> 0.46568963 | FT5: =FQ5+FR5 -> 367.01 | FV5: =FW5+FX5-FY5-GA5 -> 1223.6723 | FW5: 1553.6723 | FX5: 0 | FY5: 330 | FZ5: =FV5/1553.6723 -> 0.78759999 | GA5: 0 | GC5: 8079.2384 | GD5: =GC5/32600 -> 0.2478294 | GE5: 865.75341 | GF5: =GE5/13478 -> 0.064234561 | GH5: 11664.809 | GI5: 1148.3197 | GK5: 0.257 | GL5: 0.84 | GM5: =-GN5 -> 2618.1494 | GN5: -2618.1494 | GO5: =GM5-1517.77579117 -> 1100.3736 | GP5: =GO5/1492.3021 -> 0.73736651 | GR5: 11188.317 | GS5: 1295.2331 | GV5: 3776.591 | GW5: 1100.3736 | GX5: =MAX(GW:GW) -> 1537.0311 | GY5: =GW5/GX5 -> 0.71590848
A6: PT Solar PV Utility | B6: 14378.2 | D6: ES00 Wind Offshore Radial | E6: 2300 | I6: PT00 Wind Offshore Radial | J6: 646 | L6: FR00 Solar PV Utility | M6: 51420 | P6: 4 | Q6: 0 | R6: 0 | S6: 0 | T6: 0 | U6: 0 | V6: 0 | W6: 0 | X6: 0 | Y6: 0 | Z6: 0 | AA6: 0 | AB6: 0 | AC6: 0 | AD6: 0 | AF6: 4 | AG6: 27322.939 | AH6: 1460.5 | AI6: 317.5 | AJ6: 0.307 | AK6: 0.635 | AL6: 0.635 | AM6: 67.83 | AN6: 1781.4708 | AO6: 0.105 | AP6: 0.153 | AQ6: 19534.8 | AR6: 18404.4 | AS6: 0.438 | AT6: 0.784 | AV6: 677.231 | AW6: 0.2749998 | AX6: 866.279 | AY6: 0.53906596 | AZ6: 1121.478 | BA6: 0.57843924 | BC6: 51358.995 | BD6: 0.73770492 | BF6: 11664.809 | BG6: 0 | BH6: 0 | BI6: 0.35781623 | BJ6: 0 | BK6: 0 | BL6: 0 | BM6: 0 | BN6: 1148.32 | BO6: 0.085199585 | BP6: 0 | BQ6: 7668 | BR6: 648.91952 | BT6: -700 | BU6: 0 | BV6: 4485 | BW6: 4485 | BX6: 0 | BY6: 0 | BZ6: -5000 | CA6: 0 | CB6: -1446.1603 | CC6: 0 | CD6: -4000 | CE6: 0 | CF6: 4800 | CG6: 4800 | CH6: 13335.643 | CI6: 13335.643 | CJ6: 22620.643 | CL6: -700 | CM6: 700 | CN6: 4485 | CO6: 0 | CP6: 0 | CQ6: 0 | CR6: -5000 | CS6: 5000 | CT6: -1446.1603 | CU6: 1446.1603 | CV6: -4000 | CW6: 4000 | CX6: 4800 | CY6: 0 | CZ6: 13335.643 | DA6: 0 | DB6: 11146.16 | DD6: 26274.437 | DE6: 2003.629 | DF6: 2313.9328 | DG6: 30591.999 | DH6: 6846.224 | DI6: 47905.411 | DJ6: 6196 | DK6: 54101.411 | DM6: 892.909 | DN6: 10493.066 | DO6: 11385.975 | DP6: 1194.7295 | DQ6: 2899.4801 | DR6: 461.65552 | DS6: 3361.1356 | DT6: 161.08223 | DU6: 161.08223 | DW6: 0 | DX6: 6779.661 | DY6: 1447.7401 | DZ6: 0 | EA6: 0 | EB6: 1553.6723 | EC6: 0 | ED6: 1271.1864 | EE6: 0 | EF6: 847.5 | EG6: 0 | EH6: 7397.5989 | EI6: 0 | EJ6: 6779.661 | EK6: 1553.6723 | EL6: 847.5 | EM6: 735.835 | EN6: 461.65552 | EO6: 10964.025 | EP6: 0 | ER6: 0 | ES6: 0 | ET6: =(ES6+ER6)/($E$2+$E$3) -> 0 | EU6: 0 | EV6: 0 | EW6: =(EU6+EV6)/($J$2+$J$3) -> 0 | EY6: 0 | EZ6: 3156.57 | FA6: =(EY6+EZ6)/($E$12+$E$14) -> 0.23203283 | FB6: 4613 | FC6: =FB6/$J$10 -> 1 | FF6: 0 | FG6: 1486.2996 | FH6: =(FF6+FG6)/($E$13+$E$15) -> 0.11157777 | FI6: 0 | FJ6: =FI6/$J$11 -> 0 | FL6: 7873 | FM6: =FL6/$E$11 -> 0.68245451 | FN6: 2591 | FO6: =FN6/$J$9 -> 0.82634349 | FQ6: 278 | FR6: 367.01 | FS6: =(FQ6+FR6)/($J$8+$J$12) -> 0.81843675 | FT6: =FQ6+FR6 -> 645.01 | FV6: =FW6+FX6-FY6-GA6 -> 1223.6723 | FW6: 1553.6723 | FX6: 0 | FY6: 330 | FZ6: =FV6/1553.6723 -> 0.78759999 | GA6: 0 | GC6: 8282.0144 | GD6: =GC6/32600 -> 0.25404952 | GE6: 815.3072 | GF6: =GE6/13478 -> 0.060491705 | GH6: 12228.817 | GI6: 1097.6028 | GK6: 0.257 | GL6: 0.84 | GM6: =-GN6 -> 2618.1494 | GN6: -2618.1494 | GO6: =GM6-1517.77579117 -> 1100.3736 | GP6: =GO6/1492.3021 -> 0.73736651 | GR6: 11379.209 | GS6: 1219.3706 | GV6: 3776.591 | GW6: 1100.3736 | GX6: =MAX(GW:GW) -> 1537.0311 | GY6: =GW6/GX6 -> 0.71590848
A7: PT Solar Rooftop | B7: 9659.9 | D7: ES00 Wind Offshore Hub Ready | E7: 500 | I7: PT00 Other RES | J7: 1607 | L7: FR00 Wind Offshore Radial | M7: 23475 | P7: 5 | Q7: 0 | R7: 0 | S7: 0 | T7: 0 | U7: 0 | V7: 0 | W7: 0 | X7: 0 | Y7: 0 | Z7: 0 | AA7: 0 | AB7: 0 | AC7: 0 | AD7: 0 | AF7: 5 | AG7: 28657.936 | AH7: 1428.3 | AI7: 310.5 | AJ7: 0.322 | AK7: 0.621 | AL7: 0.621 | AM7: 65.246 | AN7: 1944.4812 | AO7: 0.101 | AP7: 0.167 | AQ7: 20560.6 | AR7: 19132.125 | AS7: 0.461 | AT7: 0.815 | AV7: 687.082 | AW7: 0.27899994 | AX7: 871.284 | AY7: 0.54218046 | AZ7: 1121.478 | BA7: 0.57843924 | BC7: 51358.995 | BD7: 0.73770492 | BF7: 12228.817 | BG7: 0 | BH7: 0 | BI7: 0.37511709 | BJ7: 0 | BK7: 0 | BL7: 0 | BM7: 0 | BN7: 1097.603 | BO7: 0.081436637 | BP7: 0 | BQ7: 7668 | BR7: 649.3794 | BT7: -700 | BU7: 0 | BV7: 4485 | BW7: 4485 | BX7: 0 | BY7: 0 | BZ7: -5000 | CA7: 0 | CB7: -2137.9981 | CC7: 0 | CD7: -4000 | CE7: 0 | CF7: 4800 | CG7: 4800 | CH7: 12475.322 | CI7: 12475.322 | CJ7: 21760.322 | CL7: -700 | CM7: 700 | CN7: 4485 | CO7: 0 | CP7: 0 | CQ7: 0 | CR7: -5000 | CS7: 5000 | CT7: -2137.9981 | CU7: 2137.9981 | CV7: -4000 | CW7: 4000 | CX7: 4800 | CY7: 0 | CZ7: 12475.322 | DA7: 0 | DB7: 11837.998 | DD7: 26537.633 | DE7: 1976.586 | DF7: 2602.5462 | DG7: 31116.765 | DH7: 6811.541 | DI7: 47372.411 | DJ7: 6255 | DK7: 53627.411 | DM7: 1053.763 | DN7: 10508.776 | DO7: 11562.539 | DP7: 1194.7295 | DQ7: 2907.758 | DR7: 453.37765 | DS7: 3361.1356 | DT7: 161.54211 | DU7: 161.54211 | DW7: 0 | DX7: 6779.661 | DY7: 1447.7401 | DZ7: 0 | EA7: 0 | EB7: 1553.6723 | EC7: 0 | ED7: 1271.1864 | EE7: 0 | EF7: 847.5 | EG7: 0 | EH7: 7397.5989 | EI7: 0 | EJ7: 6779.661 | EK7: 1553.6723 | EL7: 847.5 | EM7: 735.835 | EN7: 453.37765 | EO7: 10964.025 | EP7: 0 | ER7: 0 | ES7: 0 | ET7: =(ES7+ER7)/($E$2+$E$3) -> 0 | EU7: 0 | EV7: 0 | EW7: =(EU7+EV7)/($J$2+$J$3) -> 0 | EY7: 0 | EZ7: 3156.57 | FA7: =(EY7+EZ7)/($E$12+$E$14) -> 0.23203283 | FB7: 4613 | FC7: =FB7/$J$10 -> 1 | FF7: 0 | FG7: 7040.3117 | FH7: =(FF7+FG7)/($E$13+$E$15) -> 0.52852217 | FI7: 0 | FJ7: =FI7/$J$11 -> 0 | FL7: 7873 | FM7: =FL7/$E$11 -> 0.68245451 | FN7: 2591 | FO7: =FN7/$J$9 -> 0.82634349 | FQ7: 0 | FR7: 367.01 | FS7: =(FQ7+FR7)/($J$8+$J$12) -> 0.46568963 | FT7: =FQ7+FR7 -> 367.01 | FV7: =FW7+FX7-FY7-GA7 -> 1223.6723 | FW7: 1553.6723 | FX7: 0 | FY7: 330 | FZ7: =FV7/1553.6723 -> 0.78759999 | GA7: 0 | GC7: 8682.4601 | GD7: =GC7/32600 -> 0.26633313 | GE7: 779.29813 | GF7: =GE7/13478 -> 0.057820013 | GH7: 12302.136 | GI7: 1069.2209 | GK7: 0.257 | GL7: 0.84 | GM7: =-GN7 -> 2618.1494 | GN7: -2618.1494 | GO7: =GM7-1517.77579117 -> 1100.3736 | GP7: =GO7/1492.3021 -> 0.73736651 | GR7: 11664.809 | GS7: 1148.3197 | GV7: 3776.591 | GW7: 1100.3736 | GX7: =MAX(GW:GW) -> 1537.0311 | GY7: =GW7/GX7 -> 0.71590848
A8: PT00 Wind Onshore | B8: 11643.6 | D8: ES00 Solar CSP | E8: 4805 | I8: PT00 Run of River | J8: 508.3 | L8: FR00 Other RES | M8: 1938.8 | P8: 6 | Q8: 0 | R8: 0 | S8: 0 | T8: 0 | U8: 0 | V8: 0 | W8: 0 | X8: 0 | Y8: 0 | Z8: 0 | AA8: 0 | AB8: 0 | AC8: 0 | AD8: 0 | AF8: 6 | AG8: 28835.935 | AH8: 1393.8 | AI8: 303 | AJ8: 0.324 | AK8: 0.606 | AL8: 0.606 | AM8: 62.662 | AN8: 2072.5608 | AO8: 0.097 | AP8: 0.178 | AQ8: 21363.4 | AR8: 19578.15 | AS8: 0.479 | AT8: 0.834 | AV8: 716.634 | AW8: 0.29099998 | AX8: 890.922 | AY8: 0.55440075 | AZ8: 1121.478 | BA8: 0.57843924 | BC8: 51358.995 | BD8: 0.73770492 | BF8: 12302.136 | BG8: 0 | BH8: 0 | BI8: 0.37736613 | BJ8: 0 | BK8: 0 | BL8: 0 | BM8: 0 | BN8: 1069.221 | BO8: 0.079330835 | BP8: 0 | BQ8: 7668 | BR8: 650.29917 | BT8: -700 | BU8: 0 | BV8: 4485 | BW8: 4485 | BX8: 0 | BY8: 0 | BZ8: -5000 | CA8: 0 | CB8: 0 | CC8: 0 | CD8: -4000 | CE8: 0 | CF8: 4800 | CG8: 4800 | CH8: 16766.796 | CI8: 16766.796 | CJ8: 26051.796 | CL8: -700 | CM8: 700 | CN8: 4485 | CO8: 0 | CP8: 0 | CQ8: 0 | CR8: -5000 | CS8: 5000 | CT8: 0 | CU8: 0 | CV8: -4000 | CW8: 4000 | CX8: 4800 | CY8: 0 | CZ8: 16766.796 | DA8: 0 | DB8: 9700 | DD8: 27552.059 | DE8: 1965.631 | DF8: 2801.3606 | DG8: 32319.051 | DH8: 6946.607 | DI8: 47878.411 | DJ8: 6340 | DK8: 54218.411 | DM8: 1230.726 | DN8: 10540.196 | DO8: 11770.922 | DP8: 1292.686 | DQ8: 2924.3137 | DR8: 436.8219 | DS8: 3361.1356 | DT8: 162.46187 | DU8: 162.46187 | DW8: 0 | DX8: 6779.661 | DY8: 1447.7401 | DZ8: 0 | EA8: 0 | EB8: 1553.6723 | EC8: 0 | ED8: 1271.1864 | EE8: 0 | EF8: 847.5 | EG8: 0 | EH8: 7397.5989 | EI8: 0 | EJ8: 6779.661 | EK8: 1553.6723 | EL8: 847.5 | EM8: 735.835 | EN8: 436.8219 | EO8: 10964.025 | EP8: 0 | ER8: 0 | ES8: 0 | ET8: =(ES8+ER8)/($E$2+$E$3) -> 0 | EU8: 0 | EV8: 0 | EW8: =(EU8+EV8)/($J$2+$J$3) -> 0 | EY8: 0 | EZ8: 3156.57 | FA8: =(EY8+EZ8)/($E$12+$E$14) -> 0.23203283 | FB8: 4613 | FC8: =FB8/$J$10 -> 1 | FF8: 0 | FG8: 10423.35 | FH8: =(FF8+FG8)/($E$13+$E$15) -> 0.78248972 | FI8: 0 | FJ8: =FI8/$J$11 -> 0 | FL8: 7873 | FM8: =FL8/$E$11 -> 0.68245451 | FN8: 2591 | FO8: =FN8/$J$9 -> 0.82634349 | FQ8: 278 | FR8: 367.01 | FS8: =(FQ8+FR8)/($J$8+$J$12) -> 0.81843675 | FT8: =FQ8+FR8 -> 645.01 | FV8: =FW8+FX8-FY8-GA8 -> 1223.6723 | FW8: 1553.6723 | FX8: 0 | FY8: 330 | FZ8: =FV8/1553.6723 -> 0.78759999 | GA8: 0 | GC8: 8734.5166 | GD8: =GC8/32600 -> 0.26792996 | GE8: 759.14691 | GF8: =GE8/13478 -> 0.056324893 | GH8: 11503.818 | GI8: 1034.4002 | GK8: 0.257 | GL8: 0.84 | GM8: =-GN8 -> 2618.1494 | GN8: -2618.1494 | GO8: =GM8-1517.77579117 -> 1100.3736 | GP8: =GO8/1492.3021 -> 0.73736651 | GR8: 12228.817 | GS8: 1097.6028 | GV8: 3776.591 | GW8: 1100.3736 | GX8: =MAX(GW:GW) -> 1537.0311 | GY8: =GW8/GX8 -> 0.71590848
A9: PT00 Wind Offshore Radial | B9: 0 | D9: ES00 Other RES | E9: 2462.66 | I9: PT00 Reservoir | J9: 3135.5 | L9: FR00 Run of River | M9: 11600 | P9: 7 | Q9: 0 | R9: 0 | S9: 0 | T9: 0 | U9: 0 | V9: 0 | W9: 0 | X9: 0 | Y9: 0 | Z9: 0 | AA9: 0 | AB9: 0 | AC9: 0 | AD9: 0 | AF9: 7 | AG9: 26966.939 | AH9: 1324.8 | AI9: 288 | AJ9: 0.303 | AK9: 0.576 | AL9: 0.576 | AM9: 59.432 | AN9: 2130.7788 | AO9: 0.092 | AP9: 0.183 | AQ9: 21809.4 | AR9: 19742.475 | AS9: 0.489 | AT9: 0.841 | AV9: 807.752 | AW9: 0.32799981 | AX9: 907.654 | AY9: 0.56481269 | AZ9: 1121.478 | BA9: 0.57843924 | BC9: 51358.995 | BD9: 0.73770492 | BF9: 11503.818 | BG9: 0 | BH9: 0 | BI9: 0.35287785 | BJ9: 0 | BK9: 0 | BL9: 0 | BM9: 0 | BN9: 1034.4 | BO9: 0.076747292 | BP9: 0 | BQ9: 7668 | BR9: 650.75905 | BT9: -700 | BU9: 0 | BV9: 4485 | BW9: 4485 | BX9: 0 | BY9: 0 | BZ9: -5000 | CA9: 0 | CB9: -1692.9681 | CC9: 0 | CD9: -4000 | CE9: 0 | CF9: 4800 | CG9: 4800 | CH9: 11390.799 | CI9: 11390.799 | CJ9: 20675.799 | CL9: -700 | CM9: 700 | CN9: 4485 | CO9: 0 | CP9: 0 | CQ9: 0 | CR9: -5000 | CS9: 5000 | CT9: -1692.9681 | CU9: 1692.9681 | CV9: -4000 | CW9: 4000 | CX9: 4800 | CY9: 0 | CZ9: 11390.799 | DA9: 0 | DB9: 11392.968 | DD9: 29332.198 | DE9: 1971.125 | DF9: 3547.0086 | DG9: 34850.332 | DH9: 7154.418 | DI9: 48168.411 | DJ9: 6425 | DK9: 54593.411 | DM9: 1295.18 | DN9: 10555.906 | DO9: 11851.086 | DP9: 1390.6425 | DQ9: 2932.5916 | DR9: 428.54402 | DS9: 3361.1356 | DT9: 162.92176 | DU9: 162.92176 | DW9: 0 | DX9: 6779.661 | DY9: 1447.7401 | DZ9: 0 | EA9: 0 | EB9: 1553.6723 | EC9: 0 | ED9: 1271.1864 | EE9: 0 | EF9: 847.5 | EG9: 0 | EH9: 7397.5989 | EI9: 0 | EJ9: 6779.661 | EK9: 1553.6723 | EL9: 847.5 | EM9: 735.835 | EN9: 428.54402 | EO9: 10964.025 | EP9: 0 | ER9: 0 | ES9: 0 | ET9: =(ES9+ER9)/($E$2+$E$3) -> 0 | EU9: 0 | EV9: 0 | EW9: =(EU9+EV9)/($J$2+$J$3) -> 0 | EY9: 0 | EZ9: 3156.57 | FA9: =(EY9+EZ9)/($E$12+$E$14) -> 0.23203283 | FB9: 4613 | FC9: =FB9/$J$10 -> 1 | FF9: 0 | FG9: 8697.2256 | FH9: =(FF9+FG9)/($E$13+$E$15) -> 0.6529081 | FI9: 0 | FJ9: =FI9/$J$11 -> 0 | FL9: 7873 | FM9: =FL9/$E$11 -> 0.68245451 | FN9: 2591 | FO9: =FN9/$J$9 -> 0.82634349 | FQ9: 0 | FR9: 367.01 | FS9: =(FQ9+FR9)/($J$8+$J$12) -> 0.46568963 | FT9: =FQ9+FR9 -> 367.01 | FV9: =FW9+FX9-FY9-GA9 -> 1223.6723 | FW9: 1553.6723 | FX9: 0 | FY9: 330 | FZ9: =FV9/1553.6723 -> 0.78759999 | GA9: 0 | GC9: 8167.7108 | GD9: =GC9/32600 -> 0.25054328 | GE9: 734.424 | GF9: =GE9/13478 -> 0.054490577 | GH9: 9322.5865 | GI9: 1038.8148 | GK9: 0.257 | GL9: 0.84 | GM9: =-GN9 -> 2618.1494 | GN9: -2618.1494 | GO9: =GM9-1517.77579117 -> 1100.3736 | GP9: =GO9/1492.3021 -> 0.73736651 | GR9: 12302.136 | GS9: 1069.2209 | GV9: 3776.591 | GW9: 1100.3736 | GX9: =MAX(GW:GW) -> 1537.0311 | GY9: =GW9/GX9 -> 0.71590848
A10: ES Biomasa | B10: 2462.66 | D10: ES00 Run of River | E10: 3117.92 | I10: PT00 PS Open | J10: 4613 | L10: FR00 Reservoir | M10: 9849.04 | P10: 8 | Q10: 0 | R10: 0 | S10: 0 | T10: 0 | U10: 0 | V10: 0 | W10: 0 | X10: 0 | Y10: 0 | Z10: 0 | AA10: 0 | AB10: 0 | AC10: 0 | AD10: 0 | AF10: 8 | AG10: 21804.951 | AH10: 1258.1 | AI10: 273.5 | AJ10: 0.245 | AK10: 0.547 | AL10: 0.547 | AM10: 58.786 | AN10: 2130.7788 | AO10: 0.091 | AP10: 0.183 | AQ10: 22121.6 | AR10: 19930.275 | AS10: 0.496 | AT10: 0.849 | AV10: 881.632 | AW10: 0.35799989 | AX10: 914.144 | AY10: 0.56885128 | AZ10: 1121.478 | BA10: 0.57843924 | BC10: 51358.995 | BD10: 0.73770492 | BF10: 9322.586 | BG10: 0 | BH10: 0 | BI10: 0.2859689 | BJ10: 0 | BK10: 0 | BL10: 0 | BM10: 0 | BN10: 1038.815 | BO10: 0.077074863 | BP10: 0 | BQ10: 7668 | BR10: 651.21893 | BT10: -700 | BU10: 0 | BV10: 4485 | BW10: 4485 | BX10: 0 | BY10: 0 | BZ10: -5000 | CA10: 0 | CB10: -1588.0746 | CC10: 0 | CD10: -4000 | CE10: 0 | CF10: 4800 | CG10: 4800 | CH10: 11792.669 | CI10: 11792.669 | CJ10: 21077.669 | CL10: -700 | CM10: 700 | CN10: 4485 | CO10: 0 | CP10: 0 | CQ10: 0 | CR10: -5000 | CS10: 5000 | CT10: -1588.0746 | CU10: 1588.0746 | CV10: -4000 | CW10: 4000 | CX10: 4800 | CY10: 0 | CZ10: 11792.669 | DA10: 0 | DB10: 11288.075 | DD10: 31087.021 | DE10: 1985.193 | DF10: 3967.9018 | DG10: 37040.116 | DH10: 7300.096 | DI10: 48105.411 | DJ10: 6568 | DK10: 54673.411 | DM10: 1287.586 | DN10: 10571.616 | DO10: 11859.202 | DP10: 1483.4434 | DQ10: 2940.8695 | DR10: 420.26615 | DS10: 3361.1356 | DT10: 163.38164 | DU10: 163.38164 | DW10: 0 | DX10: 6779.661 | DY10: 1447.7401 | DZ10: 0 | EA10: 0 | EB10: 1553.6723 | EC10: 0 | ED10: 1271.1864 | EE10: 0 | EF10: 847.5 | EG10: 0 | EH10: 7397.5989 | EI10: 0 | EJ10: 6779.661 | EK10: 1553.6723 | EL10: 847.5 | EM10: 735.835 | EN10: 420.26615 | EO10: 10964.025 | EP10: 0 | ER10: 0 | ES10: 0 | ET10: =(ES10+ER10)/($E$2+$E$3) -> 0 | EU10: 0 | EV10: 0 | EW10: =(EU10+EV10)/($J$2+$J$3) -> 0 | EY10: 0 | EZ10: 3156.57 | FA10: =(EY10+EZ10)/($E$12+$E$14) -> 0.23203283 | FB10: 4613 | FC10: =FB10/$J$10 -> 1 | FF10: 0 | FG10: 0 | FH10: =(FF10+FG10)/($E$13+$E$15) -> 0 | FI10: 0 | FJ10: =FI10/$J$11 -> 0 | FL10: 7873 | FM10: =FL10/$E$11 -> 0.68245451 | FN10: 2591 | FO10: =FN10/$J$9 -> 0.82634349 | FQ10: 0 | FR10: 367.01 | FS10: =(FQ10+FR10)/($J$8+$J$12) -> 0.46568963 | FT10: =FQ10+FR10 -> 367.01 | FV10: =FW10+FX10-FY10-GA10 -> 1223.6723 | FW10: 1553.6723 | FX10: 0 | FY10: 330 | FZ10: =FV10/1553.6723 -> 0.78759999 | GA10: 0 | GC10: 6619.0361 | GD10: =GC10/32600 -> 0.20303792 | GE10: 737.55865 | GF10: =GE10/13478 -> 0.054723153 | GH10: 7455.5241 | GI10: 1038.2046 | GK10: 0.257 | GL10: 0.84 | GM10: =-GN10 -> 2618.1494 | GN10: -2618.1494 | GO10: =GM10-1517.77579117 -> 1100.3736 | GP10: =GO10/1492.3021 -> 0.73736651 | GR10: 11503.818 | GS10: 1034.4002 | GV10: 3776.591 | GW10: 1100.3736 | GX10: =MAX(GW:GW) -> 1537.0311 | GY10: =GW10/GX10 -> 0.71590848
A11: PT Biomasa | B11: 1607 | D11: ES00 Reservoir | E11: 11536.3 | I11: PT00 PS Open Pump | J11: 3837 | L11: FR00 PS Open | M11: 3304.57 | P11: 9 | Q11: 0 | R11: 0 | S11: 0 | T11: 0 | U11: 0 | V11: 0 | W11: 0 | X11: 0 | Y11: 0 | Z11: 0 | AA11: 0 | AB11: 0 | AC11: 0 | AD11: 0 | AF11: 9 | AG11: 16998.962 | AH11: 1207.5 | AI11: 262.5 | AJ11: 0.191 | AK11: 0.525 | AL11: 0.525 | AM11: 57.494 | AN11: 2002.6992 | AO11: 0.089 | AP11: 0.172 | AQ11: 22077 | AR11: 20446.725 | AS11: 0.495 | AT11: 0.871 | AV11: 913.647 | AW11: 0.37100006 | AX11: 911.743 | AY11: 0.56735719 | AZ11: 1121.478 | BA11: 0.57843924 | BC11: 51358.995 | BD11: 0.73770492 | BF11: 7455.524 | BG11: 0 | BH11: 0 | BI11: 0.22869706 | BJ11: 0 | BK11: 0 | BL11: 0 | BM11: 0 | BN11: 1038.205 | BO11: 0.077029604 | BP11: 0 | BQ11: 7668 | BR11: 651.21893 | BT11: -700 | BU11: 0 | BV11: 4485 | BW11: 4485 | BX11: 0 | BY11: 0 | BZ11: -5000 | CA11: 0 | CB11: -773.81716 | CC11: 0 | CD11: -4000 | CE11: 0 | CF11: 4800 | CG11: 4800 | CH11: 12546.926 | CI11: 12546.926 | CJ11: 21831.926 | CL11: -700 | CM11: 700 | CN11: 4485 | CO11: 0 | CP11: 0 | CQ11: 0 | CR11: -5000 | CS11: 5000 | CT11: -773.81716 | CU11: 773.81716 | CV11: -4000 | CW11: 4000 | CX11: 4800 | CY11: 0 | CZ11: 12546.926 | DA11: 0 | DB11: 10473.817 | DD11: 32115.912 | DE11: 1952.726 | DF11: 3830.0583 | DG11: 37898.696 | DH11: 7380.419 | DI11: 48050.411 | DJ11: 7092 | DK11: 55142.411 | DM11: 1211.267 | DN11: 10571.616 | DO11: 11782.883 | DP11: 1581.3998 | DQ11: 2940.8695 | DR11: 420.26615 | DS11: 3361.1356 | DT11: 163.38164 | DU11: 163.38164 | DW11: 0 | DX11: 6779.661 | DY11: 1447.7401 | DZ11: 0 | EA11: 0 | EB11: 1553.6723 | EC11: 0 | ED11: 1271.1864 | EE11: 0 | EF11: 847.5 | EG11: 0 | EH11: 7397.5989 | EI11: 0 | EJ11: 6779.661 | EK11: 1553.6723 | EL11: 847.5 | EM11: 735.835 | EN11: 420.26615 | EO11: 10964.025 | EP11: 0 | ER11: 0 | ES11: 0 | ET11: =(ES11+ER11)/($E$2+$E$3) -> 0 | EU11: 0 | EV11: 0 | EW11: =(EU11+EV11)/($J$2+$J$3) -> 0 | EY11: 0 | EZ11: 3156.57 | FA11: =(EY11+EZ11)/($E$12+$E$14) -> 0.23203283 | FB11: 4613 | FC11: =FB11/$J$10 -> 1 | FF11: 0 | FG11: 0 | FH11: =(FF11+FG11)/($E$13+$E$15) -> 0 | FI11: 0 | FJ11: =FI11/$J$11 -> 0 | FL11: 7873 | FM11: =FL11/$E$11 -> 0.68245451 | FN11: 2591 | FO11: =FN11/$J$9 -> 0.82634349 | FQ11: 278 | FR11: 367.01 | FS11: =(FQ11+FR11)/($J$8+$J$12) -> 0.81843675 | FT11: =FQ11+FR11 -> 645.01 | FV11: =FW11+FX11-FY11-GA11 -> 1223.6723 | FW11: 1553.6723 | FX11: 0 | FY11: 330 | FZ11: =FV11/1553.6723 -> 0.78759999 | GA11: 0 | GC11: 5293.422 | GD11: =GC11/32600 -> 0.16237491 | GE11: 737.12555 | GF11: =GE11/13478 -> 0.054691019 | GH11: 11070.761 | GI11: 1716.0281 | GK11: 0.257 | GL11: 0.84 | GM11: =-GN11 -> 2618.1494 | GN11: -2618.1494 | GO11: =GM11-1517.77579117 -> 1100.3736 | GP11: =GO11/1492.3021 -> 0.73736651 | GR11: 9322.5865 | GS11: 1038.8148 | GV11: 3776.591 | GW11: 1100.3736 | GX11: =MAX(GW:GW) -> 1537.0311 | GY11: =GW11/GX11 -> 0.71590848
D12: ES00 PS Open | E12: 3156.57 | I12: PT00 Pondage | J12: 279.8 | L12: FR00 PS Open Pump | M12: 3304.57 | P12: 10 | Q12: 10126 | R12: 0.122 | S12: 341.155 | T12: 0.071 | U12: 3930 | V12: 0.131 | W12: 1063.9868 | X12: 0.074 | Y12: 367.0762 | Z12: 0.038 | AA12: 3290.88 | AB12: 0.064 | AC12: 2316.04 | AD12: 0.05 | AF12: 10 | AG12: 14684.967 | AH12: 1145.4 | AI12: 249 | AJ12: 0.165 | AK12: 0.498 | AL12: 0.498 | AM12: 57.494 | AN12: 1560.2424 | AO12: 0.089 | AP12: 0.134 | AQ12: 20114.6 | AR12: 20423.25 | AS12: 0.451 | AT12: 0.87 | AV12: 962.9 | AW12: 0.39099998 | AX12: 911.591 | AY12: 0.5672626 | AZ12: 1121.478 | BA12: 0.57843924 | BC12: 51358.995 | BD12: 0.73770492 | BF12: 11070.761 | BG12: 0 | BH12: 0 | BI12: 0.3395939 | BJ12: 0 | BK12: 0 | BL12: 0 | BM12: 0 | BN12: 1716.028 | BO12: 0.12732067 | BP12: 0 | BQ12: 7668 | BR12: 651.21893 | BT12: -700 | BU12: 0 | BV12: 4485 | BW12: 4485 | BX12: 0 | BY12: 0 | BZ12: -1595.9714 | CA12: 0 | CB12: -1389.4594 | CC12: 0 | CD12: -4000 | CE12: 0 | CF12: 4800 | CG12: 4800 | CH12: 10791.921 | CI12: 10791.921 | CJ12: 20076.921 | CL12: -700 | CM12: 700 | CN12: 4485 | CO12: 0 | CP12: 0 | CQ12: 0 | CR12: -1595.9714 | CS12: 1595.9714 | CT12: -1389.4594 | CU12: 1389.4594 | CV12: -4000 | CW12: 4000 | CX12: 4800 | CY12: 0 | CZ12: 10791.921 | DA12: 0 | DB12: 7685.4308 | DD12: 33632.042 | DE12: 1727.391 | DF12: 2387.8915 | DG12: 37747.324 | DH12: 8177.754 | DI12: 48376.411 | DJ12: 7618 | DK12: 55994.411 | DM12: 1132.873 | DN12: 10571.616 | DO12: 11704.489 | DP12: 1581.3998 | DQ12: 2940.8695 | DR12: 420.26615 | DS12: 3361.1356 | DT12: 163.38164 | DU12: 163.38164 | DW12: 0 | DX12: 6779.661 | DY12: 1447.7401 | DZ12: 0 | EA12: 0 | EB12: 1553.6723 | EC12: 0 | ED12: 1271.1864 | EE12: 0 | EF12: 847.5 | EG12: 0 | EH12: 7397.5989 | EI12: 0 | EJ12: 6779.661 | EK12: 1553.6723 | EL12: 847.5 | EM12: 735.835 | EN12: 420.26615 | EO12: 10964.025 | EP12: 0 | ER12: 0 | ES12: 0 | ET12: =(ES12+ER12)/($E$2+$E$3) -> 0 | EU12: 0 | EV12: 0 | EW12: =(EU12+EV12)/($J$2+$J$3) -> 0 | EY12: 0 | EZ12: 3156.57 | FA12: =(EY12+EZ12)/($E$12+$E$14) -> 0.23203283 | FB12: 4613 | FC12: =FB12/$J$10 -> 1 | FF12: 0 | FG12: 4059.8216 | FH12: =(FF12+FG12)/($E$13+$E$15) -> 0.30477425 | FI12: 0 | FJ12: =FI12/$J$11 -> 0 | FL12: 7873 | FM12: =FL12/$E$11 -> 0.68245451 | FN12: 2591 | FO12: =FN12/$J$9 -> 0.82634349 | FQ12: 154.1 | FR12: 367.01 | FS12: =(FQ12+FR12)/($J$8+$J$12) -> 0.6612232 | FT12: =FQ12+FR12 -> 521.11 | FV12: =FW12+FX12-FY12-GA12 -> 1223.6723 | FW12: 1553.6723 | FX12: 0 | FY12: 330 | FZ12: =FV12/1553.6723 -> 0.78759999 | GA12: 0 | GC12: 7860.2403 | GD12: =GC12/32600 -> 0.24111167 | GE12: 1171.8855 | GF12: =GE12/13478 -> 0.08694803 | GH12: 17654 | GI12: 3518.2035 | GK12: 0.257 | GL12: 0.84 | GM12: =-GN12 -> 2618.1494 | GN12: -2618.1494 | GO12: =GM12-1517.77579117 -> 1100.3736 | GP12: =GO12/1492.3021 -> 0.73736651 | GR12: 7455.5241 | GS12: 1038.2046 | GV12: 3776.591 | GW12: 1100.3736 | GX12: =MAX(GW:GW) -> 1537.0311 | GY12: =GW12/GX12 -> 0.71590848
D13: ES00 PS Open Pump | E13: 2897.4 | I13: PT00RETE Solar PV Rooftop | J13: 9659.9 | L13: FR00 PS Closed | M13: 1895.43 | P13: 11 | Q13: 25979 | R13: 0.313 | S13: 903.34 | T13: 0.188 | U13: 9150 | V13: 0.305 | W13: 3810.223 | X13: 0.265 | Y13: 1371.7058 | Z13: 0.142 | AA13: 7095.96 | AB13: 0.138 | AC13: 5187.9296 | AD13: 0.112 | AF13: 11 | AG13: 13883.969 | AH13: 1071.8 | AI13: 233 | AJ13: 0.156 | AK13: 0.466 | AL13: 0.466 | AM13: 54.91 | AN13: 838.3392 | AO13: 0.085 | AP13: 0.072 | AQ13: 18241.4 | AR13: 19672.05 | AS13: 0.409 | AT13: 0.838 | AV13: 982.601 | AW13: 0.39899986 | AX13: 918.27 | AY13: 0.57141879 | AZ13: 1121.478 | BA13: 0.57843924 | BC13: 51358.995 | BD13: 0.73770492 | BF13: 17654 | BG13: 0 | BH13: 0 | BI13: 0.54153374 | BJ13: 0 | BK13: 0 | BL13: 0 | BM13: 0 | BN13: 3518.203 | BO13: 0.26103302 | BP13: 0 | BQ13: 7668 | BR13: 0 | BT13: -700 | BU13: 0 | BV13: 4485 | BW13: 4485 | BX13: 0 | BY13: 0 | BZ13: 0 | CA13: 0 | CB13: -5300 | CC13: 0 | CD13: -4000 | CE13: 0 | CF13: 4800 | CG13: 4800 | CH13: 9336.1177 | CI13: 9336.1177 | CJ13: 18621.118 | CL13: -700 | CM13: 700 | CN13: 4485 | CO13: 0 | CP13: 0 | CQ13: 0 | CR13: 0 | CS13: 0 | CT13: -5300 | CU13: 5300 | CV13: -4000 | CW13: 4000 | CX13: 4800 | CY13: 0 | CZ13: 9336.1177 | DA13: 0 | DB13: 10000 | DD13: 34203.632 | DE13: 1568.24 | DF13: 1889.8543 | DG13: 37661.726 | DH13: 9857.165 | DI13: 49873.411 | DJ13: 7409 | DK13: 57282.411 | DM13: 1061.063 | DN13: 10571.616 | DO13: 11632.679 | DP13: 1632.9559 | DQ13: 2940.8695 | DR13: 420.26615 | DS13: 3361.1356 | DT13: 163.38164 | DU13: 163.38164 | DW13: 0 | DX13: 6779.661 | DY13: 1447.7401 | DZ13: 0 | EA13: 0 | EB13: 1553.6723 | EC13: 0 | ED13: 1271.1864 | EE13: 0 | EF13: 847.5 | EG13: 0 | EH13: 7397.5989 | EI13: 0 | EJ13: 6779.661 | EK13: 1553.6723 | EL13: 847.5 | EM13: 735.835 | EN13: 420.26615 | EO13: 10964.025 | EP13: 0 | ER13: 0 | ES13: 0 | ET13: =(ES13+ER13)/($E$2+$E$3) -> 0 | EU13: 0 | EV13: 0 | EW13: =(EU13+EV13)/($J$2+$J$3) -> 0 | EY13: 0 | EZ13: 0 | FA13: =(EY13+EZ13)/($E$12+$E$14) -> 0 | FB13: 4613 | FC13: =FB13/$J$10 -> 1 | FF13: 0 | FG13: 10423.35 | FH13: =(FF13+FG13)/($E$13+$E$15) -> 0.78248972 | FI13: 0 | FJ13: =FI13/$J$11 -> 0 | FL13: 7873 | FM13: =FL13/$E$11 -> 0.68245451 | FN13: 2591 | FO13: =FN13/$J$9 -> 0.82634349 | FQ13: 0 | FR13: 367.01 | FS13: =(FQ13+FR13)/($J$8+$J$12) -> 0.46568963 | FT13: =FQ13+FR13 -> 367.01 | FV13: =FW13+FX13-FY13-GA13 -> 902.45336 | FW13: 1553.6723 | FX13: 0 | FY13: 0 | FZ13: =FV13/1553.6723 -> 0.58085181 | GA13: 651.21893 | GC13: 12534.34 | GD13: =GC13/32600 -> 0.38448896 | GE13: 1658.2016 | GF13: =GE13/13478 -> 0.12303024 | GH13: 21855.531 | GI13: 5291.8935 | GK13: 0.257 | GL13: 0.84 | GM13: =-GN13 -> 1517.7758 | GN13: -1517.7758 | GO13: =GM13-1517.77579117 -> 0 | GP13: =GO13/1492.3021 -> 0 | GR13: 11070.761 | GS13: 1716.0281 | GV13: 3776.591 | GW13: 1100.3736 | GX13: =MAX(GW:GW) -> 1537.0311 | GY13: =GW13/GX13 -> 0.71590848
D14: ES00 PS Closed | E14: 10447.41 | I14: PT00_SRES_RES_Solar | J14: 12584.9 | L14: FR00 PS Closed Pump | M14: 1895.43 | P14: 12 | Q14: 31457 | R14: 0.379 | S14: 1489.55 | T14: 0.31 | U14: 13260 | V14: 0.442 | W14: 6355.1644 | X14: 0.442 | Y14: 2424.6349 | Z14: 0.251 | AA14: 10181.16 | AB14: 0.198 | AC14: 7503.9696 | AD14: 0.162 | AF14: 12 | AG14: 14684.967 | AH14: 1005.1 | AI14: 218.5 | AJ14: 0.165 | AK14: 0.437 | AL14: 0.437 | AM14: 52.972 | AN14: 442.4568 | AO14: 0.082 | AP14: 0.038 | AQ14: 16011.4 | AR14: 19014.75 | AS14: 0.359 | AT14: 0.81 | AV14: 997.377 | AW14: 0.40499988 | AX14: 914.432 | AY14: 0.56903049 | AZ14: 1121.478 | BA14: 0.57843924 | BC14: 51358.995 | BD14: 0.73770492 | BF14: 21855.531 | BG14: 0 | BH14: 0 | BI14: 0.67041506 | BJ14: 0 | BK14: 0 | BL14: 0 | BM14: 0 | BN14: 5291.894 | BO14: 0.39263199 | BP14: 0 | BQ14: 7668 | BR14: 0 | BT14: -700 | BU14: 0 | BV14: 4485 | BW14: 4485 | BX14: 0 | BY14: 0 | BZ14: 0 | CA14: 0 | CB14: -5300 | CC14: 0 | CD14: -4000 | CE14: 0 | CF14: 4800 | CG14: 4800 | CH14: 9373.2597 | CI14: 9373.2597 | CJ14: 18658.26 | CL14: -700 | CM14: 700 | CN14: 4485 | CO14: 0 | CP14: 0 | CQ14: 0 | CR14: 0 | CS14: 0 | CT14: -5300 | CU14: 5300 | CV14: -4000 | CW14: 4000 | CX14: 4800 | CY14: 0 | CZ14: 9373.2597 | DA14: 0 | DB14: 10000 | DD14: 34988.68 | DE14: 1570.177 | DF14: 2380.3126 | DG14: 38939.17 | DH14: 11506.75 | DI14: 52512.411 | DJ14: 7066 | DK14: 59578.411 | DM14: 1007.947 | DN14: 10555.906 | DO14: 11563.853 | DP14: 1632.9559 | DQ14: 2932.5916 | DR14: 428.54402 | DS14: 3361.1356 | DT14: 162.92176 | DU14: 162.92176 | DW14: 0 | DX14: 6779.661 | DY14: 1447.7401 | DZ14: 0 | EA14: 0 | EB14: 1521.4124 | EC14: 0 | ED14: 1271.1864 | EE14: 0 | EF14: 847.5 | EG14: 0 | EH14: 7397.5989 | EI14: 0 | EJ14: 6779.661 | EK14: 1521.4124 | EL14: 847.5 | EM14: 735.835 | EN14: 428.54402 | EO14: 10964.025 | EP14: 0 | ER14: 0 | ES14: 0 | ET14: =(ES14+ER14)/($E$2+$E$3) -> 0 | EU14: 0 | EV14: 0 | EW14: =(EU14+EV14)/($J$2+$J$3) -> 0 | EY14: 0 | EZ14: 0 | FA14: =(EY14+EZ14)/($E$12+$E$14) -> 0 | FB14: 3484.0038 | FC14: =FB14/$J$10 -> 0.7552577 | FF14: 0 | FG14: 10423.35 | FH14: =(FF14+FG14)/($E$13+$E$15) -> 0.78248972 | FI14: 0 | FJ14: =FI14/$J$11 -> 0 | FL14: 7873 | FM14: =FL14/$E$11 -> 0.68245451 | FN14: 2591 | FO14: =FN14/$J$9 -> 0.82634349 | FQ14: 0 | FR14: 367.01 | FS14: =(FQ14+FR14)/($J$8+$J$12) -> 0.46568963 | FT14: =FQ14+FR14 -> 367.01 | FV14: =FW14+FX14-FY14-GA14 -> 572.91324 | FW14: 1521.4124 | FX14: 0 | FY14: 0 | FZ14: =FV14/1553.6723 -> 0.3687478 | GA14: 948.49917 | GC14: 15517.427 | GD14: =GC14/32600 -> 0.47599469 | GE14: 2092.9616 | GF14: =GE14/13478 -> 0.15528725 | GH14: 24329.671 | GI14: 6406.0815 | GK14: 0.257 | GL14: 0.84 | GM14: =-GN14 -> 1517.7758 | GN14: -1517.7758 | GO14: =GM14-1517.77579117 -> 0 | GP14: =GO14/1492.3021 -> 0 | GR14: 17654 | GS14: 3518.2035 | GV14: 3776.591 | GW14: 1100.3736 | GX14: =MAX(GW:GW) -> 1537.0311 | GY14: =GW14/GX14 -> 0.71590848
D15: ES00 PS Closed Pump | E15: 10423.35 | I15: PT00_SRES_RES_Wind_Offshore | J15: 8954 | L15: FR00 DSR Price Band 1 | M15: 7270 | P15: 13 | Q15: 32453 | R15: 0.391 | S15: 1869.145 | T15: 0.389 | U15: 15300 | V15: 0.51 | W15: 7879.2536 | X15: 0.548 | Y15: 3120.1477 | Z15: 0.323 | AA15: 11003.88 | AB15: 0.214 | AC15: 8245.1024 | AD15: 0.178 | AF15: 13 | AG15: 16909.962 | AH15: 979.8 | AI15: 213 | AJ15: 0.19 | AK15: 0.426 | AL15: 0.426 | AM15: 50.388 | AN15: 430.8132 | AO15: 0.078 | AP15: 0.037 | AQ15: 15877.6 | AR15: 18803.475 | AS15: 0.356 | AT15: 0.801 | AV15: 994.915 | AW15: 0.40400015 | AX15: 916.059 | AY15: 0.57004294 | AZ15: 1121.478 | BA15: 0.57843924 | BC15: 51358.995 | BD15: 0.73770492 | BF15: 24329.671 | BG15: 0 | BH15: 0 | BI15: 0.74630893 | BJ15: 0 | BK15: 0 | BL15: 0 | BM15: 0 | BN15: 6406.081 | BO15: 0.47529908 | BP15: 0 | BQ15: 7668 | BR15: 0 | BT15: -700 | BU15: 0 | BV15: 4485 | BW15: 4485 | BX15: 0 | BY15: 0 | BZ15: 1310.575 | CA15: 1310.575 | CB15: -5300 | CC15: 0 | CD15: -4000 | CE15: 0 | CF15: 4800 | CG15: 4800 | CH15: 10307.717 | CI15: 10307.717 | CJ15: 20903.292 | CL15: -700 | CM15: 700 | CN15: 4485 | CO15: 0 | CP15: 0 | CQ15: 0 | CR15: 1310.575 | CS15: 0 | CT15: -5300 | CU15: 5300 | CV15: -4000 | CW15: 4000 | CX15: 4800 | CY15: 0 | CZ15: 10307.717 | DA15: 0 | DB15: 10000 | DD15: 35871.457 | DE15: 1571.902 | DF15: 2602.6944 | DG15: 40046.053 | DH15: 12788.484 | DI15: 54490.411 | DJ15: 6774 | DK15: 61264.411 | DM15: 983.526 | DN15: 10540.196 | DO15: 11523.722 | DP15: 1581.3998 | DQ15: 2924.3137 | DR15: 436.8219 | DS15: 3361.1356 | DT15: 162.46187 | DU15: 162.46187 | DW15: 0 | DX15: 6779.661 | DY15: 1447.7401 | DZ15: 0 | EA15: 0 | EB15: 504.93229 | EC15: 0 | ED15: 1271.1864 | EE15: 0 | EF15: 847.5 | EG15: 0 | EH15: 7397.5989 | EI15: 0 | EJ15: 6779.661 | EK15: 504.93229 | EL15: 847.5 | EM15: 735.835 | EN15: 436.8219 | EO15: 10964.025 | EP15: 0 | ER15: 0 | ES15: 0 | ET15: =(ES15+ER15)/($E$2+$E$3) -> 0 | EU15: 0 | EV15: 0 | EW15: =(EU15+EV15)/($J$2+$J$3) -> 0 | EY15: 0 | EZ15: 0 | FA15: =(EY15+EZ15)/($E$12+$E$14) -> 0 | FB15: 4613 | FC15: =FB15/$J$10 -> 1 | FF15: 0 | FG15: 10423.35 | FH15: =(FF15+FG15)/($E$13+$E$15) -> 0.78248972 | FI15: 0 | FJ15: =FI15/$J$11 -> 0 | FL15: 7873 | FM15: =FL15/$E$11 -> 0.68245451 | FN15: 2591 | FO15: =FN15/$J$9 -> 0.82634349 | FQ15: 0 | FR15: 367.01 | FS15: =(FQ15+FR15)/($J$8+$J$12) -> 0.46568963 | FT15: =FQ15+FR15 -> 367.01 | FV15: =FW15+FX15-FY15-GA15 -> 573.37313 | FW15: 504.93229 | FX15: 330 | FY15: 0 | FZ15: =FV15/1553.6723 -> 0.3690438 | GA15: 261.55917 | GC15: 17274.066 | GD15: =GC15/32600 -> 0.52987934 | GE15: 2476.1656 | GF15: =GE15/13478 -> 0.18371906 | GH15: 24980.846 | GI15: 6829.7911 | GK15: 0.257 | GL15: 0.84 | GM15: =-GN15 -> 1517.7758 | GN15: -1517.7758 | GO15: =GM15-1517.77579117 -> 0 | GP15: =GO15/1492.3021 -> 0 | GR15: 21855.531 | GS15: 5291.8935 | GV15: 3776.591 | GW15: 1100.3736 | GX15: =MAX(GW:GW) -> 1537.0311 | GY15: =GW15/GX15 -> 0.71590848
D16: ES00 DSR Price Band 1 | E16: 3500 | I16: PT00_SRES_RES_Wind_Onshore | J16: 968 | L16: FR00RETE Solar PV Rooftop | M16: 46320.8 | P16: 14 | Q16: 32287 | R16: 0.389 | S16: 1917.195 | T16: 0.399 | U16: 15330 | V16: 0.511 | W16: 8353.7342 | X16: 0.581 | Y16: 3361.6452 | Z16: 0.348 | AA16: 10078.32 | AB16: 0.196 | AC16: 7596.6112 | AD16: 0.164 | AF16: 14 | AG16: 18422.959 | AH16: 954.5 | AI16: 207.5 | AJ16: 0.207 | AK16: 0.415 | AL16: 0.415 | AM16: 51.68 | AN16: 500.6748 | AO16: 0.08 | AP16: 0.043 | AQ16: 16100.6 | AR16: 18709.575 | AS16: 0.361 | AT16: 0.797 | AV16: 999.84 | AW16: 0.40600002 | AX16: 911.992 | AY16: 0.56751213 | AZ16: 1121.478 | BA16: 0.57843924 | BC16: 51358.995 | BD16: 0.73770492 | BF16: 24980.846 | BG16: 0 | BH16: 0 | BI16: 0.76628362 | BJ16: 0 | BK16: 0 | BL16: 0 | BM16: 0 | BN16: 6829.791 | BO16: 0.50673624 | BP16: 0 | BQ16: 7668 | BR16: 0 | BT16: -700 | BU16: 0 | BV16: 4485 | BW16: 4485 | BX16: 0 | BY16: 0 | BZ16: 5000 | CA16: 5000 | CB16: -5300 | CC16: 0 | CD16: -4000 | CE16: 0 | CF16: 4800 | CG16: 4800 | CH16: 9058.2332 | CI16: 9058.2332 | CJ16: 23343.233 | CL16: -700 | CM16: 700 | CN16: 4485 | CO16: 0 | CP16: 0 | CQ16: 0 | CR16: 5000 | CS16: 0 | CT16: -5300 | CU16: 5300 | CV16: -4000 | CW16: 4000 | CX16: 4800 | CY16: 0 | CZ16: 9058.2332 | DA16: 0 | DB16: 10000 | DD16: 36210.647 | DE16: 1573.49 | DF16: 2314.103 | DG16: 40098.24 | DH16: 12777.052 | DI16: 52294.411 | DJ16: 6546 | DK16: 58840.411 | DM16: 966.902 | DN16: 10540.196 | DO16: 11507.098 | DP16: 1607.1779 | DQ16: 2924.3137 | DR16: 436.8219 | DS16: 3361.1356 | DT16: 162.46187 | DU16: 162.46187 | DW16: 0 | DX16: 6779.661 | DY16: 1447.7401 | DZ16: 0 | EA16: 0 | EB16: 757.72199 | EC16: 0 | ED16: 1271.1864 | EE16: 0 | EF16: 847.5 | EG16: 0 | EH16: 7397.5989 | EI16: 0 | EJ16: 6779.661 | EK16: 757.72199 | EL16: 847.5 | EM16: 735.835 | EN16: 436.8219 | EO16: 10964.025 | EP16: 0 | ER16: 0 | ES16: 0 | ET16: =(ES16+ER16)/($E$2+$E$3) -> 0 | EU16: 0 | EV16: 0 | EW16: =(EU16+EV16)/($J$2+$J$3) -> 0 | EY16: 0 | EZ16: 0 | FA16: =(EY16+EZ16)/($E$12+$E$14) -> 0 | FB16: 4538.1275 | FC16: =FB16/$J$10 -> 0.98376924 | FF16: 0 | FG16: 10423.35 | FH16: =(FF16+FG16)/($E$13+$E$15) -> 0.78248972 | FI16: 0 | FJ16: =FI16/$J$11 -> 0 | FL16: 7873 | FM16: =FL16/$E$11 -> 0.68245451 | FN16: 2591 | FO16: =FN16/$J$9 -> 0.82634349 | FQ16: 0 | FR16: 367.01 | FS16: =(FQ16+FR16)/($J$8+$J$12) -> 0.46568963 | FT16: =FQ16+FR16 -> 367.01 | FV16: =FW16+FX16-FY16-GA16 -> 573.37313 | FW16: 757.72199 | FX16: 77.210304 | FY16: 0 | FZ16: =FV16/1553.6723 -> 0.3690438 | GA16: 261.55917 | GC16: 17736.401 | GD16: =GC16/32600 -> 0.54406137 | GE16: 2936.7036 | GF16: =GE16/13478 -> 0.21788868 | GH16: 23893.52 | GI16: 6512.1453 | GK16: 0.257 | GL16: 0.84 | GM16: =-GN16 -> 1517.7758 | GN16: -1517.7758 | GO16: =GM16-1517.77579117 -> 0 | GP16: =GO16/1492.3021 -> 0 | GR16: 24329.671 | GS16: 6406.0815 | GV16: 3776.591 | GW16: 1100.3736 | GX16: =MAX(GW:GW) -> 1537.0311 | GY16: =GW16/GX16 -> 0.71590848
D17: ES00RETE Solar PV Rooftop | E17: 30000 | I17: PT00_SRES_P2G | J17: 13478 | L17: FRh2 SMR CCS | M17: 158 | P17: 15 | Q17: 31374 | R17: 0.378 | S17: 1672.14 | T17: 0.348 | U17: 13530 | V17: 0.451 | W17: 7792.9844 | X17: 0.542 | Y17: 3120.1477 | Z17: 0.323 | AA17: 7764.42 | AB17: 0.151 | AC17: 5790.1 | AD17: 0.125 | AF17: 15 | AG17: 19045.957 | AH17: 945.3 | AI17: 205.5 | AJ17: 0.214 | AK17: 0.411 | AL17: 0.411 | AM17: 56.848 | AN17: 582.18 | AO17: 0.088 | AP17: 0.05 | AQ17: 17171 | AR17: 18780 | AS17: 0.385 | AT17: 0.8 | AV17: 1004.765 | AW17: 0.40799989 | AX17: 906.768 | AY17: 0.56426136 | AZ17: 1121.478 | BA17: 0.57843924 | BC17: 51358.995 | BD17: 0.73770492 | BF17: 23893.52 | BG17: 0 | BH17: 0 | BI17: 0.73293006 | BJ17: 0 | BK17: 0 | BL17: 0 | BM17: 0 | BN17: 6512.145 | BO17: 0.4831685 | BP17: 0 | BQ17: 7668 | BR17: 0 | BT17: -700 | BU17: 0 | BV17: 4485 | BW17: 4485 | BX17: 0 | BY17: 0 | BZ17: 5000 | CA17: 5000 | CB17: -5300 | CC17: 0 | CD17: -4000 | CE17: 0 | CF17: 4800 | CG17: 4800 | CH17: 11163.303 | CI17: 11163.303 | CJ17: 25448.303 | CL17: -700 | CM17: 700 | CN17: 4485 | CO17: 0 | CP17: 0 | CQ17: 0 | CR17: 5000 | CS17: 0 | CT17: -5300 | CU17: 5300 | CV17: -4000 | CW17: 4000 | CX17: 4800 | CY17: 0 | CZ17: 11163.303 | DA17: 0 | DB17: 10000 | DD17: 35437.512 | DE17: 1574.324 | DF17: 1735.9122 | DG17: 38747.748 | DH17: 12124.716 | DI17: 51166.411 | DJ17: 6399 | DK17: 57565.411 | DM17: 965.662 | DN17: 10555.906 | DO17: 11521.568 | DP17: 1581.3998 | DQ17: 2932.5916 | DR17: 428.54402 | DS17: 3361.1356 | DT17: 162.92176 | DU17: 162.92176 | DW17: 0 | DX17: 6779.661 | DY17: 1447.7401 | DZ17: 0 | EA17: 0 | EB17: 1521.4124 | EC17: 0 | ED17: 1271.1864 | EE17: 0 | EF17: 847.5 | EG17: 0 | EH17: 7397.5989 | EI17: 0 | EJ17: 6779.661 | EK17: 1521.4124 | EL17: 847.5 | EM17: 735.835 | EN17: 428.54402 | EO17: 10964.025 | EP17: 0 | ER17: 0 | ES17: 0 | ET17: =(ES17+ER17)/($E$2+$E$3) -> 0 | EU17: 0 | EV17: 0 | EW17: =(EU17+EV17)/($J$2+$J$3) -> 0 | EY17: 0 | EZ17: 0 | FA17: =(EY17+EZ17)/($E$12+$E$14) -> 0 | FB17: 4479.8726 | FC17: =FB17/$J$10 -> 0.97114081 | FF17: 0 | FG17: 10423.35 | FH17: =(FF17+FG17)/($E$13+$E$15) -> 0.78248972 | FI17: 0 | FJ17: =FI17/$J$11 -> 0 | FL17: 7873 | FM17: =FL17/$E$11 -> 0.68245451 | FN17: 2591 | FO17: =FN17/$J$9 -> 0.82634349 | FQ17: 0 | FR17: 367.01 | FS17: =(FQ17+FR17)/($J$8+$J$12) -> 0.46568963 | FT17: =FQ17+FR17 -> 367.01 | FV17: =FW17+FX17-FY17-GA17 -> 572.91324 | FW17: 1521.4124 | FX17: 0 | FY17: 0 | FZ17: =FV17/1553.6723 -> 0.3687478 | GA17: 948.49917 | GC17: 16964.399 | GD17: =GC17/32600 -> 0.52038034 | GE17: 2730.4052 | GF17: =GE17/13478 -> 0.20258237 | GH17: 21529.504 | GI17: 5504.8128 | GK17: 0.257 | GL17: 0.84 | GM17: =-GN17 -> 1517.7758 | GN17: -1517.7758 | GO17: =GM17-1517.77579117 -> 0 | GP17: =GO17/1492.3021 -> 0 | GR17: 24980.846 | GS17: 6829.7911 | GV17: 3776.591 | GW17: 1100.3736 | GX17: =MAX(GW:GW) -> 1537.0311 | GY17: =GW17/GX17 -> 0.71590848
D18: ES00_SRES_RES_Solar | E18: 37999.68 | L18: Ammonia_FRN-FRh2N-HIGH | M18: 847.5 | P18: 16 | Q18: 29465 | R18: 0.355 | S18: 1215.665 | T18: 0.253 | U18: 10470 | V18: 0.349 | W18: 6340.7862 | X18: 0.441 | Y18: 2424.6349 | Z18: 0.251 | AA18: 4936.32 | AB18: 0.096 | AC18: 3566.7016 | AD18: 0.077 | AF18: 16 | AG18: 19134.957 | AH18: 947.6 | AI18: 206 | AJ18: 0.215 | AK18: 0.412 | AL18: 0.412 | AM18: 65.246 | AN18: 663.6852 | AO18: 0.101 | AP18: 0.057 | AQ18: 19802.4 | AR18: 19061.7 | AS18: 0.444 | AT18: 0.812 | AV18: 1002.303 | AW18: 0.40700015 | AX18: 900.345 | AY18: 0.56026447 | AZ18: 1121.478 | BA18: 0.57843924 | BC18: 51358.995 | BD18: 0.73770492 | BF18: 21529.504 | BG18: 0 | BH18: 0 | BI18: 0.66041423 | BJ18: 0 | BK18: 0 | BL18: 0 | BM18: 0 | BN18: 5504.813 | BO18: 0.40842951 | BP18: 0 | BQ18: 7668 | BR18: 0 | BT18: -700 | BU18: 0 | BV18: 4485 | BW18: 4485 | BX18: 0 | BY18: 0 | BZ18: 5000 | CA18: 5000 | CB18: -5300 | CC18: 0 | CD18: -4000 | CE18: 0 | CF18: 4800 | CG18: 4800 | CH18: 12619.906 | CI18: 12619.906 | CJ18: 26904.906 | CL18: -700 | CM18: 700 | CN18: 4485 | CO18: 0 | CP18: 0 | CQ18: 0 | CR18: 5000 | CS18: 0 | CT18: -5300 | CU18: 5300 | CV18: -4000 | CW18: 4000 | CX18: 4800 | CY18: 0 | CZ18: 12619.906 | DA18: 0 | DB18: 10000 | DD18: 35147.109 | DE18: 1572.316 | DF18: 1480.2775 | DG18: 38199.702 | DH18: 11305.368 | DI18: 50740.411 | DJ18: 6816 | DK18: 57556.411 | DM18: 972.736 | DN18: 10571.616 | DO18: 11544.352 | DP18: 1581.3998 | DQ18: 2940.8695 | DR18: 420.26615 | DS18: 3361.1356 | DT18: 163.38164 | DU18: 163.38164 | DW18: 0 | DX18: 6779.661 | DY18: 1447.7401 | DZ18: 0 | EA18: 0 | EB18: 1553.6723 | EC18: 0 | ED18: 1271.1864 | EE18: 0 | EF18: 847.5 | EG18: 0 | EH18: 7397.5989 | EI18: 0 | EJ18: 6779.661 | EK18: 1553.6723 | EL18: 847.5 | EM18: 735.835 | EN18: 420.26615 | EO18: 10964.025 | EP18: 0 | ER18: 0 | ES18: 0 | ET18: =(ES18+ER18)/($E$2+$E$3) -> 0 | EU18: 0 | EV18: 0 | EW18: =(EU18+EV18)/($J$2+$J$3) -> 0 | EY18: 0 | EZ18: 0 | FA18: =(EY18+EZ18)/($E$12+$E$14) -> 0 | FB18: 4613 | FC18: =FB18/$J$10 -> 1 | FF18: 0 | FG18: 10423.35 | FH18: =(FF18+FG18)/($E$13+$E$15) -> 0.78248972 | FI18: 0 | FJ18: =FI18/$J$11 -> 0 | FL18: 7873 | FM18: =FL18/$E$11 -> 0.68245451 | FN18: 2591 | FO18: =FN18/$J$9 -> 0.82634349 | FQ18: 0 | FR18: 367.01 | FS18: =(FQ18+FR18)/($J$8+$J$12) -> 0.46568963 | FT18: =FQ18+FR18 -> 367.01 | FV18: =FW18+FX18-FY18-GA18 -> 572.45336 | FW18: 1553.6723 | FX18: 0 | FY18: 0 | FZ18: =FV18/1553.6723 -> 0.3684518 | GA18: 981.21893 | GC18: 15285.948 | GD18: =GC18/32600 -> 0.46889411 | GE18: 2295.6452 | GF18: =GE18/13478 -> 0.17032536 | GH18: 16552.667 | GI18: 3977.0912 | GK18: 0.257 | GL18: 0.84 | GM18: =-GN18 -> 1517.7758 | GN18: -1517.7758 | GO18: =GM18-1517.77579117 -> 0 | GP18: =GO18/1492.3021 -> 0 | GR18: 23893.52 | GS18: 6512.1453 | GV18: 3776.591 | GW18: 1100.3736 | GX18: =MAX(GW:GW) -> 1537.0311 | GY18: =GW18/GX18 -> 0.71590848
D19: ES00_SRES_RES_Wind_Onshore | E19: 37999.68 | L19: Ammonia_FRN-FRh2N-LOW | M19: 847.5 | P19: 17 | Q19: 20916 | R19: 0.252 | S19: 615.04 | T19: 0.128 | U19: 6210 | V19: 0.207 | W19: 4227.1908 | X19: 0.294 | Y19: 1468.3048 | Z19: 0.152 | AA19: 1799.7 | AB19: 0.035 | AC19: 1204.3408 | AD19: 0.026 | AF19: 17 | AG19: 18333.959 | AH19: 926.9 | AI19: 201.5 | AJ19: 0.206 | AK19: 0.403 | AL19: 0.403 | AM19: 71.706 | AN19: 675.3288 | AO19: 0.111 | AP19: 0.058 | AQ19: 23905.6 | AR19: 19366.875 | AS19: 0.536 | AT19: 0.825 | AV19: 1009.691 | AW19: 0.41000016 | AX19: 889.623 | AY19: 0.55359241 | AZ19: 1121.478 | BA19: 0.57843924 | BC19: 51358.995 | BD19: 0.73770492 | BF19: 16552.667 | BG19: 0 | BH19: 0 | BI19: 0.50775052 | BJ19: 0 | BK19: 0 | BL19: 0 | BM19: 0 | BN19: 3977.091 | BO19: 0.2950802 | BP19: 0 | BQ19: 7668 | BR19: 356.94 | BT19: -700 | BU19: 0 | BV19: 4485 | BW19: 4485 | BX19: 0 | BY19: 0 | BZ19: 5000 | CA19: 5000 | CB19: -5300 | CC19: 0 | CD19: -4000 | CE19: 0 | CF19: 4800 | CG19: 4800 | CH19: 8186.3134 | CI19: 8186.3134 | CJ19: 22471.313 | CL19: -700 | CM19: 700 | CN19: 4485 | CO19: 0 | CP19: 0 | CQ19: 0 | CR19: 5000 | CS19: 0 | CT19: -5300 | CU19: 5300 | CV19: -4000 | CW19: 4000 | CX19: 4800 | CY19: 0 | CZ19: 8186.3134 | DA19: 0 | DB19: 10000 | DD19: 35595.013 | DE19: 1914.402 | DF19: 1494.4245 | DG19: 39003.84 | DH19: 10324.808 | DI19: 51969.411 | DJ19: 6649 | DK19: 58618.411 | DM19: 968.74 | DN19: 10571.616 | DO19: 11540.356 | DP19: 1581.3998 | DQ19: 2940.8695 | DR19: 420.26615 | DS19: 3361.1356 | DT19: 163.38164 | DU19: 163.38164 | DW19: 0 | DX19: 6779.661 | DY19: 1447.7401 | DZ19: 0 | EA19: 0 | EB19: 1553.6723 | EC19: 0 | ED19: 1271.1864 | EE19: 0 | EF19: 847.5 | EG19: 0 | EH19: 7397.5989 | EI19: 0 | EJ19: 6779.661 | EK19: 1553.6723 | EL19: 847.5 | EM19: 735.835 | EN19: 420.26615 | EO19: 10964.025 | EP19: 0 | ER19: 0 | ES19: 0 | ET19: =(ES19+ER19)/($E$2+$E$3) -> 0 | EU19: 0 | EV19: 0 | EW19: =(EU19+EV19)/($J$2+$J$3) -> 0 | EY19: 0 | EZ19: 2377.0243 | FA19: =(EY19+EZ19)/($E$12+$E$14) -> 0.17473006 | FB19: 4613 | FC19: =FB19/$J$10 -> 1 | FF19: 0 | FG19: 10423.35 | FH19: =(FF19+FG19)/($E$13+$E$15) -> 0.78248972 | FI19: 0 | FJ19: =FI19/$J$11 -> 0 | FL19: 7873 | FM19: =FL19/$E$11 -> 0.68245451 | FN19: 2591 | FO19: =FN19/$J$9 -> 0.82634349 | FQ19: 0 | FR19: 367.01 | FS19: =(FQ19+FR19)/($J$8+$J$12) -> 0.46568963 | FT19: =FQ19+FR19 -> 367.01 | FV19: =FW19+FX19-FY19-GA19 -> 1259.3934 | FW19: 1553.6723 | FX19: 0 | FY19: 0 | FZ19: =FV19/1553.6723 -> 0.81059137 | GA19: 294.27893 | GC19: 11752.394 | GD19: =GC19/32600 -> 0.36050287 | GE19: 1860.8852 | GF19: =GE19/13478 -> 0.13806835 | GH19: 8563.5051 | GI19: 2359.0792 | GK19: 0.257 | GL19: 0.84 | GM19: =-GN19 -> 1517.7758 | GN19: -1517.7758 | GO19: =GM19-1517.77579117 -> 0 | GP19: =GO19/1492.3021 -> 0 | GR19: 21529.504 | GS19: 5504.8128 | GV19: 3776.591 | GW19: 1100.3736 | GX19: =MAX(GW:GW) -> 1537.0311 | GY19: =GW19/GX19 -> 0.71590848
D20: ES00_SRES_P2G | E20: 32600 | L20: Ammonia_FRSW-FRh2SW-HIGH | M20: 735.835 | P20: 18 | Q20: 4565 | R20: 0.055 | S20: 62.465 | T20: 0.013 | U20: 1560 | V20: 0.052 | W20: 1739.7622 | X20: 0.121 | Y20: 511.9747 | Z20: 0.053 | AA20: 0 | AB20: 0 | AC20: 0 | AD20: 0 | AF20: 18 | AG20: 15307.966 | AH20: 901.6 | AI20: 196 | AJ20: 0.172 | AK20: 0.392 | AL20: 0.392 | AM20: 80.75 | AN20: 803.4084 | AO20: 0.125 | AP20: 0.069 | AQ20: 27473.6 | AR20: 19578.15 | AS20: 0.616 | AT20: 0.834 | AV20: 1049.093 | AW20: 0.42599994 | AX20: 875.741 | AY20: 0.54495395 | AZ20: 1121.478 | BA20: 0.57843924 | BC20: 51358.995 | BD20: 0.73770492 | BF20: 8563.505 | BG20: 0 | BH20: 0 | BI20: 0.2626842 | BJ20: 0 | BK20: 0 | BL20: 0 | BM20: 0 | BN20: 2359.079 | BO20: 0.17503183 | BP20: 0 | BQ20: 7668 | BR20: 651.21893 | BT20: -700 | BU20: 0 | BV20: 4485 | BW20: 4485 | BX20: 0 | BY20: 0 | BZ20: 5000 | CA20: 5000 | CB20: -5300 | CC20: 0 | CD20: -4000 | CE20: 0 | CF20: 4800 | CG20: 4800 | CH20: 9515.0866 | CI20: 9515.0866 | CJ20: 23800.087 | CL20: -700 | CM20: 700 | CN20: 4485 | CO20: 0 | CP20: 0 | CQ20: 0 | CR20: 5000 | CS20: 0 | CT20: -5300 | CU20: 5300 | CV20: -4000 | CW20: 4000 | CX20: 4800 | CY20: 0 | CZ20: 9515.0866 | DA20: 0 | DB20: 10000 | DD20: 37848.421 | DE20: 2170.46 | DF20: 1594.917 | DG20: 41613.798 | DH20: 9622.509 | DI20: 54666.411 | DJ20: 6747 | DK20: 61413.411 | DM20: 947.268 | DN20: 10571.616 | DO20: 11518.884 | DP20: 1581.3998 | DQ20: 2940.8695 | DR20: 0 | DS20: 2940.8695 | DT20: 163.38164 | DU20: 163.38164 | DW20: 0 | DX20: 5734.761 | DY20: 1196.1601 | DZ20: 0 | EA20: 0 | EB20: 1553.6723 | EC20: 0 | ED20: 898.13259 | EE20: 0 | EF20: 847.5 | EG20: 0 | EH20: 7397.5989 | EI20: 0 | EJ20: 5734.761 | EK20: 1553.6723 | EL20: 847.5 | EM20: 735.835 | EN20: 0 | EO20: 10339.392 | EP20: 0 | ER20: 774.157 | ES20: 1591.4647 | ET20: =(ES20+ER20)/($E$2+$E$3) -> 0.082234788 | EU20: 0 | EV20: 148.698 | EW20: =(EU20+EV20)/($J$2+$J$3) -> 0.081433913 | EY20: 1017.3929 | EZ20: 3156.57 | FA20: =(EY20+EZ20)/($E$12+$E$14) -> 0.30681924 | FB20: 4613 | FC20: =FB20/$J$10 -> 1 | FF20: 0 | FG20: 0 | FH20: =(FF20+FG20)/($E$13+$E$15) -> 0 | FI20: 0 | FJ20: =FI20/$J$11 -> 0 | FL20: 7873 | FM20: =FL20/$E$11 -> 0.68245451 | FN20: 2591 | FO20: =FN20/$J$9 -> 0.82634349 | FQ20: 278 | FR20: 367.01 | FS20: =(FQ20+FR20)/($J$8+$J$12) -> 0.81843675 | FT20: =FQ20+FR20 -> 645.01 | FV20: =FW20+FX20-FY20-GA20 -> 1223.6723 | FW20: 1553.6723 | FX20: 0 | FY20: 330 | FZ20: =FV20/1553.6723 -> 0.78759999 | GA20: 0 | GC20: 6080.0885 | GD20: =GC20/32600 -> 0.18650578 | GE20: 1426.1252 | GF20: =GE20/13478 -> 0.10581134 | GH20: 6041.0902 | GI20: 1396.2889 | GK20: 0.257 | GL20: 0.84 | GM20: =-GN20 -> 2618.1494 | GN20: -2618.1494 | GO20: =GM20-1517.77579117 -> 1100.3736 | GP20: =GO20/1492.3021 -> 0.73736651 | GR20: 16552.667 | GS20: 3977.0912 | GV20: 3776.591 | GW20: 1100.3736 | GX20: =MAX(GW:GW) -> 1537.0311 | GY20: =GW20/GX20 -> 0.71590848
D21: MA-ESh2-HIGH | E21: 1100.3736 | L21: Ammonia_FRSW-FRh2SW-LOW | M21: 735.835 | P21: 19 | Q21: 0 | R21: 0 | S21: 0 | T21: 0 | U21: 0 | V21: 0 | W21: 0 | X21: 0 | Y21: 0 | Z21: 0 | AA21: 0 | AB21: 0 | AC21: 0 | AD21: 0 | AF21: 19 | AG21: 14150.968 | AH21: 867.1 | AI21: 188.5 | AJ21: 0.159 | AK21: 0.377 | AL21: 0.377 | AM21: 90.44 | AN21: 1117.7856 | AO21: 0.14 | AP21: 0.096 | AQ21: 29703.6 | AR21: 19742.475 | AS21: 0.666 | AT21: 0.841 | AV21: 1044.168 | AW21: 0.42400006 | AX21: 870.741 | AY21: 0.54184256 | AZ21: 1121.478 | BA21: 0.57843924 | BC21: 51358.995 | BD21: 0.73770492 | BF21: 6041.09 | BG21: 0 | BH21: 0 | BI21: 0.18530951 | BJ21: 0 | BK21: 0 | BL21: 0 | BM21: 0 | BN21: 1396.289 | BO21: 0.10359764 | BP21: 0 | BQ21: 7668 | BR21: 650.75905 | BT21: -700 | BU21: 0 | BV21: 4485 | BW21: 4485 | BX21: 0 | BY21: 0 | BZ21: 5000 | CA21: 5000 | CB21: -5300 | CC21: 0 | CD21: -4000 | CE21: 0 | CF21: 4800 | CG21: 4800 | CH21: 9516.3937 | CI21: 9516.3937 | CJ21: 23801.394 | CL21: -700 | CM21: 700 | CN21: 4485 | CO21: 0 | CP21: 0 | CQ21: 0 | CR21: 5000 | CS21: 0 | CT21: -5300 | CU21: 5300 | CV21: -4000 | CW21: 4000 | CX21: 4800 | CY21: 0 | CZ21: 9516.3937 | DA21: 0 | DB21: 10000 | DD21: 39546.004 | DE21: 2273.237 | DF21: 1721.6879 | DG21: 43540.929 | DH21: 9376.779 | DI21: 56199.411 | DJ21: 6343 | DK21: 62542.411 | DM21: 936.723 | DN21: 10555.906 | DO21: 11492.629 | DP21: 1581.3998 | DQ21: 2932.5916 | DR21: 0 | DS21: 2932.5916 | DT21: 162.92176 | DU21: 162.92176 | DW21: 0 | DX21: 4690.3209 | DY21: 944.58008 | DZ21: 0 | EA21: 0 | EB21: 1553.6723 | EC21: 0 | ED21: 226.67658 | EE21: 0 | EF21: 847.5 | EG21: 0 | EH21: 7284.4726 | EI21: 0 | EJ21: 4690.3209 | EK21: 1553.6723 | EL21: 847.5 | EM21: 735.835 | EN21: 0 | EO21: 9303.2293 | EP21: 0 | ER21: 799.488 | ES21: 1591.4647 | ET21: =(ES21+ER21)/($E$2+$E$3) -> 0.083115356 | EU21: 0 | EV21: 148.698 | EW21: =(EU21+EV21)/($J$2+$J$3) -> 0.081433913 | EY21: 10447.41 | EZ21: 3156.57 | FA21: =(EY21+EZ21)/($E$12+$E$14) -> 1 | FB21: 4613 | FC21: =FB21/$J$10 -> 1 | FF21: 0 | FG21: 0 | FH21: =(FF21+FG21)/($E$13+$E$15) -> 0 | FI21: 0 | FJ21: =FI21/$J$11 -> 0 | FL21: 7873 | FM21: =FL21/$E$11 -> 0.68245451 | FN21: 2591 | FO21: =FN21/$J$9 -> 0.82634349 | FQ21: 278 | FR21: 367.01 | FS21: =(FQ21+FR21)/($J$8+$J$12) -> 0.81843675 | FT21: =FQ21+FR21 -> 645.01 | FV21: =FW21+FX21-FY21-GA21 -> 1223.6723 | FW21: 1553.6723 | FX21: 0 | FY21: 330 | FZ21: =FV21/1553.6723 -> 0.78759999 | GA21: 0 | GC21: 4289.1739 | GD21: =GC21/32600 -> 0.13156975 | GE21: 991.36519 | GF21: =GE21/13478 -> 0.073554325 | GH21: 5887.6226 | GI21: 1465.3291 | GK21: 0.257 | GL21: 0.84 | GM21: =-GN21 -> 2618.1494 | GN21: -2618.1494 | GO21: =GM21-1517.77579117 -> 1100.3736 | GP21: =GO21/1492.3021 -> 0.73736651 | GR21: 8563.5051 | GS21: 2359.0792 | GV21: 3776.591 | GW21: 1100.3736 | GX21: =MAX(GW:GW) -> 1537.0311 | GY21: =GW21/GX21 -> 0.71590848
D22: MA-ESh2-LOW | E22: 1517.7758 | P22: 20 | Q22: 0 | R22: 0 | S22: 0 | T22: 0 | U22: 0 | V22: 0 | W22: 0 | X22: 0 | Y22: 0 | Z22: 0 | AA22: 0 | AB22: 0 | AC22: 0 | AD22: 0 | AF22: 20 | AG22: 13794.969 | AH22: 825.7 | AI22: 179.5 | AJ22: 0.155 | AK22: 0.359 | AL22: 0.359 | AM22: 96.254 | AN22: 1315.7268 | AO22: 0.149 | AP22: 0.113 | AQ22: 30684.8 | AR22: 19601.625 | AS22: 0.688 | AT22: 0.835 | AV22: 1044.168 | AW22: 0.42400006 | AX22: 871.059 | AY22: 0.54204045 | AZ22: 1121.478 | BA22: 0.57843924 | BC22: 51358.995 | BD22: 0.73770492 | BF22: 5887.623 | BG22: 0 | BH22: 0 | BI22: 0.18060193 | BJ22: 0 | BK22: 0 | BL22: 0 | BM22: 0 | BN22: 1465.329 | BO22: 0.10872006 | BP22: 0 | BQ22: 7668 | BR22: 650.29917 | BT22: -700 | BU22: 0 | BV22: 4485 | BW22: 4485 | BX22: 0 | BY22: 0 | BZ22: 5000 | CA22: 5000 | CB22: -5300 | CC22: 0 | CD22: -4000 | CE22: 0 | CF22: 4504.8368 | CG22: 4504.8368 | CH22: 18059.165 | CI22: 18059.165 | CJ22: 32049.002 | CL22: -700 | CM22: 700 | CN22: 4485 | CO22: 0 | CP22: 0 | CQ22: 0 | CR22: 5000 | CS22: 0 | CT22: -5300 | CU22: 5300 | CV22: -4000 | CW22: 4000 | CX22: 4504.8368 | CY22: 0 | CZ22: 18059.165 | DA22: 0 | DB22: 10000 | DD22: 39969.787 | DE22: 2306.669 | DF22: 1856.2612 | DG22: 44132.717 | DH22: 9472 | DI22: 56362.411 | DJ22: 5867 | DK22: 62229.411 | DM22: 925.002 | DN22: 10540.196 | DO22: 11465.198 | DP22: 1426.7317 | DQ22: 2924.3137 | DR22: 0 | DS22: 2924.3137 | DT22: 162.46187 | DU22: 162.46187 | DW22: 0 | DX22: 3645.8808 | DY22: 693.00008 | DZ22: 0 | EA22: 0 | EB22: 1553.6723 | EC22: 0 | ED22: 0 | EE22: 0 | EF22: 847.5 | EG22: 0 | EH22: 6726.567 | EI22: 0 | EJ22: 3645.8808 | EK22: 1553.6723 | EL22: 847.5 | EM22: 735.835 | EN22: 0 | EO22: 8267.0671 | EP22: 0 | ER22: 807.816 | ES22: 1591.4647 | ET22: =(ES22+ER22)/($E$2+$E$3) -> 0.083404857 | EU22: 0 | EV22: 149.622 | EW22: =(EU22+EV22)/($J$2+$J$3) -> 0.081939939 | EY22: 0 | EZ22: 3156.57 | FA22: =(EY22+EZ22)/($E$12+$E$14) -> 0.23203283 | FB22: 4613 | FC22: =FB22/$J$10 -> 1 | FF22: 0 | FG22: 0 | FH22: =(FF22+FG22)/($E$13+$E$15) -> 0 | FI22: 0 | FJ22: =FI22/$J$11 -> 0 | FL22: 7873 | FM22: =FL22/$E$11 -> 0.68245451 | FN22: 2591 | FO22: =FN22/$J$9 -> 0.82634349 | FQ22: 278 | FR22: 367.01 | FS22: =(FQ22+FR22)/($J$8+$J$12) -> 0.81843675 | FT22: =FQ22+FR22 -> 645.01 | FV22: =FW22+FX22-FY22-GA22 -> 1223.6723 | FW22: 1553.6723 | FX22: 0 | FY22: 330 | FZ22: =FV22/1553.6723 -> 0.78759999 | GA22: 0 | GC22: 4180.2123 | GD22: =GC22/32600 -> 0.12822737 | GE22: 1040.3836 | GF22: =GE22/13478 -> 0.077191244 | GH22: 5945.5719 | GI22: 1508.2537 | GK22: 0.257 | GL22: 0.84 | GM22: =-GN22 -> 2618.1494 | GN22: -2618.1494 | GO22: =GM22-1517.77579117 -> 1100.3736 | GP22: =GO22/1492.3021 -> 0.73736651 | GR22: 6041.0902 | GS22: 1396.2889 | GV22: 3776.591 | GW22: 1100.3736 | GX22: =MAX(GW:GW) -> 1537.0311 | GY22: =GW22/GX22 -> 0.71590848
P23: 21 | Q23: 0 | R23: 0 | S23: 0 | T23: 0 | U23: 0 | V23: 0 | W23: 0 | X23: 0 | Y23: 0 | Z23: 0 | AA23: 0 | AB23: 0 | AC23: 0 | AD23: 0 | AF23: 21 | AG23: 13883.969 | AH23: 786.6 | AI23: 171 | AJ23: 0.156 | AK23: 0.342 | AL23: 0.342 | AM23: 98.838 | AN23: 1327.3704 | AO23: 0.153 | AP23: 0.114 | AQ23: 30551 | AR23: 19507.725 | AS23: 0.685 | AT23: 0.831 | AV23: 1049.093 | AW23: 0.42599994 | AX23: 872.118 | AY23: 0.54269944 | AZ23: 1121.478 | BA23: 0.57843924 | BC23: 51358.995 | BD23: 0.73770492 | BF23: 5945.572 | BG23: 0 | BH23: 0 | BI23: 0.18237951 | BJ23: 0 | BK23: 0 | BL23: 0 | BM23: 0 | BN23: 1508.254 | BO23: 0.11190488 | BP23: 0 | BQ23: 7668 | BR23: 649.83928 | BT23: -700 | BU23: 0 | BV23: 4485 | BW23: 4485 | BX23: 0 | BY23: 0 | BZ23: 5000 | CA23: 5000 | CB23: -5300 | CC23: 0 | CD23: -4000 | CE23: 0 | CF23: 2042.3664 | CG23: 2042.3664 | CH23: 9657.8253 | CI23: 9657.8253 | CJ23: 21185.192 | CL23: -700 | CM23: 700 | CN23: 4485 | CO23: 0 | CP23: 0 | CQ23: 0 | CR23: 5000 | CS23: 0 | CT23: -5300 | CU23: 5300 | CV23: -4000 | CW23: 4000 | CX23: 2042.3664 | CY23: 0 | CZ23: 9657.8253 | DA23: 0 | DB23: 10000 | DD23: 39444.45 | DE23: 2243.464 | DF23: 1829.2846 | DG23: 43517.199 | DH23: 9191.05 | DI23: 54642.411 | DJ23: 5831 | DK23: 60473.411 | DM23: 870.591 | DN23: 10524.486 | DO23: 11395.077 | DP23: 1323.6196 | DQ23: 2916.0358 | DR23: 0 | DS23: 2916.0358 | DT23: 162.00199 | DU23: 162.00199 | DW23: 0 | DX23: 2601.4407 | DY23: 441.42008 | DZ23: 0 | EA23: 0 | EB23: 1553.6723 | EC23: 0 | ED23: 0 | EE23: 0 | EF23: 847.5 | EG23: 0 | EH23: 5941.9847 | EI23: 0 | EJ23: 2601.4407 | EK23: 1553.6723 | EL23: 847.5 | EM23: 735.835 | EN23: 0 | EO23: 7230.9048 | EP23: 0 | ER23: 841.475 | ES23: 1591.4647 | ET23: =(ES23+ER23)/($E$2+$E$3) -> 0.084574926 | EU23: 0 | EV23: 150.084 | EW23: =(EU23+EV23)/($J$2+$J$3) -> 0.082192951 | EY23: 10447.41 | EZ23: 3156.57 | FA23: =(EY23+EZ23)/($E$12+$E$14) -> 1 | FB23: 4613 | FC23: =FB23/$J$10 -> 1 | FF23: 0 | FG23: 0 | FH23: =(FF23+FG23)/($E$13+$E$15) -> 0 | FI23: 0 | FJ23: =FI23/$J$11 -> 0 | FL23: 7873 | FM23: =FL23/$E$11 -> 0.68245451 | FN23: 2591 | FO23: =FN23/$J$9 -> 0.82634349 | FQ23: 278 | FR23: 367.01 | FS23: =(FQ23+FR23)/($J$8+$J$12) -> 0.81843675 | FT23: =FQ23+FR23 -> 645.01 | FV23: =FW23+FX23-FY23-GA23 -> 1223.6723 | FW23: 1553.6723 | FX23: 0 | FY23: 330 | FZ23: =FV23/1553.6723 -> 0.78759999 | GA23: 0 | GC23: 4221.3561 | GD23: =GC23/32600 -> 0.12948945 | GE23: 1070.8603 | GF23: =GE23/13478 -> 0.079452466 | GH23: 6146.2825 | GI23: 1535.3559 | GK23: 0.257 | GL23: 0.84 | GM23: =-GN23 -> 2618.1494 | GN23: -2618.1494 | GO23: =GM23-1517.77579117 -> 1100.3736 | GP23: =GO23/1492.3021 -> 0.73736651 | GR23: 5887.6226 | GS23: 1465.3291 | GV23: 3776.591 | GW23: 1100.3736 | GX23: =MAX(GW:GW) -> 1537.0311 | GY23: =GW23/GX23 -> 0.71590848
P24: 22 | Q24: 0 | R24: 0 | S24: 0 | T24: 0 | U24: 0 | V24: 0 | W24: 0 | X24: 0 | Y24: 0 | Z24: 0 | AA24: 0 | AB24: 0 | AC24: 0 | AD24: 0 | AF24: 22 | AG24: 14417.968 | AH24: 765.9 | AI24: 166.5 | AJ24: 0.162 | AK24: 0.333 | AL24: 0.333 | AM24: 99.484 | AN24: 1327.3704 | AO24: 0.154 | AP24: 0.114 | AQ24: 30149.6 | AR24: 19202.55 | AS24: 0.676 | AT24: 0.818 | AV24: 1004.765 | AW24: 0.40799989 | AX24: 872.959 | AY24: 0.54322278 | AZ24: 1121.478 | BA24: 0.57843924 | BC24: 51358.995 | BD24: 0.73770492 | BF24: 6146.282 | BG24: 0 | BH24: 0 | BI24: 0.18853626 | BJ24: 0 | BK24: 0 | BL24: 0 | BM24: 0 | BN24: 1535.356 | BO24: 0.11391571 | BP24: 0 | BQ24: 7668 | BR24: 649.3794 | BT24: -700 | BU24: 0 | BV24: 4485 | BW24: 4485 | BX24: 0 | BY24: 0 | BZ24: 5000 | CA24: 5000 | CB24: -5300 | CC24: 0 | CD24: -4000 | CE24: 0 | CF24: 0 | CG24: 0 | CH24: 9732.1485 | CI24: 9732.1485 | CJ24: 19217.149 | CL24: -700 | CM24: 700 | CN24: 4485 | CO24: 0 | CP24: 0 | CQ24: 0 | CR24: 5000 | CS24: 0 | CT24: -5300 | CU24: 5300 | CV24: -4000 | CW24: 4000 | CX24: 0 | CY24: 0 | CZ24: 9732.1485 | DA24: 0 | DB24: 10000 | DD24: 37823.045 | DE24: 2313.441 | DF24: 1756.4524 | DG24: 41892.938 | DH24: 8729.903 | DI24: 53281.411 | DJ24: 5512 | DK24: 58793.411 | DM24: 752.793 | DN24: 10508.776 | DO24: 11261.569 | DP24: 1246.2856 | DQ24: 2907.758 | DR24: 0 | DS24: 2907.758 | DT24: 161.54211 | DU24: 161.54211 | DW24: 0 | DX24: 1557.0005 | DY24: 292.95784 | DZ24: 0 | EA24: 0 | EB24: 1553.6723 | EC24: 0 | ED24: 0 | EE24: 0 | EF24: 847.5 | EG24: 0 | EH24: 5054.2847 | EI24: 0 | EJ24: 1557.0005 | EK24: 1553.6723 | EL24: 847.5 | EM24: 735.835 | EN24: 0 | EO24: 6194.7426 | EP24: 0 | ER24: 845.639 | ES24: 1591.4647 | ET24: =(ES24+ER24)/($E$2+$E$3) -> 0.084719677 | EU24: 0 | EV24: 150.084 | EW24: =(EU24+EV24)/($J$2+$J$3) -> 0.082192951 | EY24: 4370.1045 | EZ24: 3156.57 | FA24: =(EY24+EZ24)/($E$12+$E$14) -> 0.55327003 | FB24: 4613 | FC24: =FB24/$J$10 -> 1 | FF24: 0 | FG24: 0 | FH24: =(FF24+FG24)/($E$13+$E$15) -> 0 | FI24: 0 | FJ24: =FI24/$J$11 -> 0 | FL24: 7873 | FM24: =FL24/$E$11 -> 0.68245451 | FN24: 2591 | FO24: =FN24/$J$9 -> 0.82634349 | FQ24: 278 | FR24: 367.01 | FS24: =(FQ24+FR24)/($J$8+$J$12) -> 0.81843675 | FT24: =FQ24+FR24 -> 645.01 | FV24: =FW24+FX24-FY24-GA24 -> 1223.6723 | FW24: 1553.6723 | FX24: 0 | FY24: 330 | FZ24: =FV24/1553.6723 -> 0.78759999 | GA24: 0 | GC24: 4363.8602 | GD24: =GC24/32600 -> 0.13386074 | GE24: 1090.1028 | GF24: =GE24/13478 -> 0.080880157 | GH24: 6571.3689 | GI24: 1480.5355 | GK24: 0.257 | GL24: 0.84 | GM24: =-GN24 -> 2618.1494 | GN24: -2618.1494 | GO24: =GM24-1517.77579117 -> 1100.3736 | GP24: =GO24/1492.3021 -> 0.73736651 | GR24: 5945.5719 | GS24: 1508.2537 | GV24: 3776.591 | GW24: 1100.3736 | GX24: =MAX(GW:GW) -> 1537.0311 | GY24: =GW24/GX24 -> 0.71590848
P25: 23 | Q25: 0 | R25: 0 | S25: 0 | T25: 0 | U25: 0 | V25: 0 | W25: 0 | X25: 0 | Y25: 0 | Z25: 0 | AA25: 0 | AB25: 0 | AC25: 0 | AD25: 0 | AF25: 23 | AG25: 15396.965 | AH25: 795.8 | AI25: 173 | AJ25: 0.173 | AK25: 0.346 | AL25: 0.346 | AM25: 94.962 | AN25: 1490.3808 | AO25: 0.147 | AP25: 0.128 | AQ25: 29569.8 | AR25: 18920.85 | AS25: 0.663 | AT25: 0.806 | AV25: 1012.153 | AW25: 0.41099989 | AX25: 880.584 | AY25: 0.54796764 | AZ25: 1121.478 | BA25: 0.57843924 | BC25: 51358.995 | BD25: 0.73770492 | BF25: 6571.369 | BG25: 0 | BH25: 0 | BI25: 0.20157574 | BJ25: 0 | BK25: 0 | BL25: 0 | BM25: 0 | BN25: 1480.535 | BO25: 0.10984827 | BP25: 0 | BQ25: 7668 | BR25: 648.91952 | BT25: -700 | BU25: 0 | BV25: 4485 | BW25: 4485 | BX25: 0 | BY25: 0 | BZ25: 0 | CA25: 0 | CB25: -5300 | CC25: 0 | CD25: -4000 | CE25: 0 | CF25: 0 | CG25: 0 | CH25: 10546.376 | CI25: 10546.376 | CJ25: 15031.376 | CL25: -700 | CM25: 700 | CN25: 4485 | CO25: 0 | CP25: 0 | CQ25: 0 | CR25: 0 | CS25: 0 | CT25: -5300 | CU25: 5300 | CV25: -4000 | CW25: 4000 | CX25: 0 | CY25: 0 | CZ25: 10546.376 | DA25: 0 | DB25: 10000 | DD25: 35535.332 | DE25: 2244.586 | DF25: 1767.0648 | DG25: 39546.983 | DH25: 8735.696 | DI25: 60671.411 | DJ25: 5654 | DK25: 66325.411 | DM25: 677.218 | DN25: 10493.066 | DO25: 11170.284 | DP25: 1194.7295 | DQ25: 2899.4801 | DR25: 0 | DS25: 2899.4801 | DT25: 161.08223 | DU25: 161.08223 | DW25: 0 | DX25: 2412.1128 | DY25: 544.53784 | DZ25: 0 | EA25: 0 | EB25: 1553.6723 | EC25: 0 | ED25: 0 | EE25: 0 | EF25: 847.5 | EG25: 0 | EH25: 5666.0949 | EI25: 0 | EJ25: 2412.1128 | EK25: 1553.6723 | EL25: 847.5 | EM25: 735.835 | EN25: 0 | EO25: 7058.1327 | EP25: 0 | ER25: 849.803 | ES25: 1591.4647 | ET25: =(ES25+ER25)/($E$2+$E$3) -> 0.084864428 | EU25: 0 | EV25: 150.084 | EW25: =(EU25+EV25)/($J$2+$J$3) -> 0.082192951 | EY25: 1901.5744 | EZ25: 3156.57 | FA25: =(EY25+EZ25)/($E$12+$E$14) -> 0.37181357 | FB25: 4613 | FC25: =FB25/$J$10 -> 1 | FF25: 0 | FG25: 0 | FH25: =(FF25+FG25)/($E$13+$E$15) -> 0 | FI25: 0 | FJ25: =FI25/$J$11 -> 0 | FL25: 7873 | FM25: =FL25/$E$11 -> 0.68245451 | FN25: 2591 | FO25: =FN25/$J$9 -> 0.82634349 | FQ25: 278 | FR25: 367.01 | FS25: =(FQ25+FR25)/($J$8+$J$12) -> 0.81843675 | FT25: =FQ25+FR25 -> 645.01 | FV25: =FW25+FX25-FY25-GA25 -> 1223.6723 | FW25: 1553.6723 | FX25: 0 | FY25: 330 | FZ25: =FV25/1553.6723 -> 0.78759999 | GA25: 0 | GC25: 4665.672 | GD25: =GC25/32600 -> 0.14311877 | GE25: 1051.1798 | GF25: =GE25/13478 -> 0.077992273 | GH25: 6957.9152 | GI25: 1406.8767 | GK25: 0.257 | GL25: 0.84 | GM25: =-GN25 -> 2618.1494 | GN25: -2618.1494 | GO25: =GM25-1517.77579117 -> 1100.3736 | GP25: =GO25/1492.3021 -> 0.73736651 | GR25: 6146.2825 | GS25: 1535.3559 | GV25: 3776.591 | GW25: 1100.3736 | GX25: =MAX(GW:GW) -> 1537.0311 | GY25: =GW25/GX25 -> 0.71590848
P26: 24 | Q26: 0 | R26: 0 | S26: 0 | T26: 0 | U26: 0 | V26: 0 | W26: 0 | X26: 0 | Y26: 0 | Z26: 0 | AA26: 0 | AB26: 0 | AC26: 0 | AD26: 0 | AF26: 24 | AG26: 16286.963 | AH26: 811.9 | AI26: 176.5 | AJ26: 0.183 | AK26: 0.353 | AL26: 0.353 | AM26: 88.502 | AN26: 1816.4016 | AO26: 0.137 | AP26: 0.156 | AQ26: 29391.4 | AR26: 18897.375 | AS26: 0.659 | AT26: 0.805 | AV26: 1004.765 | AW26: 0.40799989 | AX26: 890.729 | AY26: 0.55428065 | AZ26: 1121.478 | BA26: 0.57843924 | BC26: 51358.995 | BD26: 0.73770492 | BF26: 6957.915 | BG26: 0 | BH26: 0 | BI26: 0.21343298 | BJ26: 0 | BK26: 0 | BL26: 0 | BM26: 0 | BN26: 1406.877 | BO26: 0.10438322 | BP26: 0 | BQ26: 7668 | BR26: 648.91952 | BT26: -700 | BU26: 0 | BV26: 4485 | BW26: 4485 | BX26: 0 | BY26: 0 | BZ26: -4810.0725 | CA26: 0 | CB26: -5300 | CC26: 0 | CD26: -4000 | CE26: 0 | CF26: -4800 | CG26: 0 | CH26: 10858.562 | CI26: 10858.562 | CJ26: 15343.562 | CL26: -700 | CM26: 700 | CN26: 4485 | CO26: 0 | CP26: 0 | CQ26: 0 | CR26: -4810.0725 | CS26: 4810.0725 | CT26: -5300 | CU26: 5300 | CV26: -4000 | CW26: 4000 | CX26: -4800 | CY26: 4800 | CZ26: 10858.562 | DA26: 0 | DB26: 19610.073 | DD26: 33040.881 | DE26: 2151.831 | DF26: 1471.6368 | DG26: 36664.349 | DH26: 8425.489 | DI26: 58109.411 | DJ26: 5743 | DK26: 63852.411 | DM26: 646.517 | DN26: 10493.066 | DO26: 11139.583 | DP26: 1194.7295 | DQ26: 2899.4801 | DR26: 0 | DS26: 2899.4801 | DT26: 161.08223 | DU26: 161.08223 | DW26: 0 | DX26: 3457.0128 | DY26: 796.11784 | DZ26: 0 | EA26: 0 | EB26: 1553.6723 | EC26: 0 | ED26: 0 | EE26: 0 | EF26: 847.5 | EG26: 0 | EH26: 6459.4149 | EI26: 0 | EJ26: 3457.0128 | EK26: 1553.6723 | EL26: 847.5 | EM26: 735.835 | EN26: 0 | EO26: 8103.0327 | EP26: 0 | ER26: 837.311 | ES26: 1591.4647 | ET26: =(ES26+ER26)/($E$2+$E$3) -> 0.084430175 | EU26: 0 | EV26: 59.540188 | EW26: =(EU26+EV26)/($J$2+$J$3) -> 0.032606965 | EY26: 0 | EZ26: 3156.57 | FA26: =(EY26+EZ26)/($E$12+$E$14) -> 0.23203283 | FB26: 4613 | FC26: =FB26/$J$10 -> 1 | FF26: 0 | FG26: 0 | FH26: =(FF26+FG26)/($E$13+$E$15) -> 0 | FI26: 0 | FJ26: =FI26/$J$11 -> 0 | FL26: 7873 | FM26: =FL26/$E$11 -> 0.68245451 | FN26: 2591 | FO26: =FN26/$J$9 -> 0.82634349 | FQ26: 278 | FR26: 367.01 | FS26: =(FQ26+FR26)/($J$8+$J$12) -> 0.81843675 | FT26: =FQ26+FR26 -> 645.01 | FV26: =FW26+FX26-FY26-GA26 -> 1223.6723 | FW26: 1553.6723 | FX26: 0 | FY26: 330 | FZ26: =FV26/1553.6723 -> 0.78759999 | GA26: 0 | GC26: 4940.1196 | GD26: =GC26/32600 -> 0.15153741 | GE26: 998.88267 | GF26: =GE26/13478 -> 0.074112084 | GH26: 7269.6492 | GI26: 1319.4265 | GK26: 0.257 | GL26: 0.84 | GM26: =-GN26 -> 2618.1494 | GN26: -2618.1494 | GO26: =GM26-1517.77579117 -> 1100.3736 | GP26: =GO26/1492.3021 -> 0.73736651 | GR26: 6571.3689 | GS26: 1480.5355 | GV26: 3776.591 | GW26: 1100.3736 | GX26: =MAX(GW:GW) -> 1537.0311 | GY26: =GW26/GX26 -> 0.71590848
P27: 25 | Q27: 0 | R27: 0 | S27: 0 | T27: 0 | U27: 0 | V27: 0 | W27: 0 | X27: 0 | Y27: 0 | Z27: 0 | AA27: 0 | AB27: 0 | AC27: 0 | AD27: 0 | AF27: 25 | AG27: 16998.962 | AH27: 814.2 | AI27: 177 | AJ27: 0.191 | AK27: 0.354 | AL27: 0.354 | AM27: 80.75 | AN27: 2060.9172 | AO27: 0.125 | AP27: 0.177 | AQ27: 28410.2 | AR27: 18967.8 | AS27: 0.637 | AT27: 0.808 | AV27: 962.9 | AW27: 0.39099998 | AX27: 891.797 | AY27: 0.55494524 | AZ27: 1121.478 | BA27: 0.57843924 | BC27: 51358.995 | BD27: 0.73770492 | BF27: 7269.649 | BG27: 0 | BH27: 0 | BI27: 0.22299537 | BJ27: 0 | BK27: 0 | BL27: 0 | BM27: 0 | BN27: 1319.426 | BO27: 0.097894792 | BP27: 0 | BQ27: 7668 | BR27: 648.91853 | BT27: -700 | BU27: 0 | BV27: 4485 | BW27: 4485 | BX27: 0 | BY27: 0 | BZ27: -5000 | CA27: 0 | CB27: -5300 | CC27: 0 | CD27: -4000 | CE27: 0 | CF27: -4800 | CG27: 0 | CH27: 10465.699 | CI27: 10465.699 | CJ27: 14950.699 | CL27: -700 | CM27: 700 | CN27: 4485 | CO27: 0 | CP27: 0 | CQ27: 0 | CR27: -5000 | CS27: 5000 | CT27: -5300 | CU27: 5300 | CV27: -4000 | CW27: 4000 | CX27: -4800 | CY27: 4800 | CZ27: 10465.699 | DA27: 0 | DB27: 19800 | DD27: 31786.223 | DE27: 2078.295 | DF27: 1181.2321 | DG27: 35045.75 | DH27: 8278.491 | DI27: 51910.411 | DJ27: 5751 | DK27: 57661.411 | DM27: 683.41 | DN27: 10493.066 | DO27: 11176.476 | DP27: 1184.7913 | DQ27: 2899.4624 | DR27: 0 | DS27: 2899.4624 | DT27: 161.08124 | DU27: 161.08124 | DW27: 0 | DX27: 4501.9138 | DY27: 804.05041 | DZ27: 0 | EA27: 0 | EB27: 1553.6723 | EC27: 0 | ED27: 149.28616 | EE27: 0 | EF27: 847.5 | EG27: 0 | EH27: 7347.1149 | EI27: 0 | EJ27: 4501.9138 | EK27: 1553.6723 | EL27: 847.5 | EM27: 735.835 | EN27: 0 | EO27: 9147.9514 | EP27: 0 | ER27: 820.308 | ES27: 1591.4647 | ET27: =(ES27+ER27)/($E$2+$E$3) -> 0.08383911 | EU27: 0 | EV27: 0 | EW27: =(EU27+EV27)/($J$2+$J$3) -> 0 | EY27: 0 | EZ27: 3156.57 | FA27: =(EY27+EZ27)/($E$12+$E$14) -> 0.23203283 | FB27: 4613 | FC27: =FB27/$J$10 -> 1 | FF27: 0 | FG27: 0 | FH27: =(FF27+FG27)/($E$13+$E$15) -> 0 | FI27: 0 | FJ27: =FI27/$J$11 -> 0 | FL27: 7873 | FM27: =FL27/$E$11 -> 0.68245451 | FN27: 2591 | FO27: =FN27/$J$9 -> 0.82634349 | FQ27: 278 | FR27: 367.01 | FS27: =(FQ27+FR27)/($J$8+$J$12) -> 0.81843675 | FT27: =FQ27+FR27 -> 645.01 | FV27: =FW27+FX27-FY27-GA27 -> 1223.6723 | FW27: 1553.6723 | FX27: 0 | FY27: 330 | FZ27: =FV27/1553.6723 -> 0.78759999 | GA27: 0 | GC27: 5161.4508 | GD27: =GC27/32600 -> 0.15832671 | GE27: 936.79246 | GF27: =GE27/13478 -> 0.069505302 | GH27: 7015.8772 | GI27: 1240.1715 | GK27: 0.257 | GL27: 0.84 | GM27: =-GN27 -> 2710.9561 | GN27: -2710.9561 | GO27: =GM27-1517.77579117 -> 1193.1803 | GP27: =GO27/1492.3021 -> 0.79955681 | GR27: 6957.9152 | GS27: 1406.8767 | GV27: 3776.591 | GW27: 1193.1803 | GX27: =MAX(GW:GW) -> 1537.0311 | GY27: =GW27/GX27 -> 0.77628899
P28: 26 | Q28: 0 | R28: 0 | S28: 0 | T28: 0 | U28: 0 | V28: 0 | W28: 0 | X28: 0 | Y28: 0 | Z28: 0 | AA28: 0 | AB28: 0 | AC28: 0 | AD28: 0 | AF28: 26 | AG28: 16464.963 | AH28: 795.8 | AI28: 173 | AJ28: 0.185 | AK28: 0.346 | AL28: 0.346 | AM28: 72.998 | AN28: 2130.7788 | AO28: 0.113 | AP28: 0.183 | AQ28: 28544 | AR28: 19460.775 | AS28: 0.64 | AT28: 0.829 | AV28: 953.049 | AW28: 0.38699983 | AX28: 890.97 | AY28: 0.55443062 | AZ28: 1121.478 | BA28: 0.57843924 | BC28: 51358.995 | BD28: 0.73770492 | BF28: 7015.877 | BG28: 0 | BH28: 0 | BI28: 0.21521095 | BJ28: 0 | BK28: 0 | BL28: 0 | BM28: 0 | BN28: 1240.171 | BO28: 0.092014468 | BP28: 0 | BQ28: 7668 | BR28: 648.91853 | BT28: -700 | BU28: 0 | BV28: 4485 | BW28: 4485 | BX28: 0 | BY28: 0 | BZ28: -5000 | CA28: 0 | CB28: -5300 | CC28: 0 | CD28: -4000 | CE28: 0 | CF28: -4800 | CG28: 0 | CH28: 10670.13 | CI28: 10670.13 | CJ28: 15155.13 | CL28: -700 | CM28: 700 | CN28: 4485 | CO28: 0 | CP28: 0 | CQ28: 0 | CR28: -5000 | CS28: 5000 | CT28: -5300 | CU28: 5300 | CV28: -4000 | CW28: 4000 | CX28: -4800 | CY28: 4800 | CZ28: 10670.13 | DA28: 0 | DB28: 19800 | DD28: 30001.379 | DE28: 2007.146 | DF28: 902.25762 | DG28: 32910.783 | DH28: 7875.855 | DI28: 51609.411 | DJ28: 5689 | DK28: 57298.411 | DM28: 705.694 | DN28: 10493.066 | DO28: 11198.76 | DP28: 1184.7913 | DQ28: 2899.4624 | DR28: 0 | DS28: 2899.4624 | DT28: 161.08124 | DU28: 161.08124 | DW28: 0 | DX28: 5546.8138 | DY28: 927.6864 | DZ28: 0 | EA28: 0 | EB28: 1553.6723 | EC28: 0 | ED28: 1020.0662 | EE28: 0 | EF28: 847.5 | EG28: 0 | EH28: 7397.5989 | EI28: 0 | EJ28: 5546.8138 | EK28: 1553.6723 | EL28: 847.5 | EM28: 735.835 | EN28: 0 | EO28: 10192.851 | EP28: 0 | ER28: 803.652 | ES28: 1591.4647 | ET28: =(ES28+ER28)/($E$2+$E$3) -> 0.083260106 | EU28: 0 | EV28: 0 | EW28: =(EU28+EV28)/($J$2+$J$3) -> 0 | EY28: 0 | EZ28: 3156.57 | FA28: =(EY28+EZ28)/($E$12+$E$14) -> 0.23203283 | FB28: 4613 | FC28: =FB28/$J$10 -> 1 | FF28: 0 | FG28: 0 | FH28: =(FF28+FG28)/($E$13+$E$15) -> 0 | FI28: 0 | FJ28: =FI28/$J$11 -> 0 | FL28: 7873 | FM28: =FL28/$E$11 -> 0.68245451 | FN28: 2591 | FO28: =FN28/$J$9 -> 0.82634349 | FQ28: 278 | FR28: 367.01 | FS28: =(FQ28+FR28)/($J$8+$J$12) -> 0.81843675 | FT28: =FQ28+FR28 -> 645.01 | FV28: =FW28+FX28-FY28-GA28 -> 1223.6723 | FW28: 1553.6723 | FX28: 0 | FY28: 330 | FZ28: =FV28/1553.6723 -> 0.78759999 | GA28: 0 | GC28: 4981.2727 | GD28: =GC28/32600 -> 0.15279978 | GE28: 880.52141 | GF28: =GE28/13478 -> 0.065330272 | GH28: 6657.6699 | GI28: 1148.8398 | GK28: 0.257 | GL28: 0.84 | GM28: =-GN28 -> 2710.9561 | GN28: -2710.9561 | GO28: =GM28-1517.77579117 -> 1193.1803 | GP28: =GO28/1492.3021 -> 0.79955681 | GR28: 7269.6492 | GS28: 1319.4265 | GV28: 3776.591 | GW28: 1193.1803 | GX28: =MAX(GW:GW) -> 1537.0311 | GY28: =GW28/GX28 -> 0.77628899
P29: 27 | Q29: 0 | R29: 0 | S29: 0 | T29: 0 | U29: 0 | V29: 0 | W29: 0 | X29: 0 | Y29: 0 | Z29: 0 | AA29: 0 | AB29: 0 | AC29: 0 | AD29: 0 | AF29: 27 | AG29: 15574.965 | AH29: 763.6 | AI29: 166 | AJ29: 0.175 | AK29: 0.332 | AL29: 0.332 | AM29: 65.246 | AN29: 2130.7788 | AO29: 0.101 | AP29: 0.183 | AQ29: 28767 | AR29: 20141.55 | AS29: 0.645 | AT29: 0.858 | AV29: 953.049 | AW29: 0.38699983 | AX29: 889.765 | AY29: 0.55368077 | AZ29: 1121.478 | BA29: 0.57843924 | BC29: 51358.995 | BD29: 0.73770492 | BF29: 6657.67 | BG29: 0 | BH29: 0 | BI29: 0.20422301 | BJ29: 0 | BK29: 0 | BL29: 0 | BM29: 0 | BN29: 1148.84 | BO29: 0.085238166 | BP29: 0 | BQ29: 7668 | BR29: 648.91853 | BT29: -700 | BU29: 0 | BV29: 4485 | BW29: 4485 | BX29: 0 | BY29: 0 | BZ29: -5000 | CA29: 0 | CB29: -5300 | CC29: 0 | CD29: -4000 | CE29: 0 | CF29: -4800 | CG29: 0 | CH29: 9896.0287 | CI29: 9896.0287 | CJ29: 14381.029 | CL29: -700 | CM29: 700 | CN29: 4485 | CO29: 0 | CP29: 0 | CQ29: 0 | CR29: -5000 | CS29: 5000 | CT29: -5300 | CU29: 5300 | CV29: -4000 | CW29: 4000 | CX29: -4800 | CY29: 4800 | CZ29: 9896.0287 | DA29: 0 | DB29: 19800 | DD29: 28988.097 | DE29: 1969.221 | DF29: 1468.1493 | DG29: 32425.467 | DH29: 7514.993 | DI29: 49514.411 | DJ29: 5648 | DK29: 55162.411 | DM29: 746.85 | DN29: 10493.066 | DO29: 11239.916 | DP29: 1184.7913 | DQ29: 2899.4624 | DR29: 0 | DS29: 2899.4624 | DT29: 161.08124 | DU29: 161.08124 | DW29: 0 | DX29: 5747.0737 | DY29: 876.82601 | DZ29: 0 | EA29: 0 | EB29: 1553.6723 | EC29: 0 | ED29: 1271.1864 | EE29: 0 | EF29: 847.5 | EG29: 0 | EH29: 7397.5989 | EI29: 0 | EJ29: 5747.0737 | EK29: 1553.6723 | EL29: 847.5 | EM29: 735.835 | EN29: 0 | EO29: 10393.111 | EP29: 0 | ER29: 807.816 | ES29: 1591.4647 | ET29: =(ES29+ER29)/($E$2+$E$3) -> 0.083404857 | EU29: 0 | EV29: 0 | EW29: =(EU29+EV29)/($J$2+$J$3) -> 0 | EY29: 0 | EZ29: 3156.57 | FA29: =(EY29+EZ29)/($E$12+$E$14) -> 0.23203283 | FB29: 4613 | FC29: =FB29/$J$10 -> 1 | FF29: 0 | FG29: 0 | FH29: =(FF29+FG29)/($E$13+$E$15) -> 0 | FI29: 0 | FJ29: =FI29/$J$11 -> 0 | FL29: 7873 | FM29: =FL29/$E$11 -> 0.68245451 | FN29: 2591 | FO29: =FN29/$J$9 -> 0.82634349 | FQ29: 278 | FR29: 367.01 | FS29: =(FQ29+FR29)/($J$8+$J$12) -> 0.81843675 | FT29: =FQ29+FR29 -> 645.01 | FV29: =FW29+FX29-FY29-GA29 -> 1223.6723 | FW29: 1553.6723 | FX29: 0 | FY29: 330 | FZ29: =FV29/1553.6723 -> 0.78759999 | GA29: 0 | GC29: 4726.9457 | GD29: =GC29/32600 -> 0.14499833 | GE29: 815.6764 | GF29: =GE29/13478 -> 0.060519098 | GH29: 6235.2841 | GI29: 1068.1687 | GK29: 0.257 | GL29: 0.84 | GM29: =-GN29 -> 2710.9561 | GN29: -2710.9561 | GO29: =GM29-1517.77579117 -> 1193.1803 | GP29: =GO29/1492.3021 -> 0.79955681 | GR29: 7015.8772 | GS29: 1240.1715 | GV29: 3776.591 | GW29: 1193.1803 | GX29: =MAX(GW:GW) -> 1537.0311 | GY29: =GW29/GX29 -> 0.77628899
P30: 28 | Q30: 0 | R30: 0 | S30: 0 | T30: 0 | U30: 0 | V30: 0 | W30: 0 | X30: 0 | Y30: 0 | Z30: 0 | AA30: 0 | AB30: 0 | AC30: 0 | AD30: 0 | AF30: 28 | AG30: 14595.967 | AH30: 763.6 | AI30: 166 | AJ30: 0.164 | AK30: 0.332 | AL30: 0.332 | AM30: 59.432 | AN30: 2095.848 | AO30: 0.092 | AP30: 0.18 | AQ30: 29525.2 | AR30: 20892.75 | AS30: 0.662 | AT30: 0.89 | AV30: 953.049 | AW30: 0.38699983 | AX30: 883.247 | AY30: 0.54962477 | AZ30: 1121.478 | BA30: 0.57843924 | BC30: 51358.995 | BD30: 0.73770492 | BF30: 6235.284 | BG30: 0 | BH30: 0 | BI30: 0.19126638 | BJ30: 0 | BK30: 0 | BL30: 0 | BM30: 0 | BN30: 1068.169 | BO30: 0.079252782 | BP30: 0 | BQ30: 7668 | BR30: 648.91853 | BT30: -700 | BU30: 0 | BV30: 4485 | BW30: 4485 | BX30: 0 | BY30: 0 | BZ30: -5000 | CA30: 0 | CB30: -5300 | CC30: 0 | CD30: -4000 | CE30: 0 | CF30: -4800 | CG30: 0 | CH30: 9871.5661 | CI30: 9871.5661 | CJ30: 14356.566 | CL30: -700 | CM30: 700 | CN30: 4485 | CO30: 0 | CP30: 0 | CQ30: 0 | CR30: -5000 | CS30: 5000 | CT30: -5300 | CU30: 5300 | CV30: -4000 | CW30: 4000 | CX30: -4800 | CY30: 4800 | CZ30: 9871.5661 | DA30: 0 | DB30: 19800 | DD30: 28649.393 | DE30: 1950.888 | DF30: 2313.1031 | DG30: 32913.384 | DH30: 7359.599 | DI30: 47611.411 | DJ30: 5415 | DK30: 53026.411 | DM30: 827.44 | DN30: 10493.066 | DO30: 11320.506 | DP30: 1184.7913 | DQ30: 2899.4624 | DR30: 0 | DS30: 2899.4624 | DT30: 161.08124 | DU30: 161.08124 | DW30: 0 | DX30: 4702.1737 | DY30: 804.06777 | DZ30: 0 | EA30: 0 | EB30: 1553.6723 | EC30: 0 | ED30: 400.40644 | EE30: 0 | EF30: 847.5 | EG30: 0 | EH30: 7296.2371 | EI30: 0 | EJ30: 4702.1737 | EK30: 1553.6723 | EL30: 847.5 | EM30: 735.835 | EN30: 0 | EO30: 9348.2113 | EP30: 0 | ER30: 807.816 | ES30: 1591.4647 | ET30: =(ES30+ER30)/($E$2+$E$3) -> 0.083404857 | EU30: 0 | EV30: 0 | EW30: =(EU30+EV30)/($J$2+$J$3) -> 0 | EY30: 0 | EZ30: 3156.57 | FA30: =(EY30+EZ30)/($E$12+$E$14) -> 0.23203283 | FB30: 4613 | FC30: =FB30/$J$10 -> 1 | FF30: 0 | FG30: 0 | FH30: =(FF30+FG30)/($E$13+$E$15) -> 0 | FI30: 0 | FJ30: =FI30/$J$11 -> 0 | FL30: 7873 | FM30: =FL30/$E$11 -> 0.68245451 | FN30: 2591 | FO30: =FN30/$J$9 -> 0.82634349 | FQ30: 278 | FR30: 367.01 | FS30: =(FQ30+FR30)/($J$8+$J$12) -> 0.81843675 | FT30: =FQ30+FR30 -> 645.01 | FV30: =FW30+FX30-FY30-GA30 -> 1223.6723 | FW30: 1553.6723 | FX30: 0 | FY30: 330 | FZ30: =FV30/1553.6723 -> 0.78759999 | GA30: 0 | GC30: 4427.0516 | GD30: =GC30/32600 -> 0.13579913 | GE30: 758.39999 | GF30: =GE30/13478 -> 0.056269475 | GH30: 5922.4553 | GI30: 1000.4831 | GK30: 0.257 | GL30: 0.84 | GM30: =-GN30 -> 2710.9561 | GN30: -2710.9561 | GO30: =GM30-1517.77579117 -> 1193.1803 | GP30: =GO30/1492.3021 -> 0.79955681 | GR30: 6657.6699 | GS30: 1148.8398 | GV30: 3776.591 | GW30: 1193.1803 | GX30: =MAX(GW:GW) -> 1537.0311 | GY30: =GW30/GX30 -> 0.77628899
P31: 29 | Q31: 0 | R31: 0 | S31: 0 | T31: 0 | U31: 0 | V31: 0 | W31: 0 | X31: 0 | Y31: 0 | Z31: 0 | AA31: 0 | AB31: 0 | AC31: 0 | AD31: 0 | AF31: 29 | AG31: 13883.969 | AH31: 777.4 | AI31: 169 | AJ31: 0.156 | AK31: 0.338 | AL31: 0.338 | AM31: 54.264 | AN31: 2130.7788 | AO31: 0.084 | AP31: 0.183 | AQ31: 30060.4 | AR31: 21057.075 | AS31: 0.674 | AT31: 0.897 | AV31: 953.049 | AW31: 0.38699983 | AX31: 873.609 | AY31: 0.54362726 | AZ31: 1121.478 | BA31: 0.57843924 | BC31: 51358.995 | BD31: 0.73770492 | BF31: 5922.455 | BG31: 0 | BH31: 0 | BI31: 0.1816704 | BJ31: 0 | BK31: 0 | BL31: 0 | BM31: 0 | BN31: 1000.483 | BO31: 0.074230821 | BP31: 0 | BQ31: 7668 | BR31: 649.37842 | BT31: -700 | BU31: 0 | BV31: 4485 | BW31: 4485 | BX31: 0 | BY31: 0 | BZ31: -5000 | CA31: 0 | CB31: -5300 | CC31: 0 | CD31: -4000 | CE31: 0 | CF31: -4800 | CG31: 0 | CH31: 13746.922 | CI31: 13746.922 | CJ31: 18231.922 | CL31: -700 | CM31: 700 | CN31: 4485 | CO31: 0 | CP31: 0 | CQ31: 0 | CR31: -5000 | CS31: 5000 | CT31: -5300 | CU31: 5300 | CV31: -4000 | CW31: 4000 | CX31: -4800 | CY31: 4800 | CZ31: 13746.922 | DA31: 0 | DB31: 19800 | DD31: 29466.87 | DE31: 1944.563 | DF31: 2597.959 | DG31: 34009.392 | DH31: 7340.927 | DI31: 47310.411 | DJ31: 5372 | DK31: 52682.411 | DM31: 974.066 | DN31: 10508.776 | DO31: 11482.842 | DP31: 1184.7913 | DQ31: 2907.7402 | DR31: 0 | DS31: 2907.7402 | DT31: 161.54112 | DU31: 161.54112 | DW31: 0 | DX31: 3656.8138 | DY31: 730.5432 | DZ31: 0 | EA31: 0 | EB31: 1553.6723 | EC31: 0 | ED31: 0 | EE31: 0 | EF31: 847.5 | EG31: 0 | EH31: 6716.5304 | EI31: 0 | EJ31: 3656.8138 | EK31: 1553.6723 | EL31: 847.5 | EM31: 735.835 | EN31: 0 | EO31: 8294.5736 | EP31: 0 | ER31: 811.98 | ES31: 1591.4647 | ET31: =(ES31+ER31)/($E$2+$E$3) -> 0.083549608 | EU31: 0 | EV31: 0 | EW31: =(EU31+EV31)/($J$2+$J$3) -> 0 | EY31: 0 | EZ31: 3156.57 | FA31: =(EY31+EZ31)/($E$12+$E$14) -> 0.23203283 | FB31: 4613 | FC31: =FB31/$J$10 -> 1 | FF31: 0 | FG31: 0 | FH31: =(FF31+FG31)/($E$13+$E$15) -> 0 | FI31: 0 | FJ31: =FI31/$J$11 -> 0 | FL31: 7873 | FM31: =FL31/$E$11 -> 0.68245451 | FN31: 2591 | FO31: =FN31/$J$9 -> 0.82634349 | FQ31: 278 | FR31: 367.01 | FS31: =(FQ31+FR31)/($J$8+$J$12) -> 0.81843675 | FT31: =FQ31+FR31 -> 645.01 | FV31: =FW31+FX31-FY31-GA31 -> 1223.6723 | FW31: 1553.6723 | FX31: 0 | FY31: 330 | FZ31: =FV31/1553.6723 -> 0.78759999 | GA31: 0 | GC31: 4204.943 | GD31: =GC31/32600 -> 0.12898598 | GE31: 710.34293 | GF31: =GE31/13478 -> 0.052703883 | GH31: 5629.3384 | GI31: 923.51061 | GK31: 0.257 | GL31: 0.84 | GM31: =-GN31 -> 2710.9561 | GN31: -2710.9561 | GO31: =GM31-1517.77579117 -> 1193.1803 | GP31: =GO31/1492.3021 -> 0.79955681 | GR31: 6235.2841 | GS31: 1068.1687 | GV31: 3776.591 | GW31: 1193.1803 | GX31: =MAX(GW:GW) -> 1537.0311 | GY31: =GW31/GX31 -> 0.77628899
P32: 30 | Q32: 0 | R32: 0 | S32: 0 | T32: 0 | U32: 0 | V32: 0 | W32: 0 | X32: 0 | Y32: 0 | Z32: 0 | AA32: 0 | AB32: 0 | AC32: 0 | AD32: 0 | AF32: 30 | AG32: 13171.97 | AH32: 784.3 | AI32: 170.5 | AJ32: 0.148 | AK32: 0.341 | AL32: 0.341 | AM32: 50.388 | AN32: 2154.066 | AO32: 0.078 | AP32: 0.185 | AQ32: 30818.6 | AR32: 21104.025 | AS32: 0.691 | AT32: 0.899 | AV32: 953.049 | AW32: 0.38699983 | AX32: 868.929 | AY32: 0.540715 | AZ32: 1121.478 | BA32: 0.57843924 | BC32: 51358.995 | BD32: 0.73770492 | BF32: 5629.338 | BG32: 0 | BH32: 0 | BI32: 0.17267908 | BJ32: 0 | BK32: 0 | BL32: 0 | BM32: 0 | BN32: 923.511 | BO32: 0.068519884 | BP32: 0 | BQ32: 7668 | BR32: 650.29818 | BT32: -700 | BU32: 0 | BV32: 4485 | BW32: 4485 | BX32: 0 | BY32: 0 | BZ32: -5000 | CA32: 0 | CB32: -5300 | CC32: 0 | CD32: -4000 | CE32: 0 | CF32: -4800 | CG32: 0 | CH32: 11246.939 | CI32: 11246.939 | CJ32: 15731.939 | CL32: -700 | CM32: 700 | CN32: 4485 | CO32: 0 | CP32: 0 | CQ32: 0 | CR32: -5000 | CS32: 5000 | CT32: -5300 | CU32: 5300 | CV32: -4000 | CW32: 4000 | CX32: -4800 | CY32: 4800 | CZ32: 11246.939 | DA32: 0 | DB32: 19800 | DD32: 31665.787 | DE32: 1959.203 | DF32: 2814.0394 | DG32: 36439.029 | DH32: 7482.491 | DI32: 49387.411 | DJ32: 5331 | DK32: 54718.411 | DM32: 1200.165 | DN32: 10540.196 | DO32: 11740.361 | DP32: 1282.7478 | DQ32: 2924.296 | DR32: 0 | DS32: 2924.296 | DT32: 162.46089 | DU32: 162.46089 | DW32: 0 | DX32: 2610.994 | DY32: 478.9632 | DZ32: 0 | EA32: 0 | EB32: 1553.6723 | EC32: 0 | ED32: 0 | EE32: 0 | EF32: 847.5 | EG32: 0 | EH32: 5905.7349 | EI32: 0 | EJ32: 2610.994 | EK32: 1553.6723 | EL32: 847.5 | EM32: 735.835 | EN32: 0 | EO32: 7232.1981 | EP32: 0 | ER32: 824.472 | ES32: 1591.4647 | ET32: =(ES32+ER32)/($E$2+$E$3) -> 0.08398386 | EU32: 0 | EV32: 150.084 | EW32: =(EU32+EV32)/($J$2+$J$3) -> 0.082192951 | EY32: 0 | EZ32: 3156.57 | FA32: =(EY32+EZ32)/($E$12+$E$14) -> 0.23203283 | FB32: 4613 | FC32: =FB32/$J$10 -> 1 | FF32: 0 | FG32: 0 | FH32: =(FF32+FG32)/($E$13+$E$15) -> 0 | FI32: 0 | FJ32: =FI32/$J$11 -> 0 | FL32: 7873 | FM32: =FL32/$E$11 -> 0.68245451 | FN32: 2591 | FO32: =FN32/$J$9 -> 0.82634349 | FQ32: 278 | FR32: 367.01 | FS32: =(FQ32+FR32)/($J$8+$J$12) -> 0.81843675 | FT32: =FQ32+FR32 -> 645.01 | FV32: =FW32+FX32-FY32-GA32 -> 1223.6723 | FW32: 1553.6723 | FX32: 0 | FY32: 330 | FZ32: =FV32/1553.6723 -> 0.78759999 | GA32: 0 | GC32: 3996.83 | GD32: =GC32/32600 -> 0.12260215 | GE32: 655.69281 | GF32: =GE32/13478 -> 0.048649118 | GH32: 5083.9085 | GI32: 891.1858 | GK32: 0.257 | GL32: 0.84 | GM32: =-GN32 -> 2710.9561 | GN32: -2710.9561 | GO32: =GM32-1517.77579117 -> 1193.1803 | GP32: =GO32/1492.3021 -> 0.79955681 | GR32: 5922.4553 | GS32: 1000.4831 | GV32: 3776.591 | GW32: 1193.1803 | GX32: =MAX(GW:GW) -> 1537.0311 | GY32: =GW32/GX32 -> 0.77628899
P33: 31 | Q33: 0 | R33: 0 | S33: 0 | T33: 0 | U33: 0 | V33: 0 | W33: 0 | X33: 0 | Y33: 0 | Z33: 0 | AA33: 0 | AB33: 0 | AC33: 0 | AD33: 0 | AF33: 31 | AG33: 11925.973 | AH33: 802.7 | AI33: 174.5 | AJ33: 0.134 | AK33: 0.349 | AL33: 0.349 | AM33: 49.096 | AN33: 2119.1352 | AO33: 0.076 | AP33: 0.182 | AQ33: 31799.8 | AR33: 21268.35 | AS33: 0.713 | AT33: 0.906 | AV33: 962.9 | AW33: 0.39099998 | AX33: 886.813 | AY33: 0.55184381 | AZ33: 1121.478 | BA33: 0.57843924 | BC33: 51358.995 | BD33: 0.73770492 | BF33: 5083.909 | BG33: 0 | BH33: 0 | BI33: 0.15594813 | BJ33: 0 | BK33: 0 | BL33: 0 | BM33: 0 | BN33: 891.186 | BO33: 0.066121531 | BP33: 0 | BQ33: 7668 | BR33: 650.75806 | BT33: -700 | BU33: 0 | BV33: 4485 | BW33: 4485 | BX33: 0 | BY33: 0 | BZ33: -5000 | CA33: 0 | CB33: -5300 | CC33: 0 | CD33: -4000 | CE33: 0 | CF33: -4800 | CG33: 0 | CH33: 9449.636 | CI33: 9449.636 | CJ33: 13934.636 | CL33: -700 | CM33: 700 | CN33: 4485 | CO33: 0 | CP33: 0 | CQ33: 0 | CR33: -5000 | CS33: 5000 | CT33: -5300 | CU33: 5300 | CV33: -4000 | CW33: 4000 | CX33: -4800 | CY33: 4800 | CZ33: 9449.636 | DA33: 0 | DB33: 19800 | DD33: 34767.924 | DE33: 2026.588 | DF33: 3569.1876 | DG33: 40363.7 | DH33: 7854.13 | DI33: 52837.411 | DJ33: 4997 | DK33: 57834.411 | DM33: 1269.197 | DN33: 10555.906 | DO33: 11825.103 | DP33: 1380.7043 | DQ33: 2932.5738 | DR33: 0 | DS33: 2932.5738 | DT33: 162.92077 | DU33: 162.92077 | DW33: 0 | DX33: 2600.5209 | DY33: 441.42008 | DZ33: 0 | EA33: 0 | EB33: 1553.6723 | EC33: 0 | ED33: 0 | EE33: 0 | EF33: 847.5 | EG33: 0 | EH33: 5924.527 | EI33: 0 | EJ33: 2600.5209 | EK33: 1553.6723 | EL33: 847.5 | EM33: 735.835 | EN33: 0 | EO33: 7213.4471 | EP33: 0 | ER33: 875.134 | ES33: 1591.4647 | ET33: =(ES33+ER33)/($E$2+$E$3) -> 0.085744995 | EU33: 0 | EV33: 151.932 | EW33: =(EU33+EV33)/($J$2+$J$3) -> 0.083205002 | EY33: 0 | EZ33: 3156.57 | FA33: =(EY33+EZ33)/($E$12+$E$14) -> 0.23203283 | FB33: 4613 | FC33: =FB33/$J$10 -> 1 | FF33: 0 | FG33: 0 | FH33: =(FF33+FG33)/($E$13+$E$15) -> 0 | FI33: 0 | FJ33: =FI33/$J$11 -> 0 | FL33: 7873 | FM33: =FL33/$E$11 -> 0.68245451 | FN33: 2591 | FO33: =FN33/$J$9 -> 0.82634349 | FQ33: 278 | FR33: 367.01 | FS33: =(FQ33+FR33)/($J$8+$J$12) -> 0.81843675 | FT33: =FQ33+FR33 -> 645.01 | FV33: =FW33+FX33-FY33-GA33 -> 1223.6723 | FW33: 1553.6723 | FX33: 0 | FY33: 330 | FZ33: =FV33/1553.6723 -> 0.78759999 | GA33: 0 | GC33: 3609.5754 | GD33: =GC33/32600 -> 0.11072317 | GE33: 632.74206 | GF33: =GE33/13478 -> 0.046946287 | GH33: 4379.7501 | GI33: 916.97151 | GK33: 0.257 | GL33: 0.84 | GM33: =-GN33 -> 2710.9561 | GN33: -2710.9561 | GO33: =GM33-1517.77579117 -> 1193.1803 | GP33: =GO33/1492.3021 -> 0.79955681 | GR33: 5629.3384 | GS33: 923.51061 | GV33: 3776.591 | GW33: 1193.1803 | GX33: =MAX(GW:GW) -> 1537.0311 | GY33: =GW33/GX33 -> 0.77628899
P34: 32 | Q34: 0 | R34: 0 | S34: 0 | T34: 0 | U34: 0 | V34: 0 | W34: 0 | X34: 0 | Y34: 0 | Z34: 0 | AA34: 0 | AB34: 0 | AC34: 0 | AD34: 0 | AF34: 32 | AG34: 10234.977 | AH34: 816.5 | AI34: 177.5 | AJ34: 0.115 | AK34: 0.355 | AL34: 0.355 | AM34: 51.034 | AN34: 1921.194 | AO34: 0.079 | AP34: 0.165 | AQ34: 32736.4 | AR34: 21244.875 | AS34: 0.734 | AT34: 0.905 | AV34: 1036.78 | AW34: 0.42100006 | AX34: 959.124 | AY34: 0.59684132 | AZ34: 1121.478 | BA34: 0.57843924 | BC34: 51358.995 | BD34: 0.73770492 | BF34: 4379.75 | BG34: 0 | BH34: 0 | BI34: 0.13434816 | BJ34: 0 | BK34: 0 | BL34: 0 | BM34: 0 | BN34: 916.972 | BO34: 0.068034723 | BP34: 0 | BQ34: 7668 | BR34: 651.21794 | BT34: -700 | BU34: 0 | BV34: 4485 | BW34: 4485 | BX34: 0 | BY34: 0 | BZ34: -5000 | CA34: 0 | CB34: -5300 | CC34: 0 | CD34: -4000 | CE34: 0 | CF34: -4800 | CG34: 0 | CH34: 8886.8793 | CI34: 8886.8793 | CJ34: 13371.879 | CL34: -700 | CM34: 700 | CN34: 4485 | CO34: 0 | CP34: 0 | CQ34: 0 | CR34: -5000 | CS34: 5000 | CT34: -5300 | CU34: 5300 | CV34: -4000 | CW34: 4000 | CX34: -4800 | CY34: 4800 | CZ34: 8886.8793 | DA34: 0 | DB34: 19800 | DD34: 37480.88 | DE34: 2138.437 | DF34: 3984.4755 | DG34: 43603.792 | DH34: 8412.123 | DI34: 54289.411 | DJ34: 5018 | DK34: 59307.411 | DM34: 1259.536 | DN34: 10571.616 | DO34: 11831.152 | DP34: 1473.5052 | DQ34: 2940.8517 | DR34: 0 | DS34: 2940.8517 | DT34: 163.38065 | DU34: 163.38065 | DW34: 0 | DX34: 3644.961 | DY34: 693.00008 | DZ34: 0 | EA34: 0 | EB34: 1553.6723 | EC34: 0 | ED34: 0 | EE34: 0 | EF34: 847.5 | EG34: 0 | EH34: 6709.1092 | EI34: 0 | EJ34: 3644.961 | EK34: 1553.6723 | EL34: 847.5 | EM34: 735.835 | EN34: 0 | EO34: 8249.6093 | EP34: 0 | ER34: 959.108 | ES34: 1591.4647 | ET34: =(ES34+ER34)/($E$2+$E$3) -> 0.088664137 | EU34: 0 | EV34: 166.518 | EW34: =(EU34+EV34)/($J$2+$J$3) -> 0.091192971 | EY34: 10447.41 | EZ34: 3156.57 | FA34: =(EY34+EZ34)/($E$12+$E$14) -> 1 | FB34: 4613 | FC34: =FB34/$J$10 -> 1 | FF34: 0 | FG34: 0 | FH34: =(FF34+FG34)/($E$13+$E$15) -> 0 | FI34: 0 | FJ34: =FI34/$J$11 -> 0 | FL34: 7873 | FM34: =FL34/$E$11 -> 0.68245451 | FN34: 2591 | FO34: =FN34/$J$9 -> 0.82634349 | FQ34: 278 | FR34: 367.01 | FS34: =(FQ34+FR34)/($J$8+$J$12) -> 0.81843675 | FT34: =FQ34+FR34 -> 645.01 | FV34: =FW34+FX34-FY34-GA34 -> 1223.6723 | FW34: 1553.6723 | FX34: 0 | FY34: 330 | FZ34: =FV34/1553.6723 -> 0.78759999 | GA34: 0 | GC34: 3109.6225 | GD34: =GC34/32600 -> 0.095387193 | GE34: 651.05012 | GF34: =GE34/13478 -> 0.048304654 | GH34: 4461.4411 | GI34: 955.51368 | GK34: 0.257 | GL34: 0.84 | GM34: =-GN34 -> 2710.9561 | GN34: -2710.9561 | GO34: =GM34-1517.77579117 -> 1193.1803 | GP34: =GO34/1492.3021 -> 0.79955681 | GR34: 5083.9085 | GS34: 891.1858 | GV34: 3776.591 | GW34: 1193.1803 | GX34: =MAX(GW:GW) -> 1537.0311 | GY34: =GW34/GX34 -> 0.77628899
... P149: 147 | Q149: 0 | R149: 0 | S149: 0 | T149: 0 | U149: 0 | V149: 0 | W149: 0 | X149: 0 | Y149: 0 | Z149: 0 | AA149: 0 | AB149: 0 | AC149: 0 | AD149: 0 | AF149: 147 | AG149: 53755.879 | AH149: 1978 | AI149: 430 | AJ149: 0.604 | AK149: 0.86 | AL149: 0.86 | AM149: 468.996 | AN149: 8755.9872 | AO149: 0.726 | AP149: 0.752 | AQ149: 33450 | AR149: 21150.975 | AS149: 0.75 | AT149: 0.901 | AV149: 886.558 | AW149: 0.36000016 | AX149: 926.037 | AY149: 0.57625202 | AZ149: 1121.478 | BA149: 0.57843924 | BC149: 53641.617 | BD149: 0.7704918 | BF149: 22964.167 | BG149: 0 | BH149: 0 | BI149: 0.7044223 | BJ149: 0 | BK149: 0 | BL149: 0 | BM149: 0 | BN149: 6507.533 | BO149: 0.48282631 | BP149: 0 | BQ149: 7668 | BR149: 0 | BT149: -700 | BU149: 0 | BV149: 4485 | BW149: 4485 | BX149: 0 | BY149: 0 | BZ149: -5000 | CA149: 0 | CB149: -5300 | CC149: 0 | CD149: -4000 | CE149: 0 | CF149: -4800 | CG149: 0 | CH149: 22339.959 | CI149: 22339.959 | CJ149: 26824.959 | CL149: -700 | CM149: 700 | CN149: 4485 | CO149: 0 | CP149: 0 | CQ149: 0 | CR149: -5000 | CS149: 5000 | CT149: -5300 | CU149: 5300 | CV149: -4000 | CW149: 4000 | CX149: -4800 | CY149: 4800 | CZ149: 22339.959 | DA149: 0 | DB149: 19800 | DD149: 27467.655 | DE149: 1992.927 | DF149: 1581.5953 | DG149: 31042.177 | DH149: 7143.91 | DI149: 51701.411 | DJ149: 8095 | DK149: 59796.411 | DM149: 752.068 | DN149: 10490.399 | DO149: 11242.467 | DP149: 1455.3989 | DQ149: 2897.8864 | DR149: 463.24924 | DS149: 3361.1356 | DT149: 160.99369 | DU149: 160.99369 | DW149: 0 | DX149: 6779.661 | DY149: 1447.7401 | DZ149: 0 | EA149: 0 | EB149: 244.84131 | EC149: 0 | ED149: 1271.1864 | EE149: 0 | EF149: 847.5 | EG149: 0 | EH149: 7397.5989 | EI149: 0 | EJ149: 6779.661 | EK149: 244.84131 | EL149: 847.5 | EM149: 735.835 | EN149: 463.24924 | EO149: 10964.025 | EP149: 0 | ER149: 0 | ES149: 0 | ET149: =(ES149+ER149)/($E$2+$E$3) -> 0 | EU149: 0 | EV149: 0 | EW149: =(EU149+EV149)/($J$2+$J$3) -> 0 | EY149: 7817.5125 | EZ149: 0 | FA149: =(EY149+EZ149)/($E$12+$E$14) -> 0.57464893 | FB149: 0 | FC149: =FB149/$J$10 -> 0 | FF149: 2897.4 | FG149: 10423.35 | FH149: =(FF149+FG149)/($E$13+$E$15) -> 1 | FI149: 3837 | FJ149: =FI149/$J$11 -> 1 | FL149: 7873 | FM149: =FL149/$E$11 -> 0.68245451 | FN149: 2591 | FO149: =FN149/$J$9 -> 0.82634349 | FQ149: 278 | FR149: 367.01 | FS149: =(FQ149+FR149)/($J$8+$J$12) -> 0.81843675 | FT149: =FQ149+FR149 -> 645.01 | FV149: =FW149+FX149-FY149-GA149 -> 574.84131 | FW149: 244.84131 | FX149: 330 | FY149: 0 | FZ149: =FV149/1553.6723 -> 0.36998878 | GA149: 0 | GC149: 16008.175 | GD149: =GC149/32600 -> 0.4910483 | GE149: 2704.9238 | GF149: =GE149/13478 -> 0.20069178 | GH149: 24578.392 | GI149: 6567.3727 | GK149: 0.257 | GL149: 0.84 | GM149: =-GN149 -> 1517.7758 | GN149: -1517.7758 | GO149: =GM149-1517.77579117 -> 0 | GP149: =GO149/1492.3021 -> 0 | GR149: 21433.611 | GS149: 6305.2455 | GV149: 3776.591 | GW149: 930.30215 | GX149: =MAX(GW:GW) -> 1537.0311 | GY149: =GW149/GX149 -> 0.60525917
P150: 148 | Q150: 0 | R150: 0 | S150: 0 | T150: 0 | U150: 0 | V150: 0 | W150: 0 | X150: 0 | Y150: 0 | Z150: 0 | AA150: 0 | AB150: 0 | AC150: 0 | AD150: 0 | AF150: 148 | AG150: 57582.871 | AH150: 2010.2 | AI150: 437 | AJ150: 0.647 | AK150: 0.874 | AL150: 0.874 | AM150: 473.518 | AN150: 9175.1568 | AO150: 0.733 | AP150: 0.788 | AQ150: 35546.2 | AR150: 20611.05 | AS150: 0.797 | AT150: 0.878 | AV150: 886.558 | AW150: 0.36000016 | AX150: 932.174 | AY150: 0.58007094 | AZ150: 1121.478 | BA150: 0.57843924 | BC150: 53641.617 | BD150: 0.7704918 | BF150: 24578.392 | BG150: 0 | BH150: 0 | BI150: 0.7539384 | BJ150: 0 | BK150: 0 | BL150: 0 | BM150: 0 | BN150: 6567.373 | BO150: 0.48726614 | BP150: 0 | BQ150: 7668 | BR150: 0 | BT150: -700 | BU150: 0 | BV150: 4485 | BW150: 4485 | BX150: 0 | BY150: 0 | BZ150: -5000 | CA150: 0 | CB150: -5300 | CC150: 0 | CD150: -4000 | CE150: 0 | CF150: -4800 | CG150: 0 | CH150: 38048.083 | CI150: 38048.083 | CJ150: 42533.083 | CL150: -700 | CM150: 700 | CN150: 4485 | CO150: 0 | CP150: 0 | CQ150: 0 | CR150: -5000 | CS150: 5000 | CT150: -5300 | CU150: 5300 | CV150: -4000 | CW150: 4000 | CX150: -4800 | CY150: 4800 | CZ150: 38048.083 | DA150: 0 | DB150: 19800 | DD150: 26794.48 | DE150: 1963.656 | DF150: 2498.7367 | DG150: 31256.873 | DH150: 6954.551 | DI150: 50110.411 | DJ150: 7869 | DK150: 57979.411 | DM150: 841.479 | DN150: 10490.399 | DO150: 11331.878 | DP150: 1455.3989 | DQ150: 2897.8864 | DR150: 463.24924 | DS150: 3361.1356 | DT150: 160.99369 | DU150: 160.99369 | DW150: 0 | DX150: 6779.661 | DY150: 1447.7401 | DZ150: 0 | EA150: 0 | EB150: 244.84131 | EC150: 0 | ED150: 1271.1864 | EE150: 0 | EF150: 847.5 | EG150: 0 | EH150: 7397.5989 | EI150: 0 | EJ150: 6779.661 | EK150: 244.84131 | EL150: 847.5 | EM150: 735.835 | EN150: 463.24924 | EO150: 10964.025 | EP150: 0 | ER150: 0 | ES150: 0 | ET150: =(ES150+ER150)/($E$2+$E$3) -> 0 | EU150: 0 | EV150: 0 | EW150: =(EU150+EV150)/($J$2+$J$3) -> 0 | EY150: 7817.5125 | EZ150: 0 | FA150: =(EY150+EZ150)/($E$12+$E$14) -> 0.57464893 | FB150: 0 | FC150: =FB150/$J$10 -> 0 | FF150: 2897.4 | FG150: 10423.35 | FH150: =(FF150+FG150)/($E$13+$E$15) -> 1 | FI150: 3837 | FJ150: =FI150/$J$11 -> 1 | FL150: 7873 | FM150: =FL150/$E$11 -> 0.68245451 | FN150: 2591 | FO150: =FN150/$J$9 -> 0.82634349 | FQ150: 0 | FR150: 367.01 | FS150: =(FQ150+FR150)/($J$8+$J$12) -> 0.46568963 | FT150: =FQ150+FR150 -> 367.01 | FV150: =FW150+FX150-FY150-GA150 -> #REF! | FW150: 244.84131 | FX150: 330 | FY150: =330*#REF! -> #REF! | FZ150: =FV150/1553.6723 -> #REF! | GA150: 0 | GC150: 17450.658 | GD150: =GC150/32600 -> 0.53529627 | GE150: 2270.1638 | GF150: =GE150/13478 -> 0.16843477 | GH150: 26177.436 | GI150: 6449.9723 | GK150: 0.257 | GL150: 0.84 | GM150: =-GN150 -> 1517.7758 | GN150: -1517.7758 | GO150: =GM150-1517.77579117 -> 0 | GP150: =GO150/1492.3021 -> 0 | GR150: 22964.167 | GS150: 6507.5327 | GV150: 3776.591 | GW150: 930.30215 | GX150: =MAX(GW:GW) -> 1537.0311 | GY150: =GW150/GX150 -> 0.60525917
P151: 149 | Q151: 0 | R151: 0 | S151: 0 | T151: 0 | U151: 0 | V151: 0 | W151: 0 | X151: 0 | Y151: 0 | Z151: 0 | AA151: 0 | AB151: 0 | AC151: 0 | AD151: 0 | AF151: 149 | AG151: 61320.862 | AH151: 2037.8 | AI151: 443 | AJ151: 0.689 | AK151: 0.886 | AL151: 0.886 | AM151: 465.12 | AN151: 9408.0288 | AO151: 0.72 | AP151: 0.808 | AQ151: 36304.4 | AR151: 20000.7 | AS151: 0.814 | AT151: 0.852 | AV151: 879.17 | AW151: 0.35700015 | AX151: 932.147 | AY151: 0.58005414 | AZ151: 1121.478 | BA151: 0.57843924 | BC151: 53641.617 | BD151: 0.7704918 | BF151: 26177.436 | BG151: 0 | BH151: 0 | BI151: 0.80298883 | BJ151: 0 | BK151: 0 | BL151: 0 | BM151: 0 | BN151: 6449.972 | BO151: 0.47855557 | BP151: 0 | BQ151: 7668 | BR151: 0 | BT151: -700 | BU151: 0 | BV151: 4485 | BW151: 4485 | BX151: 0 | BY151: 0 | BZ151: -5000 | CA151: 0 | CB151: -5300 | CC151: 0 | CD151: -4000 | CE151: 0 | CF151: -4800 | CG151: 0 | CH151: 28564.7 | CI151: 28564.7 | CJ151: 33049.7 | CL151: -700 | CM151: 700 | CN151: 4485 | CO151: 0 | CP151: 0 | CQ151: 0 | CR151: -5000 | CS151: 5000 | CT151: -5300 | CU151: 5300 | CV151: -4000 | CW151: 4000 | CX151: -4800 | CY151: 4800 | CZ151: 28564.7 | DA151: 0 | DB151: 19800 | DD151: 26630.736 | DE151: 1954.935 | DF151: 2804.0451 | DG151: 31389.716 | DH151: 6894.78 | DI151: 49683.411 | DJ151: 7869 | DK151: 57552.411 | DM151: 987.78 | DN151: 10522.091 | DO151: 11509.871 | DP151: 1455.3989 | DQ151: 2914.5856 | DR151: 446.55003 | DS151: 3361.1356 | DT151: 161.92142 | DU151: 161.92142 | DW151: 0 | DX151: 6779.661 | DY151: 1447.7401 | DZ151: 0 | EA151: 0 | EB151: 243.91358 | EC151: 0 | ED151: 1271.1864 | EE151: 0 | EF151: 847.5 | EG151: 0 | EH151: 7397.5989 | EI151: 0 | EJ151: 6779.661 | EK151: 243.91358 | EL151: 847.5 | EM151: 735.835 | EN151: 446.55003 | EO151: 10964.025 | EP151: 0 | ER151: 0 | ES151: 0 | ET151: =(ES151+ER151)/($E$2+$E$3) -> 0 | EU151: 0 | EV151: 0 | EW151: =(EU151+EV151)/($J$2+$J$3) -> 0 | EY151: 0 | EZ151: 0 | FA151: =(EY151+EZ151)/($E$12+$E$14) -> 0 | FB151: 0 | FC151: =FB151/$J$10 -> 0 | FF151: 2897.4 | FG151: 10423.35 | FH151: =(FF151+FG151)/($E$13+$E$15) -> 1 | FI151: 3837 | FJ151: =FI151/$J$11 -> 1 | FL151: 7873 | FM151: =FL151/$E$11 -> 0.68245451 | FN151: 2591 | FO151: =FN151/$J$9 -> 0.82634349 | FQ151: 278 | FR151: 367.01 | FS151: =(FQ151+FR151)/($J$8+$J$12) -> 0.81843675 | FT151: =FQ151+FR151 -> 645.01 | FV151: =FW151+FX151-FY151-GA151 -> #REF! | FW151: 243.91358 | FX151: 330 | FY151: =330*#REF! -> #REF! | FZ151: =FV151/1553.6723 -> #REF! | GA151: 0 | GC151: 18585.98 | GD151: =GC151/32600 -> 0.57012207 | GE151: 1835.4038 | GF151: =GE151/13478 -> 0.13617776 | GH151: 26939.273 | GI151: 6175.2074 | GK151: 0.257 | GL151: 0.84 | GM151: =-GN151 -> 1517.7758 | GN151: -1517.7758 | GO151: =GM151-1517.77579117 -> 0 | GP151: =GO151/1492.3021 -> 0 | GR151: 24578.392 | GS151: 6567.3727 | GV151: 3776.591 | GW151: 930.30215 | GX151: =MAX(GW:GW) -> 1537.0311 | GY151: =GW151/GX151 -> 0.60525917
P152: 150 | Q152: 0 | R152: 0 | S152: 0 | T152: 0 | U152: 0 | V152: 0 | W152: 0 | X152: 0 | Y152: 0 | Z152: 0 | AA152: 0 | AB152: 0 | AC152: 0 | AD152: 0 | AF152: 150 | AG152: 63100.858 | AH152: 2056.2 | AI152: 447 | AJ152: 0.709 | AK152: 0.894 | AL152: 0.894 | AM152: 445.094 | AN152: 9256.662 | AO152: 0.689 | AP152: 0.795 | AQ152: 36616.6 | AR152: 19578.15 | AS152: 0.821 | AT152: 0.834 | AV152: 884.095 | AW152: 0.35900002 | AX152: 934.016 | AY152: 0.58121717 | AZ152: 1121.478 | BA152: 0.57843924 | BC152: 53641.617 | BD152: 0.7704918 | BF152: 26939.273 | BG152: 0 | BH152: 0 | BI152: 0.82635807 | BJ152: 0 | BK152: 0 | BL152: 0 | BM152: 0 | BN152: 6175.207 | BO152: 0.45816939 | BP152: 0 | BQ152: 7668 | BR152: 0 | BT152: -700 | BU152: 0 | BV152: 4485 | BW152: 4485 | BX152: 0 | BY152: 0 | BZ152: -5000 | CA152: 0 | CB152: -5300 | CC152: 0 | CD152: -4000 | CE152: 0 | CF152: -4800 | CG152: 0 | CH152: 23454.642 | CI152: 23454.642 | CJ152: 27939.642 | CL152: -700 | CM152: 700 | CN152: 4485 | CO152: 0 | CP152: 0 | CQ152: 0 | CR152: -5000 | CS152: 5000 | CT152: -5300 | CU152: 5300 | CV152: -4000 | CW152: 4000 | CX152: -4800 | CY152: 4800 | CZ152: 23454.642 | DA152: 0 | DB152: 19800 | DD152: 26829.452 | DE152: 1954.27 | DF152: 2984.8624 | DG152: 31768.584 | DH152: 6929.802 | DI152: 50184.411 | DJ152: 7819 | DK152: 58003.411 | DM152: 1161.427 | DN152: 10553.783 | DO152: 11715.21 | DP152: 1455.3989 | DQ152: 2931.2848 | DR152: 429.85082 | DS152: 3361.1356 | DT152: 162.84916 | DU152: 162.84916 | DW152: 0 | DX152: 6779.661 | DY152: 1447.7401 | DZ152: 0 | EA152: 0 | EB152: 242.98584 | EC152: 0 | ED152: 1271.1864 | EE152: 0 | EF152: 847.5 | EG152: 0 | EH152: 7397.5989 | EI152: 0 | EJ152: 6779.661 | EK152: 242.98584 | EL152: 847.5 | EM152: 735.835 | EN152: 429.85082 | EO152: 10964.025 | EP152: 0 | ER152: 0 | ES152: 0 | ET152: =(ES152+ER152)/($E$2+$E$3) -> 0 | EU152: 0 | EV152: 0 | EW152: =(EU152+EV152)/($J$2+$J$3) -> 0 | EY152: 0 | EZ152: 0 | FA152: =(EY152+EZ152)/($E$12+$E$14) -> 0 | FB152: 0 | FC152: =FB152/$J$10 -> 0 | FF152: 2897.4 | FG152: 10423.35 | FH152: =(FF152+FG152)/($E$13+$E$15) -> 1 | FI152: 3837 | FJ152: =FI152/$J$11 -> 1 | FL152: 7873 | FM152: =FL152/$E$11 -> 0.68245451 | FN152: 2591 | FO152: =FN152/$J$9 -> 0.82634349 | FQ152: 0 | FR152: 367.01 | FS152: =(FQ152+FR152)/($J$8+$J$12) -> 0.46568963 | FT152: =FQ152+FR152 -> 367.01 | FV152: =FW152+FX152-FY152-GA152 -> #REF! | FW152: 242.98584 | FX152: 330 | FY152: =330*#REF! -> #REF! | FZ152: =FV152/1553.6723 -> #REF! | GA152: 0 | GC152: 19126.884 | GD152: =GC152/32600 -> 0.58671423 | GE152: 1455.3989 | GF152: =GE152/13478 -> 0.1079833 | GH152: 26489.846 | GI152: 6224.9139 | GK152: 0.257 | GL152: 0.84 | GM152: =-GN152 -> 1517.7758 | GN152: -1517.7758 | GO152: =GM152-1517.77579117 -> 0 | GP152: =GO152/1492.3021 -> 0 | GR152: 26177.436 | GS152: 6449.9723 | GV152: 3776.591 | GW152: 930.30215 | GX152: =MAX(GW:GW) -> 1537.0311 | GY152: =GW152/GX152 -> 0.60525917
P153: 151 | Q153: 0 | R153: 0 | S153: 0 | T153: 0 | U153: 0 | V153: 0 | W153: 0 | X153: 0 | Y153: 0 | Z153: 0 | AA153: 0 | AB153: 0 | AC153: 0 | AD153: 0 | AF153: 151 | AG153: 62032.861 | AH153: 2060.8 | AI153: 448 | AJ153: 0.697 | AK153: 0.896 | AL153: 0.896 | AM153: 448.324 | AN153: 9198.444 | AO153: 0.694 | AP153: 0.79 | AQ153: 37285.6 | AR153: 19179.075 | AS153: 0.836 | AT153: 0.817 | AV153: 889.02 | AW153: 0.36099989 | AX153: 943.673 | AY153: 0.58722651 | AZ153: 1121.478 | BA153: 0.57843924 | BC153: 53641.617 | BD153: 0.7704918 | BF153: 26489.846 | BG153: 0 | BH153: 0 | BI153: 0.81257196 | BJ153: 0 | BK153: 0 | BL153: 0 | BM153: 0 | BN153: 6224.914 | BO153: 0.4618574 | BP153: 0 | BQ153: 7668 | BR153: 0 | BT153: -700 | BU153: 0 | BV153: 4485 | BW153: 4485 | BX153: 0 | BY153: 0 | BZ153: -5000 | CA153: 0 | CB153: -5300 | CC153: 0 | CD153: -4000 | CE153: 0 | CF153: -4800 | CG153: 0 | CH153: 24177.853 | CI153: 24177.853 | CJ153: 28662.853 | CL153: -700 | CM153: 700 | CN153: 4485 | CO153: 0 | CP153: 0 | CQ153: 0 | CR153: -5000 | CS153: 5000 | CT153: -5300 | CU153: 5300 | CV153: -4000 | CW153: 4000 | CX153: -4800 | CY153: 4800 | CZ153: 24177.853 | DA153: 0 | DB153: 19800 | DD153: 27697.37 | DE153: 1976.765 | DF153: 3746.0904 | DG153: 33420.225 | DH153: 6996.299 | DI153: 50078.411 | DJ153: 7850 | DK153: 57928.411 | DM153: 1222.274 | DN153: 10569.629 | DO153: 11791.903 | DP153: 1455.3989 | DQ153: 2939.6344 | DR153: 421.50122 | DS153: 3361.1356 | DT153: 163.31302 | DU153: 163.31302 | DW153: 0 | DX153: 6779.661 | DY153: 1447.7401 | DZ153: 0 | EA153: 0 | EB153: 242.52198 | EC153: 0 | ED153: 1271.1864 | EE153: 0 | EF153: 847.5 | EG153: 0 | EH153: 7397.5989 | EI153: 0 | EJ153: 6779.661 | EK153: 242.52198 | EL153: 847.5 | EM153: 735.835 | EN153: 421.50122 | EO153: 10964.025 | EP153: 0 | ER153: 0 | ES153: 0 | ET153: =(ES153+ER153)/($E$2+$E$3) -> 0 | EU153: 0 | EV153: 0 | EW153: =(EU153+EV153)/($J$2+$J$3) -> 0 | EY153: 6511.5987 | EZ153: 0 | FA153: =(EY153+EZ153)/($E$12+$E$14) -> 0.47865394 | FB153: 0 | FC153: =FB153/$J$10 -> 0 | FF153: 2897.4 | FG153: 10423.35 | FH153: =(FF153+FG153)/($E$13+$E$15) -> 1 | FI153: 3837 | FJ153: =FI153/$J$11 -> 1 | FL153: 7873 | FM153: =FL153/$E$11 -> 0.68245451 | FN153: 2591 | FO153: =FN153/$J$9 -> 0.82634349 | FQ153: 0 | FR153: 367.01 | FS153: =(FQ153+FR153)/($J$8+$J$12) -> 0.46568963 | FT153: =FQ153+FR153 -> 367.01 | FV153: =FW153+FX153-FY153-GA153 -> #REF! | FW153: 242.52198 | FX153: 330 | FY153: =330*#REF! -> #REF! | FZ153: =FV153/1553.6723 -> #REF! | GA153: 0 | GC153: 9805.0834 | GD153: =GC153/32600 -> 0.30076943 | GE153: 1455.3989 | GF153: =GE153/13478 -> 0.1079833 | GH153: 25487.447 | GI153: 6055.6414 | GK153: 0.257 | GL153: 0.84 | GM153: =-GN153 -> 1517.7758 | GN153: -1517.7758 | GO153: =GM153-1517.77579117 -> 0 | GP153: =GO153/1492.3021 -> 0 | GR153: 26939.273 | GS153: 6175.2074 | GV153: 3776.591 | GW153: 930.30215 | GX153: =MAX(GW:GW) -> 1537.0311 | GY153: =GW153/GX153 -> 0.60525917
P154: 152 | Q154: 0 | R154: 0 | S154: 0 | T154: 0 | U154: 0 | V154: 0 | W154: 0 | X154: 0 | Y154: 0 | Z154: 0 | AA154: 0 | AB154: 0 | AC154: 0 | AD154: 0 | AF154: 152 | AG154: 59718.866 | AH154: 2079.2 | AI154: 452 | AJ154: 0.671 | AK154: 0.904 | AL154: 0.904 | AM154: 436.05 | AN154: 9058.7208 | AO154: 0.675 | AP154: 0.778 | AQ154: 37687 | AR154: 18850.425 | AS154: 0.845 | AT154: 0.803 | AV154: 891.483 | AW154: 0.36200003 | AX154: 1016.37 | AY154: 0.63246422 | AZ154: 1121.478 | BA154: 0.57843924 | BC154: 53641.617 | BD154: 0.7704918 | BF154: 25487.447 | BG154: 0 | BH154: 0 | BI154: 0.78182353 | BJ154: 0 | BK154: 0 | BL154: 0 | BM154: 0 | BN154: 6055.641 | BO154: 0.44929819 | BP154: 0 | BQ154: 7668 | BR154: 0 | BT154: -700 | BU154: 0 | BV154: 4485 | BW154: 4485 | BX154: 0 | BY154: 0 | BZ154: -5000 | CA154: 0 | CB154: -5300 | CC154: 0 | CD154: -4000 | CE154: 0 | CF154: -4800 | CG154: 0 | CH154: 18549.629 | CI154: 18549.629 | CJ154: 23034.629 | CL154: -700 | CM154: 700 | CN154: 4485 | CO154: 0 | CP154: 0 | CQ154: 0 | CR154: -5000 | CS154: 5000 | CT154: -5300 | CU154: 5300 | CV154: -4000 | CW154: 4000 | CX154: -4800 | CY154: 4800 | CZ154: 18549.629 | DA154: 0 | DB154: 19800 | DD154: 29304.959 | DE154: 2014.755 | DF154: 4164.2738 | DG154: 35483.988 | DH154: 6963.815 | DI154: 49789.411 | DJ154: 8040 | DK154: 57829.411 | DM154: 1218.196 | DN154: 10553.783 | DO154: 11771.979 | DP154: 1455.3989 | DQ154: 2931.2848 | DR154: 429.85082 | DS154: 3361.1356 | DT154: 162.84916 | DU154: 162.84916 | DW154: 0 | DX154: 6779.661 | DY154: 1447.7401 | DZ154: 0 | EA154: 0 | EB154: 242.98584 | EC154: 0 | ED154: 1271.1864 | EE154: 0 | EF154: 847.5 | EG154: 0 | EH154: 7397.5989 | EI154: 0 | EJ154: 6779.661 | EK154: 242.98584 | EL154: 847.5 | EM154: 735.835 | EN154: 429.85082 | EO154: 10964.025 | EP154: 0 | ER154: 0 | ES154: 0 | ET154: =(ES154+ER154)/($E$2+$E$3) -> 0 | EU154: 0 | EV154: 0 | EW154: =(EU154+EV154)/($J$2+$J$3) -> 0 | EY154: 562.79134 | EZ154: 0 | FA154: =(EY154+EZ154)/($E$12+$E$14) -> 0.04136961 | FB154: 0 | FC154: =FB154/$J$10 -> 0 | FF154: 2897.4 | FG154: 10423.35 | FH154: =(FF154+FG154)/($E$13+$E$15) -> 1 | FI154: 3078.2522 | FJ154: =FI154/$J$11 -> 0.80225493 | FL154: 7873 | FM154: =FL154/$E$11 -> 0.68245451 | FN154: 2591 | FO154: =FN154/$J$9 -> 0.82634349 | FQ154: 278 | FR154: 367.01 | FS154: =(FQ154+FR154)/($J$8+$J$12) -> 0.81843675 | FT154: =FQ154+FR154 -> 645.01 | FV154: =FW154+FX154-FY154-GA154 -> #REF! | FW154: 242.98584 | FX154: 330 | FY154: =330*#REF! -> #REF! | FZ154: =FV154/1553.6723 -> #REF! | GA154: 0 | GC154: 18096.087 | GD154: =GC154/32600 -> 0.5550947 | GE154: 1455.3989 | GF154: =GE154/13478 -> 0.1079833 | GH154: 24359.144 | GI154: 5428.9404 | GK154: 0.257 | GL154: 0.84 | GM154: =-GN154 -> 1517.7758 | GN154: -1517.7758 | GO154: =GM154-1517.77579117 -> 0 | GP154: =GO154/1492.3021 -> 0 | GR154: 26489.846 | GS154: 6224.9139 | GV154: 3776.591 | GW154: 930.30215 | GX154: =MAX(GW:GW) -> 1537.0311 | GY154: =GW154/GX154 -> 0.60525917
P155: 153 | Q155: 0 | R155: 0 | S155: 0 | T155: 0 | U155: 0 | V155: 0 | W155: 0 | X155: 0 | Y155: 0 | Z155: 0 | AA155: 0 | AB155: 0 | AC155: 0 | AD155: 0 | AF155: 153 | AG155: 56959.872 | AH155: 2097.6 | AI155: 456 | AJ155: 0.64 | AK155: 0.912 | AL155: 0.912 | AM155: 390.83 | AN155: 8383.392 | AO155: 0.605 | AP155: 0.72 | AQ155: 37820.8 | AR155: 18897.375 | AS155: 0.848 | AT155: 0.805 | AV155: 891.483 | AW155: 0.36200003 | AX155: 1031.785 | AY155: 0.64205663 | AZ155: 1121.478 | BA155: 0.57843924 | BC155: 53641.617 | BD155: 0.7704918 | BF155: 24359.144 | BG155: 0 | BH155: 0 | BI155: 0.74721301 | BJ155: 0 | BK155: 0 | BL155: 0 | BM155: 0 | BN155: 5428.94 | BO155: 0.40280012 | BP155: 0 | BQ155: 7668 | BR155: 0 | BT155: -700 | BU155: 0 | BV155: 4485 | BW155: 4485 | BX155: 0 | BY155: 0 | BZ155: -5000 | CA155: 0 | CB155: -5300 | CC155: 0 | CD155: -4000 | CE155: 0 | CF155: -4800 | CG155: 0 | CH155: 20200.097 | CI155: 20200.097 | CJ155: 24685.097 | CL155: -700 | CM155: 700 | CN155: 4485 | CO155: 0 | CP155: 0 | CQ155: 0 | CR155: -5000 | CS155: 5000 | CT155: -5300 | CU155: 5300 | CV155: -4000 | CW155: 4000 | CX155: -4800 | CY155: 4800 | CZ155: 20200.097 | DA155: 0 | DB155: 19800 | DD155: 31600.331 | DE155: 2035.595 | DF155: 4005.3452 | DG155: 37641.271 | DH155: 7009.672 | DI155: 49762.411 | DJ155: 8874 | DK155: 58636.411 | DM155: 1137.687 | DN155: 10553.783 | DO155: 11691.47 | DP155: 1455.3989 | DQ155: 2931.2848 | DR155: 429.85082 | DS155: 3361.1356 | DT155: 162.84916 | DU155: 162.84916 | DW155: 0 | DX155: 6779.661 | DY155: 1447.7401 | DZ155: 0 | EA155: 0 | EB155: 242.98584 | EC155: 0 | ED155: 1271.1864 | EE155: 0 | EF155: 847.5 | EG155: 0 | EH155: 7397.5989 | EI155: 0 | EJ155: 6779.661 | EK155: 242.98584 | EL155: 847.5 | EM155: 735.835 | EN155: 429.85082 | EO155: 10964.025 | EP155: 0 | ER155: 0 | ES155: 0 | ET155: =(ES155+ER155)/($E$2+$E$3) -> 0 | EU155: 0 | EV155: 0 | EW155: =(EU155+EV155)/($J$2+$J$3) -> 0 | EY155: 7211.924 | EZ155: 0 | FA155: =(EY155+EZ155)/($E$12+$E$14) -> 0.53013339 | FB155: 0 | FC155: =FB155/$J$10 -> 0 | FF155: 2897.4 | FG155: 0 | FH155: =(FF155+FG155)/($E$13+$E$15) -> 0.21751028 | FI155: 3837 | FJ155: =FI155/$J$11 -> 1 | FL155: 7873 | FM155: =FL155/$E$11 -> 0.68245451 | FN155: 2591 | FO155: =FN155/$J$9 -> 0.82634349 | FQ155: 0 | FR155: 367.01 | FS155: =(FQ155+FR155)/($J$8+$J$12) -> 0.46568963 | FT155: =FQ155+FR155 -> 367.01 | FV155: =FW155+FX155-FY155-GA155 -> #REF! | FW155: 242.98584 | FX155: 330 | FY155: =330*#REF! -> #REF! | FZ155: =FV155/1553.6723 -> #REF! | GA155: 0 | GC155: 9766.5536 | GD155: =GC155/32600 -> 0.29958753 | GE155: 1455.3989 | GF155: =GE155/13478 -> 0.1079833 | GH155: 24295.388 | GI155: 4891.6632 | GK155: 0.257 | GL155: 0.84 | GM155: =-GN155 -> 1517.7758 | GN155: -1517.7758 | GO155: =GM155-1517.77579117 -> 0 | GP155: =GO155/1492.3021 -> 0 | GR155: 25487.447 | GS155: 6055.6414 | GV155: 3776.591 | GW155: 930.30215 | GX155: =MAX(GW:GW) -> 1537.0311 | GY155: =GW155/GX155 -> 0.60525917
P156: 154 | Q156: 2490 | R156: 0.03 | S156: 0 | T156: 0 | U156: 1110 | V156: 0.037 | W156: 172.5384 | X156: 0.012 | Y156: 115.9188 | Z156: 0.012 | AA156: 1079.82 | AB156: 0.021 | AC156: 972.7368 | AD156: 0.021 | AF156: 154 | AG156: 53933.879 | AH156: 2099.9 | AI156: 456.5 | AJ156: 0.606 | AK156: 0.913 | AL156: 0.913 | AM156: 341.088 | AN156: 7742.994 | AO156: 0.528 | AP156: 0.665 | AQ156: 37151.8 | AR156: 19085.175 | AS156: 0.833 | AT156: 0.813 | AV156: 906.259 | AW156: 0.36800005 | AX156: 0 | AY156: 0 | AZ156: 1121.478 | BA156: 0.57843924 | BC156: 53641.617 | BD156: 0.7704918 | BF156: 24295.388 | BG156: 0 | BH156: 0 | BI156: 0.7452573 | BJ156: 0 | BK156: 0 | BL156: 0 | BM156: 0 | BN156: 4891.663 | BO156: 0.36293686 | BP156: 0 | BQ156: 7668 | BR156: 0 | BT156: -700 | BU156: 0 | BV156: 4485 | BW156: 4485 | BX156: 0 | BY156: 0 | BZ156: -5000 | CA156: 0 | CB156: -5300 | CC156: 0 | CD156: -4000 | CE156: 0 | CF156: -4800 | CG156: 0 | CH156: 20381.173 | CI156: 20381.173 | CJ156: 24866.173 | CL156: -700 | CM156: 700 | CN156: 4485 | CO156: 0 | CP156: 0 | CQ156: 0 | CR156: -5000 | CS156: 5000 | CT156: -5300 | CU156: 5300 | CV156: -4000 | CW156: 4000 | CX156: -4800 | CY156: 4800 | CZ156: 20381.173 | DA156: 0 | DB156: 19800 | DD156: 34110.508 | DE156: 1913.068 | DF156: 2484.8286 | DG156: 38508.405 | DH156: 7404.299 | DI156: 50267.411 | DJ156: 9802 | DK156: 60069.411 | DM156: 1060.563 | DN156: 10553.783 | DO156: 11614.346 | DP156: 1455.3989 | DQ156: 2931.2848 | DR156: 429.85082 | DS156: 3361.1356 | DT156: 162.84916 | DU156: 162.84916 | DW156: 0 | DX156: 6779.661 | DY156: 1447.7401 | DZ156: 0 | EA156: 0 | EB156: 242.98584 | EC156: 0 | ED156: 1271.1864 | EE156: 0 | EF156: 847.5 | EG156: 0 | EH156: 7397.5989 | EI156: 0 | EJ156: 6779.661 | EK156: 242.98584 | EL156: 847.5 | EM156: 735.835 | EN156: 429.85082 | EO156: 10964.025 | EP156: 0 | ER156: 0 | ES156: 0 | ET156: =(ES156+ER156)/($E$2+$E$3) -> 0 | EU156: 0 | EV156: 0 | EW156: =(EU156+EV156)/($J$2+$J$3) -> 0 | EY156: 6322.1895 | EZ156: 0 | FA156: =(EY156+EZ156)/($E$12+$E$14) -> 0.46473088 | FB156: 0 | FC156: =FB156/$J$10 -> 0 | FF156: 2897.4 | FG156: 0 | FH156: =(FF156+FG156)/($E$13+$E$15) -> 0.21751028 | FI156: 0 | FJ156: =FI156/$J$11 -> 0 | FL156: 7873 | FM156: =FL156/$E$11 -> 0.68245451 | FN156: 2591 | FO156: =FN156/$J$9 -> 0.82634349 | FQ156: 0 | FR156: 0 | FS156: =(FQ156+FR156)/($J$8+$J$12) -> 0 | FT156: =FQ156+FR156 -> 0 | FV156: =FW156+FX156-FY156-GA156 -> #REF! | FW156: 242.98584 | FX156: 330 | FY156: =330*#REF! -> #REF! | FZ156: =FV156/1553.6723 -> #REF! | GA156: 0 | GC156: 9746.7172 | GD156: =GC156/32600 -> 0.29897906 | GE156: 1455.3989 | GF156: =GE156/13478 -> 0.1079833 | GH156: 26488.442 | GI156: 4668.4676 | GK156: 0.257 | GL156: 0.84 | GM156: =-GN156 -> 1517.7758 | GN156: -1517.7758 | GO156: =GM156-1517.77579117 -> 0 | GP156: =GO156/1492.3021 -> 0 | GR156: 24359.144 | GS156: 5428.9404 | GV156: 3776.591 | GW156: 930.30215 | GX156: =MAX(GW:GW) -> 1537.0311 | GY156: =GW156/GX156 -> 0.60525917
P157: 155 | Q157: 6806 | R157: 0.082 | S157: 81.685 | T157: 0.017 | U157: 3210 | V157: 0.107 | W157: 704.5318 | X157: 0.049 | Y157: 540.9544 | Z157: 0.056 | AA157: 4267.86 | AB157: 0.083 | AC157: 3427.7392 | AD157: 0.074 | AF157: 155 | AG157: 53666.879 | AH157: 2093 | AI157: 455 | AJ157: 0.603 | AK157: 0.91 | AL157: 0.91 | AM157: 288.116 | AN157: 7230.6756 | AO157: 0.446 | AP157: 0.621 | AQ157: 36705.8 | AR157: 19695.525 | AS157: 0.823 | AT157: 0.839 | AV157: 901.334 | AW157: 0.36600018 | AX157: 1033.389 | AY157: 0.64305476 | AZ157: 1121.478 | BA157: 0.57843924 | BC157: 53641.617 | BD157: 0.7704918 | BF157: 26488.442 | BG157: 0 | BH157: 0 | BI157: 0.8125289 | BJ157: 0 | BK157: 0 | BL157: 0 | BM157: 0 | BN157: 4668.468 | BO157: 0.34637691 | BP157: 0 | BQ157: 7668 | BR157: 0 | BT157: -700 | BU157: 0 | BV157: 4485 | BW157: 4485 | BX157: 0 | BY157: 0 | BZ157: -5000 | CA157: 0 | CB157: -5300 | CC157: 0 | CD157: -4000 | CE157: 0 | CF157: -4800 | CG157: 0 | CH157: 20889.164 | CI157: 20889.164 | CJ157: 25374.164 | CL157: -700 | CM157: 700 | CN157: 4485 | CO157: 0 | CP157: 0 | CQ157: 0 | CR157: -5000 | CS157: 5000 | CT157: -5300 | CU157: 5300 | CV157: -4000 | CW157: 4000 | CX157: -4800 | CY157: 4800 | CZ157: 20889.164 | DA157: 0 | DB157: 19800 | DD157: 35040.794 | DE157: 1764.179 | DF157: 2000.9532 | DG157: 38805.926 | DH157: 7957.683 | DI157: 51744.411 | DJ157: 9675 | DK157: 61419.411 | DM157: 990.994 | DN157: 10553.783 | DO157: 11544.777 | DP157: 1639.1187 | DQ157: 2931.2848 | DR157: 429.85082 | DS157: 3361.1356 | DT157: 162.84916 | DU157: 162.84916 | DW157: 0 | DX157: 6779.661 | DY157: 1447.7401 | DZ157: 0 | EA157: 0 | EB157: 242.98584 | EC157: 0 | ED157: 1271.1864 | EE157: 0 | EF157: 847.5 | EG157: 0 | EH157: 7397.5989 | EI157: 0 | EJ157: 6779.661 | EK157: 242.98584 | EL157: 847.5 | EM157: 735.835 | EN157: 429.85082 | EO157: 10964.025 | EP157: 0 | ER157: 0 | ES157: 0 | ET157: =(ES157+ER157)/($E$2+$E$3) -> 0 | EU157: 0 | EV157: 0 | EW157: =(EU157+EV157)/($J$2+$J$3) -> 0 | EY157: 4283.9896 | EZ157: 0 | FA157: =(EY157+EZ157)/($E$12+$E$14) -> 0.31490708 | FB157: 0 | FC157: =FB157/$J$10 -> 0 | FF157: 2897.4 | FG157: 10423.35 | FH157: =(FF157+FG157)/($E$13+$E$15) -> 1 | FI157: 3837 | FJ157: =FI157/$J$11 -> 1 | FL157: 7873 | FM157: =FL157/$E$11 -> 0.68245451 | FN157: 2591 | FO157: =FN157/$J$9 -> 0.82634349 | FQ157: 278 | FR157: 367.01 | FS157: =(FQ157+FR157)/($J$8+$J$12) -> 0.81843675 | FT157: =FQ157+FR157 -> 645.01 | FV157: =FW157+FX157-FY157-GA157 -> #REF! | FW157: 242.98584 | FX157: 330 | FY157: =330*#REF! -> #REF! | FZ157: =FV157/1553.6723 -> #REF! | GA157: 0 | GC157: 14391.626 | GD157: =GC157/32600 -> 0.44146093 | GE157: 1639.1187 | GF157: =GE157/13478 -> 0.12161439 | GH157: 29483.574 | GI157: 4582.625 | GK157: 0.257 | GL157: 0.84 | GM157: =-GN157 -> 1517.7758 | GN157: -1517.7758 | GO157: =GM157-1517.77579117 -> 0 | GP157: =GO157/1492.3021 -> 0 | GR157: 24295.388 | GS157: 4891.6632 | GV157: 3776.591 | GW157: 930.30215 | GX157: =MAX(GW:GW) -> 1537.0311 | GY157: =GW157/GX157 -> 0.60525917
P158: 156 | Q158: 11288 | R158: 0.136 | S158: 134.54 | T158: 0.028 | U158: 5370 | V158: 0.179 | W158: 1294.038 | X158: 0.09 | Y158: 1043.2692 | Z158: 0.108 | AA158: 8124.36 | AB158: 0.158 | AC158: 6253.308 | AD158: 0.135 | AF158: 156 | AG158: 55001.876 | AH158: 2093 | AI158: 455 | AJ158: 0.618 | AK158: 0.91 | AL158: 0.91 | AM158: 239.666 | AN158: 6695.07 | AO158: 0.371 | AP158: 0.575 | AQ158: 36170.6 | AR158: 20634.525 | AS158: 0.811 | AT158: 0.879 | AV158: 911.184 | AW158: 0.36999992 | AX158: 1024.323 | AY158: 0.63741319 | AZ158: 1121.478 | BA158: 0.57843924 | BC158: 53641.617 | BD158: 0.7704918 | BF158: 29483.574 | BG158: 0 | BH158: 0 | BI158: 0.90440411 | BJ158: 0 | BK158: 0 | BL158: 0 | BM158: 0 | BN158: 4582.625 | BO158: 0.34000779 | BP158: 0 | BQ158: 7668 | BR158: 0 | BT158: -700 | BU158: 0 | BV158: 4485 | BW158: 4485 | BX158: 0 | BY158: 0 | BZ158: -5000 | CA158: 0 | CB158: -5300 | CC158: 0 | CD158: -4000 | CE158: 0 | CF158: -4800 | CG158: 0 | CH158: 20592.228 | CI158: 20592.228 | CJ158: 25077.228 | CL158: -700 | CM158: 700 | CN158: 4485 | CO158: 0 | CP158: 0 | CQ158: 0 | CR158: -5000 | CS158: 5000 | CT158: -5300 | CU158: 5300 | CV158: -4000 | CW158: 4000 | CX158: -4800 | CY158: 4800 | CZ158: 20592.228 | DA158: 0 | DB158: 19800 | DD158: 35902.012 | DE158: 1736.216 | DF158: 2578.038 | DG158: 40216.266 | DH158: 8638.798 | DI158: 54506.411 | DJ158: 9365 | DK158: 63871.411 | DM158: 941.683 | DN158: 10569.629 | DO158: 11511.312 | DP158: 1639.1187 | DQ158: 2939.6344 | DR158: 421.50122 | DS158: 3361.1356 | DT158: 163.31302 | DU158: 163.31302 | DW158: 0 | DX158: 6779.661 | DY158: 1447.7401 | DZ158: 0 | EA158: 0 | EB158: 242.52198 | EC158: 0 | ED158: 1271.1864 | EE158: 0 | EF158: 847.5 | EG158: 0 | EH158: 7397.5989 | EI158: 0 | EJ158: 6779.661 | EK158: 242.52198 | EL158: 847.5 | EM158: 735.835 | EN158: 421.50122 | EO158: 10964.025 | EP158: 0 | ER158: 0 | ES158: 0 | ET158: =(ES158+ER158)/($E$2+$E$3) -> 0 | EU158: 0 | EV158: 0 | EW158: =(EU158+EV158)/($J$2+$J$3) -> 0 | EY158: 2998.6297 | EZ158: 0 | FA158: =(EY158+EZ158)/($E$12+$E$14) -> 0.22042297 | FB158: 0 | FC158: =FB158/$J$10 -> 0 | FF158: 2897.4 | FG158: 10423.35 | FH158: =(FF158+FG158)/($E$13+$E$15) -> 1 | FI158: 3837 | FJ158: =FI158/$J$11 -> 1 | FL158: 7873 | FM158: =FL158/$E$11 -> 0.68245451 | FN158: 2591 | FO158: =FN158/$J$9 -> 0.82634349 | FQ158: 278 | FR158: 367.01 | FS158: =(FQ158+FR158)/($J$8+$J$12) -> 0.81843675 | FT158: =FQ158+FR158 -> 645.01 | FV158: =FW158+FX158-FY158-GA158 -> #REF! | FW158: 242.52198 | FX158: 330 | FY158: =330*#REF! -> #REF! | FZ158: =FV158/1553.6723 -> #REF! | GA158: 0 | GC158: 9732.9149 | GD158: =GC158/32600 -> 0.29855567 | GE158: 1639.1187 | GF158: =GE158/13478 -> 0.12161439 | GH158: 32600 | GI158: 4978.9623 | GK158: 0.257 | GL158: 0.84 | GM158: =-GN158 -> 1517.7758 | GN158: -1517.7758 | GO158: =GM158-1517.77579117 -> 0 | GP158: =GO158/1492.3021 -> 0 | GR158: 26488.442 | GS158: 4668.4676
P159: 157 | Q159: 15272 | R159: 0.184 | S159: 172.98 | T159: 0.036 | U159: 7200 | V159: 0.24 | W159: 2185.4864 | X159: 0.152 | Y159: 1584.2236 | Z159: 0.164 | AA159: 11466.66 | AB159: 0.223 | AC159: 8847.2728 | AD159: 0.191 | AF159: 157 | AG159: 58561.868 | AH159: 2099.9 | AI159: 456.5 | AJ159: 0.658 | AK159: 0.913 | AL159: 0.913 | AM159: 213.826 | AN159: 6799.8624 | AO159: 0.331 | AP159: 0.584 | AQ159: 35501.6 | AR159: 21550.05 | AS159: 0.796 | AT159: 0.918 | AV159: 908.722 | AW159: 0.36900019 | AX159: 1017.357 | AY159: 0.63307841 | AZ159: 1121.478 | BA159: 0.57843924 | BC159: 53641.617 | BD159: 0.7704918 | BF159: 32600 | BG159: 117.562 | BH159: 364.918 | BI159: 1 | BJ159: 0.012696949 | BK159: 0 | BL159: 0 | BM159: 0 | BN159: 4978.962 | BO159: 0.36941401 | BP159: 0 | BQ159: 7668 | BR159: 0 | BT159: -700 | BU159: 0 | BV159: 4485 | BW159: 4485 | BX159: 0 | BY159: 0 | BZ159: -5000 | CA159: 0 | CB159: -5300 | CC159: 0 | CD159: -4000 | CE159: 0 | CF159: -4800 | CG159: 0 | CH159: 23293.241 | CI159: 23293.241 | CJ159: 27778.241 | CL159: -700 | CM159: 700 | CN159: 4485 | CO159: 0 | CP159: 0 | CQ159: 0 | CR159: -5000 | CS159: 5000 | CT159: -5300 | CU159: 5300 | CV159: -4000 | CW159: 4000 | CX159: -4800 | CY159: 4800 | CZ159: 23293.241 | DA159: 0 | DB159: 19800 | DD159: 36858.575 | DE159: 1676.62 | DF159: 2861.3687 | DG159: 41396.564 | DH159: 9593.99 | DI159: 56557.411 | DJ159: 8858 | DK159: 65415.411 | DM159: 916.39 | DN159: 10553.783 | DO159: 11470.173 | DP159: 1639.1187 | DQ159: 2931.2848 | DR159: 429.85082 | DS159: 3361.1356 | DT159: 162.84916 | DU159: 162.84916 | DW159: 0 | DX159: 6779.661 | DY159: 1447.7401 | DZ159: 0 | EA159: 0 | EB159: 242.98584 | EC159: 0 | ED159: 1271.1864 | EE159: 0 | EF159: 847.5 | EG159: 0 | EH159: 7397.5989 | EI159: 0 | EJ159: 6779.661 | EK159: 242.98584 | EL159: 847.5 | EM159: 735.835 | EN159: 429.85082 | EO159: 10964.025 | EP159: 0 | ER159: 0 | ES159: 0 | ET159: =(ES159+ER159)/($E$2+$E$3) -> 0 | EU159: 0 | EV159: 0 | EW159: =(EU159+EV159)/($J$2+$J$3) -> 0 | EY159: 551.08659 | EZ159: 0 | FA159: =(EY159+EZ159)/($E$12+$E$14) -> 0.040509218 | FB159: 0 | FC159: =FB159/$J$10 -> 0 | FF159: 2897.4 | FG159: 10423.35 | FH159: =(FF159+FG159)/($E$13+$E$15) -> 1 | FI159: 659.54797 | FJ159: =FI159/$J$11 -> 0.17189157 | FL159: 7873 | FM159: =FL159/$E$11 -> 0.68245451 | FN159: 2591 | FO159: =FN159/$J$9 -> 0.82634349 | FQ159: 278 | FR159: 367.01 | FS159: =(FQ159+FR159)/($J$8+$J$12) -> 0.81843675 | FT159: =FQ159+FR159 -> 645.01 | FV159: =FW159+FX159-FY159-GA159 -> #REF! | FW159: 242.98584 | FX159: 330 | FY159: =330*#REF! -> #REF! | FZ159: =FV159/1553.6723 -> #REF! | GA159: 0 | GC159: 10192.116 | GD159: =GC159/32600 -> 0.31264158 | GE159: 1639.1187 | GF159: =GE159/13478 -> 0.12161439 | GH159: 32600 | GI159: 5510.4906 | GK159: 0.257 | GL159: 0.84 | GM159: =-GN159 -> 1517.7758 | GN159: -1517.7758 | GO159: =GM159-1517.77579117 -> 0 | GP159: =GO159/1492.3021 -> 0 | GR159: 29483.574 | GS159: 4582.625
P160: 158 | Q160: 17347 | R160: 0.209 | S160: 187.395 | T160: 0.039 | U160: 8160 | V160: 0.272 | W160: 2976.2874 | X160: 0.207 | Y160: 1970.6196 | Z160: 0.204 | AA160: 13934.82 | AB160: 0.271 | AC160: 10514.822 | AD160: 0.227 | AF160: 158 | AG160: 61943.861 | AH160: 2111.4 | AI160: 459 | AJ160: 0.696 | AK160: 0.918 | AL160: 0.918 | AM160: 209.304 | AN160: 7207.3884 | AO160: 0.324 | AP160: 0.619 | AQ160: 35590.8 | AR160: 22207.35 | AS160: 0.798 | AT160: 0.946 | AV160: 911.184 | AW160: 0.36999992 | AX160: 1014.687 | AY160: 0.63141693 | AZ160: 1121.478 | BA160: 0.57843924 | BC160: 53641.617 | BD160: 0.7704918 | BF160: 32600 | BG160: 761.295 | BH160: 2202.545 | BI160: 1 | BJ160: 0.077996446 | BK160: 0 | BL160: 0 | BM160: 0 | BN160: 5510.491 | BO160: 0.40885079 | BP160: 0 | BQ160: 7668 | BR160: 0 | BT160: -700 | BU160: 0 | BV160: 4485 | BW160: 4485 | BX160: 0 | BY160: 0 | BZ160: -5000 | CA160: 0 | CB160: -5300 | CC160: 0 | CD160: -4000 | CE160: 0 | CF160: -4800 | CG160: 0 | CH160: 25924.268 | CI160: 25924.268 | CJ160: 30409.268 | CL160: -700 | CM160: 700 | CN160: 4485 | CO160: 0 | CP160: 0 | CQ160: 0 | CR160: -5000 | CS160: 5000 | CT160: -5300 | CU160: 5300 | CV160: -4000 | CW160: 4000 | CX160: -4800 | CY160: 4800 | CZ160: 25924.268 | DA160: 0 | DB160: 19800 | DD160: 37272.042 | DE160: 1696.915 | DF160: 2565.5269 | DG160: 41534.484 | DH160: 9738.678 | DI160: 54547.411 | DJ160: 8496 | DK160: 63043.411 | DM160: 899.38 | DN160: 10553.783 | DO160: 11453.163 | DP160: 1639.1187 | DQ160: 2931.2848 | DR160: 429.85082 | DS160: 3361.1356 | DT160: 162.84916 | DU160: 162.84916 | DW160: 0 | DX160: 6779.661 | DY160: 1447.7401 | DZ160: 0 | EA160: 0 | EB160: 242.98584 | EC160: 0 | ED160: 1271.1864 | EE160: 0 | EF160: 847.5 | EG160: 0 | EH160: 7397.5989 | EI160: 0 | EJ160: 6779.661 | EK160: 242.98584 | EL160: 847.5 | EM160: 735.835 | EN160: 429.85082 | EO160: 10964.025 | EP160: 0 | ER160: 0 | ES160: 0 | ET160: =(ES160+ER160)/($E$2+$E$3) -> 0 | EU160: 0 | EV160: 0 | EW160: =(EU160+EV160)/($J$2+$J$3) -> 0 | EY160: 0 | EZ160: 0 | FA160: =(EY160+EZ160)/($E$12+$E$14) -> 0 | FB160: 0 | FC160: =FB160/$J$10 -> 0 | FF160: 2897.4 | FG160: 10423.35 | FH160: =(FF160+FG160)/($E$13+$E$15) -> 1 | FI160: 3837 | FJ160: =FI160/$J$11 -> 1 | FL160: 7873 | FM160: =FL160/$E$11 -> 0.68245451 | FN160: 2591 | FO160: =FN160/$J$9 -> 0.82634349 | FQ160: 0 | FR160: 367.01 | FS160: =(FQ160+FR160)/($J$8+$J$12) -> 0.46568963 | FT160: =FQ160+FR160 -> 367.01 | FV160: =FW160+FX160-FY160-GA160 -> #REF! | FW160: 242.98584 | FX160: 330 | FY160: =330*#REF! -> #REF! | FZ160: =FV160/1553.6723 -> #REF! | GA160: 0 | GC160: 12669.101 | GD160: =GC160/32600 -> 0.38862272 | GE160: 1639.1187 | GF160: =GE160/13478 -> 0.12161439 | GH160: 32600 | GI160: 5844.0984 | GK160: 0.257 | GL160: 0.84 | GM160: =-GN160 -> 1517.7758 | GN160: -1517.7758 | GO160: =GM160-1517.77579117 -> 0 | GP160: =GO160/1492.3021 -> 0 | GR160: 32600 | GS160: 4978.9623
P161: 159 | Q161: 17347 | R161: 0.209 | S161: 163.37 | T161: 0.034 | U161: 7920 | V161: 0.264 | W161: 3436.3898 | X161: 0.239 | Y161: 2057.5587 | Z161: 0.213 | AA161: 14346.18 | AB161: 0.279 | AC161: 10329.538 | AD161: 0.223 | AF161: 159 | AG161: 64168.856 | AH161: 2118.3 | AI161: 460.5 | AJ161: 0.721 | AK161: 0.921 | AL161: 0.921 | AM161: 214.472 | AN161: 7335.468 | AO161: 0.332 | AP161: 0.63 | AQ161: 36259.8 | AR161: 22512.525 | AS161: 0.813 | AT161: 0.959 | AV161: 913.647 | AW161: 0.37100006 | AX161: 1004.417 | AY161: 0.62502614 | AZ161: 1121.478 | BA161: 0.57843924 | BC161: 53641.617 | BD161: 0.7704918 | BF161: 32600 | BG161: 934.546 | BH161: 2844.448 | BI161: 1 | BJ161: 0.099448048 | BK161: 0 | BL161: 0 | BM161: 0 | BN161: 5844.098 | BO161: 0.43360276 | BP161: 0 | BQ161: 7668 | BR161: 0 | BT161: -700 | BU161: 0 | BV161: 4485 | BW161: 4485 | BX161: 0 | BY161: 0 | BZ161: -5000 | CA161: 0 | CB161: -5300 | CC161: 0 | CD161: -4000 | CE161: 0 | CF161: -4800 | CG161: 0 | CH161: 26310.574 | CI161: 26310.574 | CJ161: 30795.574 | CL161: -700 | CM161: 700 | CN161: 4485 | CO161: 0 | CP161: 0 | CQ161: 0 | CR161: -5000 | CS161: 5000 | CT161: -5300 | CU161: 5300 | CV161: -4000 | CW161: 4000 | CX161: -4800 | CY161: 4800 | CZ161: 26310.574 | DA161: 0 | DB161: 19800 | DD161: 36194.607 | DE161: 1894.821 | DF161: 1930.2141 | DG161: 40019.642 | DH161: 9656.439 | DI161: 53531.411 | DJ161: 8304 | DK161: 61835.411 | DM161: 895.109 | DN161: 10569.629 | DO161: 11464.738 | DP161: 1639.1187 | DQ161: 2939.6344 | DR161: 421.50122 | DS161: 3361.1356 | DT161: 163.31302 | DU161: 163.31302 | DW161: 0 | DX161: 6779.661 | DY161: 1447.7401 | DZ161: 0 | EA161: 0 | EB161: 242.52198 | EC161: 0 | ED161: 1271.1864 | EE161: 0 | EF161: 847.5 | EG161: 0 | EH161: 7397.5989 | EI161: 0 | EJ161: 6779.661 | EK161: 242.52198 | EL161: 847.5 | EM161: 735.835 | EN161: 421.50122 | EO161: 10964.025 | EP161: 0 | ER161: 0 | ES161: 0 | ET161: =(ES161+ER161)/($E$2+$E$3) -> 0 | EU161: 0 | EV161: 0 | EW161: =(EU161+EV161)/($J$2+$J$3) -> 0 | EY161: 0 | EZ161: 0 | FA161: =(EY161+EZ161)/($E$12+$E$14) -> 0 | FB161: 0 | FC161: =FB161/$J$10 -> 0 | FF161: 2897.4 | FG161: 10423.35 | FH161: =(FF161+FG161)/($E$13+$E$15) -> 1 | FI161: 3837 | FJ161: =FI161/$J$11 -> 1 | FL161: 7873 | FM161: =FL161/$E$11 -> 0.68245451 | FN161: 2591 | FO161: =FN161/$J$9 -> 0.82634349 | FQ161: 278 | FR161: 367.01 | FS161: =(FQ161+FR161)/($J$8+$J$12) -> 0.81843675 | FT161: =FQ161+FR161 -> 645.01 | FV161: =FW161+FX161-FY161-GA161 -> #REF! | FW161: 242.52198 | FX161: 330 | FY161: =330*#REF! -> #REF! | FZ161: =FV161/1553.6723 -> #REF! | GA161: 0 | GC161: 13499.93 | GD161: =GC161/32600 -> 0.41410828 | GE161: 1639.1187 | GF161: =GE161/13478 -> 0.12161439 | GH161: 32600 | GI161: 5522.1392 | GK161: 0.257 | GL161: 0.84 | GM161: =-GN161 -> 1517.7758 | GN161: -1517.7758 | GO161: =GM161-1517.77579117 -> 0 | GP161: =GO161/1492.3021 -> 0 | GR161: 32600 | GS161: 5510.4906
P162: 160 | Q162: 14442 | R162: 0.174 | S162: 105.71 | T162: 0.022 | U162: 6120 | V162: 0.204 | W162: 3048.1784 | X162: 0.212 | Y162: 1680.8226 | Z162: 0.174 | AA162: 9821.22 | AB162: 0.191 | AC162: 6855.4784 | AD162: 0.148 | AF162: 160 | AG162: 65770.852 | AH162: 2122.9 | AI162: 461.5 | AJ162: 0.739 | AK162: 0.923 | AL162: 0.923 | AM162: 220.932 | AN162: 7184.1012 | AO162: 0.342 | AP162: 0.617 | AQ162: 36928.8 | AR162: 22536 | AS162: 0.828 | AT162: 0.96 | AV162: 901.334 | AW162: 0.36600018 | AX162: 998.851 | AY162: 0.62156254 | AZ162: 1121.478 | BA162: 0.57843924 | BC162: 53641.617 | BD162: 0.7704918 | BF162: 32600 | BG162: 543.825 | BH162: 2128.309 | BI162: 1 | BJ162: 0.070319908 | BK162: 0 | BL162: 0 | BM162: 0 | BN162: 5522.139 | BO162: 0.40971502 | BP162: 0 | BQ162: 7668 | BR162: 0 | BT162: -700 | BU162: 0 | BV162: 4485 | BW162: 4485 | BX162: 0 | BY162: 0 | BZ162: -5000 | CA162: 0 | CB162: -5300 | CC162: 0 | CD162: -4000 | CE162: 0 | CF162: -4800 | CG162: 0 | CH162: 25664.11 | CI162: 25664.11 | CJ162: 30149.11 | CL162: -700 | CM162: 700 | CN162: 4485 | CO162: 0 | CP162: 0 | CQ162: 0 | CR162: -5000 | CS162: 5000 | CT162: -5300 | CU162: 5300 | CV162: -4000 | CW162: 4000 | CX162: -4800 | CY162: 4800 | CZ162: 25664.11 | DA162: 0 | DB162: 19800 | DD162: 35482.705 | DE162: 2031.595 | DF162: 1637.9074 | DG162: 39152.207 | DH162: 9420.32 | DI162: 53144.411 | DJ162: 9066 | DK162: 62210.411 | DM162: 901.026 | DN162: 10553.783 | DO162: 11454.809 | DP162: 1455.3989 | DQ162: 2931.2848 | DR162: 429.85082 | DS162: 3361.1356 | DT162: 162.84916 | DU162: 162.84916 | DW162: 0 | DX162: 6779.661 | DY162: 1447.7401 | DZ162: 0 | EA162: 0 | EB162: 242.98584 | EC162: 0 | ED162: 1271.1864 | EE162: 0 | EF162: 847.5 | EG162: 0 | EH162: 7397.5989 | EI162: 0 | EJ162: 6779.661 | EK162: 242.98584 | EL162: 847.5 | EM162: 735.835 | EN162: 429.85082 | EO162: 10964.025 | EP162: 0 | ER162: 0 | ES162: 0 | ET162: =(ES162+ER162)/($E$2+$E$3) -> 0 | EU162: 0 | EV162: 0 | EW162: =(EU162+EV162)/($J$2+$J$3) -> 0 | EY162: 0 | EZ162: 0 | FA162: =(EY162+EZ162)/($E$12+$E$14) -> 0 | FB162: 0 | FC162: =FB162/$J$10 -> 0 | FF162: 2897.4 | FG162: 10423.35 | FH162: =(FF162+FG162)/($E$13+$E$15) -> 1 | FI162: 3837 | FJ162: =FI162/$J$11 -> 1 | FL162: 7873 | FM162: =FL162/$E$11 -> 0.68245451 | FN162: 2591 | FO162: =FN162/$J$9 -> 0.82634349 | FQ162: 218.69847 | FR162: 367.01 | FS162: =(FQ162+FR162)/($J$8+$J$12) -> 0.74319054 | FT162: =FQ162+FR162 -> 585.70847 | FV162: =FW162+FX162-FY162-GA162 -> #REF! | FW162: 242.98584 | FX162: 330 | FY162: =330*#REF! -> #REF! | FZ162: =FV162/1553.6723 -> #REF! | GA162: 0 | GC162: 9705.684 | GD162: =GC162/32600 -> 0.29772037 | GE162: 1455.3989 | GF162: =GE162/13478 -> 0.1079833 | GH162: 32600 | GI162: 4794.9756 | GK162: 0.257 | GL162: 0.84 | GM162: =-GN162 -> 1517.7758 | GN162: -1517.7758 | GO162: =GM162-1517.77579117 -> 0 | GP162: =GO162/1492.3021 -> 0 | GR162: 32600 | GS162: 5844.0984
P163: 161 | Q163: 9296 | R163: 0.112 | S163: 0 | T163: 0 | U163: 3570 | V163: 0.119 | W163: 2300.512 | X163: 0.16 | Y163: 1081.9088 | Z163: 0.112 | AA163: 4473.54 | AB163: 0.087 | AC163: 2918.2104 | AD163: 0.063 | AF163: 161 | AG163: 69152.845 | AH163: 2125.2 | AI163: 462 | AJ163: 0.777 | AK163: 0.924 | AL163: 0.924 | AM163: 220.286 | AN163: 7125.8832 | AO163: 0.341 | AP163: 0.612 | AQ163: 37241 | AR163: 22465.575 | AS163: 0.835 | AT163: 0.957 | AV163: 916.11 | AW163: 0.37200019 | AX163: 1003.027 | AY163: 0.62416117 | AZ163: 1121.478 | BA163: 0.57843924 | BC163: 53641.617 | BD163: 0.7704918 | BF163: 32600 | BG163: 168.406 | BH163: 1135.772 | BI163: 1 | BJ163: 0.034320763 | BK163: 0 | BL163: 0 | BM163: 0 | BN163: 4794.976 | BO163: 0.35576317 | BP163: 0 | BQ163: 7668 | BR163: 0 | BT163: -700 | BU163: 0 | BV163: 4485 | BW163: 4485 | BX163: 0 | BY163: 0 | BZ163: -5000 | CA163: 0 | CB163: -5300 | CC163: 0 | CD163: -4000 | CE163: 0 | CF163: -4800 | CG163: 0 | CH163: 21176.457 | CI163: 21176.457 | CJ163: 25661.457 | CL163: -700 | CM163: 700 | CN163: 4485 | CO163: 0 | CP163: 0 | CQ163: 0 | CR163: -5000 | CS163: 5000 | CT163: -5300 | CU163: 5300 | CV163: -4000 | CW163: 4000 | CX163: -4800 | CY163: 4800 | CZ163: 21176.457 | DA163: 0 | DB163: 19800 | DD163: 35524.81 | DE163: 2055.689 | DF163: 1632.8602 | DG163: 39213.359 | DH163: 9212.378 | DI163: 54704.411 | DJ163: 9032 | DK163: 63736.411 | DM163: 899.172 | DN163: 10553.783 | DO163: 11452.955 | DP163: 1455.3989 | DQ163: 2931.2848 | DR163: 429.85082 | DS163: 3361.1356 | DT163: 162.84916 | DU163: 162.84916 | DW163: 0 | DX163: 6779.661 | DY163: 1447.7401 | DZ163: 0 | EA163: 0 | EB163: 242.98584 | EC163: 0 | ED163: 1271.1864 | EE163: 0 | EF163: 847.5 | EG163: 0 | EH163: 7397.5989 | EI163: 0 | EJ163: 6779.661 | EK163: 242.98584 | EL163: 847.5 | EM163: 735.835 | EN163: 429.85082 | EO163: 10964.025 | EP163: 0 | ER163: 0 | ES163: 0 | ET163: =(ES163+ER163)/($E$2+$E$3) -> 0 | EU163: 0 | EV163: 0 | EW163: =(EU163+EV163)/($J$2+$J$3) -> 0 | EY163: 0 | EZ163: 0 | FA163: =(EY163+EZ163)/($E$12+$E$14) -> 0 | FB163: 0 | FC163: =FB163/$J$10 -> 0 | FF163: 2897.4 | FG163: 10423.35 | FH163: =(FF163+FG163)/($E$13+$E$15) -> 1 | FI163: 3837 | FJ163: =FI163/$J$11 -> 1 | FL163: 7873 | FM163: =FL163/$E$11 -> 0.68245451 | FN163: 2591 | FO163: =FN163/$J$9 -> 0.82634349 | FQ163: 0 | FR163: 367.01 | FS163: =(FQ163+FR163)/($J$8+$J$12) -> 0.46568963 | FT163: =FQ163+FR163 -> 367.01 | FV163: =FW163+FX163-FY163-GA163 -> #REF! | FW163: 242.98584 | FX163: 330 | FY163: =330*#REF! -> #REF! | FZ163: =FV163/1553.6723 -> #REF! | GA163: 0 | GC163: 9705.2072 | GD163: =GC163/32600 -> 0.29770574 | GE163: 1455.3989 | GF163: =GE163/13478 -> 0.1079833 | GH163: 30243.231 | GI163: 3960.0947 | GK163: 0.257 | GL163: 0.84 | GM163: =-GN163 -> 1517.7758 | GN163: -1517.7758 | GO163: =GM163-1517.77579117 -> 0 | GP163: =GO163/1492.3021 -> 0 | GR163: 32600 | GS163: 5522.1392
P164: 162 | Q164: 2324 | R164: 0.028 | S164: 0 | T164: 0 | U164: 960 | V164: 0.032 | W164: 1308.4162 | X164: 0.091 | Y164: 434.6955 | Z164: 0.045 | AA164: 0 | AB164: 0 | AC164: 0 | AD164: 0 | AF164: 162 | AG164: 68173.847 | AH164: 2122.9 | AI164: 461.5 | AJ164: 0.766 | AK164: 0.923 | AL164: 0.923 | AM164: 221.578 | AN164: 6019.7412 | AO164: 0.343 | AP164: 0.517 | AQ164: 35546.2 | AR164: 22442.1 | AS164: 0.797 | AT164: 0.956 | AV164: 923.497 | AW164: 0.3749998 | AX164: 1006.406 | AY164: 0.62626385 | AZ164: 1121.478 | BA164: 0.57843924 | BC164: 53641.617 | BD164: 0.7704918 | BF164: 30243.231 | BG164: 0 | BH164: 0 | BI164: 0.92770647 | BJ164: 0 | BK164: 0 | BL164: 0 | BM164: 0 | BN164: 3960.095 | BO164: 0.29381919 | BP164: 0 | BQ164: 7668 | BR164: 0 | BT164: -700 | BU164: 0 | BV164: 4485 | BW164: 4485 | BX164: 0 | BY164: 0 | BZ164: -5000 | CA164: 0 | CB164: -5300 | CC164: 0 | CD164: -4000 | CE164: 0 | CF164: -4800 | CG164: 0 | CH164: 19961.347 | CI164: 19961.347 | CJ164: 24446.347 | CL164: -700 | CM164: 700 | CN164: 4485 | CO164: 0 | CP164: 0 | CQ164: 0 | CR164: -5000 | CS164: 5000 | CT164: -5300 | CU164: 5300 | CV164: -4000 | CW164: 4000 | CX164: -4800 | CY164: 4800 | CZ164: 19961.347 | DA164: 0 | DB164: 19800 | DD164: 37301.246 | DE164: 2217.583 | DF164: 1706.7499 | DG164: 41225.579 | DH164: 9355.285 | DI164: 57836.411 | DJ164: 9500 | DK164: 67336.411 | DM164: 881.502 | DN164: 10553.783 | DO164: 11435.285 | DP164: 1455.3989 | DQ164: 2931.2848 | DR164: 429.85082 | DS164: 3361.1356 | DT164: 162.84916 | DU164: 162.84916 | DW164: 0 | DX164: 6779.661 | DY164: 1447.7401 | DZ164: 0 | EA164: 0 | EB164: 242.98584 | EC164: 0 | ED164: 1271.1864 | EE164: 0 | EF164: 847.5 | EG164: 0 | EH164: 7397.5989 | EI164: 0 | EJ164: 6779.661 | EK164: 242.98584 | EL164: 847.5 | EM164: 735.835 | EN164: 429.85082 | EO164: 10964.025 | EP164: 0 | ER164: 0 | ES164: 0 | ET164: =(ES164+ER164)/($E$2+$E$3) -> 0 | EU164: 0 | EV164: 0 | EW164: =(EU164+EV164)/($J$2+$J$3) -> 0 | EY164: 2973.3031 | EZ164: 0 | FA164: =(EY164+EZ164)/($E$12+$E$14) -> 0.21856127 | FB164: 0 | FC164: =FB164/$J$10 -> 0 | FF164: 2897.4 | FG164: 0 | FH164: =(FF164+FG164)/($E$13+$E$15) -> 0.21751028 | FI164: 1530.0317 | FJ164: =FI164/$J$11 -> 0.39875729 | FL164: 7873 | FM164: =FL164/$E$11 -> 0.68245451 | FN164: 2591 | FO164: =FN164/$J$9 -> 0.82634349 | FQ164: 0 | FR164: 367.01 | FS164: =(FQ164+FR164)/($J$8+$J$12) -> 0.46568963 | FT164: =FQ164+FR164 -> 367.01 | FV164: =FW164+FX164-FY164-GA164 -> #REF! | FW164: 242.98584 | FX164: 330 | FY164: =330*#REF! -> #REF! | FZ164: =FV164/1553.6723 -> #REF! | GA164: 0 | GC164: 20705.662 | GD164: =GC164/32600 -> 0.63514302 | GE164: 1455.3989 | GF164: =GE164/13478 -> 0.1079833 | GH164: 27240.467 | GI164: 3136.3065 | GK164: 0.257 | GL164: 0.84 | GM164: =-GN164 -> 1517.7758 | GN164: -1517.7758 | GO164: =GM164-1517.77579117 -> 0 | GP164: =GO164/1492.3021 -> 0 | GR164: 32600 | GS164: 4794.9756
P165: 163 | Q165: 0 | R165: 0 | S165: 0 | T165: 0 | U165: 0 | V165: 0 | W165: 0 | X165: 0 | Y165: 0 | Z165: 0 | AA165: 0 | AB165: 0 | AC165: 0 | AD165: 0 | AF165: 163 | AG165: 63812.857 | AH165: 2118.3 | AI165: 460.5 | AJ165: 0.717 | AK165: 0.921 | AL165: 0.921 | AM165: 219.64 | AN165: 3772.5264 | AO165: 0.34 | AP165: 0.324 | AQ165: 34386.6 | AR165: 22301.25 | AS165: 0.771 | AT165: 0.95 | AV165: 925.96 | AW165: 0.37599994 | AX165: 1007.8 | AY165: 0.6271313 | AZ165: 1121.478 | BA165: 0.57843924 | BC165: 53641.617 | BD165: 0.7704918 | BF165: 27240.467 | BG165: 0 | BH165: 0 | BI165: 0.83559715 | BJ165: 0 | BK165: 0 | BL165: 0 | BM165: 0 | BN165: 3136.307 | BO165: 0.23269825 | BP165: 0 | BQ165: 7668 | BR165: 0 | BT165: -700 | BU165: 0 | BV165: 4485 | BW165: 4485 | BX165: 0 | BY165: 0 | BZ165: -5000 | CA165: 0 | CB165: -5300 | CC165: 0 | CD165: -4000 | CE165: 0 | CF165: -4800 | CG165: 0 | CH165: 16343.859 | CI165: 16343.859 | CJ165: 20828.859 | CL165: -700 | CM165: 700 | CN165: 4485 | CO165: 0 | CP165: 0 | CQ165: 0 | CR165: -5000 | CS165: 5000 | CT165: -5300 | CU165: 5300 | CV165: -4000 | CW165: 4000 | CX165: -4800 | CY165: 4800 | CZ165: 16343.859 | DA165: 0 | DB165: 19800 | DD165: 38251.662 | DE165: 2316.568 | DF165: 1812.6673 | DG165: 42380.897 | DH165: 9407.565 | DI165: 59335.411 | DJ165: 9099 | DK165: 68434.411 | DM165: 876.221 | DN165: 10569.629 | DO165: 11445.85 | DP165: 1455.3989 | DQ165: 2939.6344 | DR165: 421.50122 | DS165: 3361.1356 | DT165: 163.31302 | DU165: 163.31302 | DW165: 0 | DX165: 6779.661 | DY165: 1447.7401 | DZ165: 0 | EA165: 0 | EB165: 242.52198 | EC165: 0 | ED165: 1271.1864 | EE165: 0 | EF165: 847.5 | EG165: 0 | EH165: 7397.5989 | EI165: 0 | EJ165: 6779.661 | EK165: 242.52198 | EL165: 847.5 | EM165: 735.835 | EN165: 421.50122 | EO165: 10964.025 | EP165: 0 | ER165: 0 | ES165: 0 | ET165: =(ES165+ER165)/($E$2+$E$3) -> 0 | EU165: 0 | EV165: 0 | EW165: =(EU165+EV165)/($J$2+$J$3) -> 0 | EY165: 0 | EZ165: 0 | FA165: =(EY165+EZ165)/($E$12+$E$14) -> 0 | FB165: 2064.9702 | FC165: =FB165/$J$10 -> 0.44764148 | FF165: 2897.4 | FG165: 0 | FH165: =(FF165+FG165)/($E$13+$E$15) -> 0.21751028 | FI165: 0 | FJ165: =FI165/$J$11 -> 0 | FL165: 7873 | FM165: =FL165/$E$11 -> 0.68245451 | FN165: 2591 | FO165: =FN165/$J$9 -> 0.82634349 | FQ165: 278 | FR165: 367.01 | FS165: =(FQ165+FR165)/($J$8+$J$12) -> 0.81843675 | FT165: =FQ165+FR165 -> 645.01 | FV165: =FW165+FX165-FY165-GA165 -> #REF! | FW165: 242.52198 | FX165: 330 | FY165: =330*#REF! -> #REF! | FZ165: =FV165/1553.6723 -> #REF! | GA165: 0 | GC165: 9716.078 | GD165: =GC165/32600 -> 0.2980392 | GE165: 1455.3989 | GF165: =GE165/13478 -> 0.1079833 | GH165: 26492.049 | GI165: 3067.5387 | GK165: 0.257 | GL165: 0.84 | GM165: =-GN165 -> 1517.7758 | GN165: -1517.7758 | GO165: =GM165-1517.77579117 -> 0 | GP165: =GO165/1492.3021 -> 0 | GR165: 30243.231 | GS165: 3960.0947
P166: 164 | Q166: 0 | R166: 0 | S166: 0 | T166: 0 | U166: 0 | V166: 0 | W166: 0 | X166: 0 | Y166: 0 | Z166: 0 | AA166: 0 | AB166: 0 | AC166: 0 | AD166: 0 | AF166: 164 | AG166: 62032.861 | AH166: 2122.9 | AI166: 461.5 | AJ166: 0.697 | AK166: 0.923 | AL166: 0.923 | AM166: 218.348 | AN166: 2922.5436 | AO166: 0.338 | AP166: 0.251 | AQ166: 34431.2 | AR166: 22043.025 | AS166: 0.772 | AT166: 0.939 | AV166: 925.96 | AW166: 0.37599994 | AX166: 1012.452 | AY166: 0.63002614 | AZ166: 1121.478 | BA166: 0.57843924 | BC166: 53641.617 | BD166: 0.7704918 | BF166: 26492.049 | BG166: 0 | BH166: 0 | BI166: 0.81263954 | BJ166: 0 | BK166: 0 | BL166: 0 | BM166: 0 | BN166: 3067.539 | BO166: 0.22759601 | BP166: 0 | BQ166: 7668 | BR166: 0 | BT166: -700 | BU166: 0 | BV166: 4485 | BW166: 4485 | BX166: 0 | BY166: 0 | BZ166: -5000 | CA166: 0 | CB166: -5300 | CC166: 0 | CD166: -4000 | CE166: 0 | CF166: -4800 | CG166: 0 | CH166: 26004.06 | CI166: 26004.06 | CJ166: 30489.06 | CL166: -700 | CM166: 700 | CN166: 4485 | CO166: 0 | CP166: 0 | CQ166: 0 | CR166: -5000 | CS166: 5000 | CT166: -5300 | CU166: 5300 | CV166: -4000 | CW166: 4000 | CX166: -4800 | CY166: 4800 | CZ166: 26004.06 | DA166: 0 | DB166: 19800 | DD166: 38545.404 | DE166: 2318.469 | DF166: 1932.658 | DG166: 42796.531 | DH166: 9485.728 | DI166: 59483.411 | DJ166: 8575 | DK166: 68058.411 | DM166: 865.381 | DN166: 10553.783 | DO166: 11419.164 | DP166: 1455.3989 | DQ166: 2931.2848 | DR166: 429.85082 | DS166: 3361.1356 | DT166: 162.84916 | DU166: 162.84916 | DW166: 0 | DX166: 6779.661 | DY166: 1447.7401 | DZ166: 0 | EA166: 0 | EB166: 242.98584 | EC166: 0 | ED166: 1271.1864 | EE166: 0 | EF166: 847.5 | EG166: 0 | EH166: 7397.5989 | EI166: 0 | EJ166: 6779.661 | EK166: 242.98584 | EL166: 847.5 | EM166: 735.835 | EN166: 429.85082 | EO166: 10964.025 | EP166: 0 | ER166: 0 | ES166: 0 | ET166: =(ES166+ER166)/($E$2+$E$3) -> 0 | EU166: 0 | EV166: 0 | EW166: =(EU166+EV166)/($J$2+$J$3) -> 0 | EY166: 0 | EZ166: 0 | FA166: =(EY166+EZ166)/($E$12+$E$14) -> 0 | FB166: 4613 | FC166: =FB166/$J$10 -> 1 | FF166: 2897.4 | FG166: 10423.35 | FH166: =(FF166+FG166)/($E$13+$E$15) -> 1 | FI166: 3837 | FJ166: =FI166/$J$11 -> 1 | FL166: 7873 | FM166: =FL166/$E$11 -> 0.68245451 | FN166: 2591 | FO166: =FN166/$J$9 -> 0.82634349 | FQ166: 278 | FR166: 367.01 | FS166: =(FQ166+FR166)/($J$8+$J$12) -> 0.81843675 | FT166: =FQ166+FR166 -> 645.01 | FV166: =FW166+FX166-FY166-GA166 -> #REF! | FW166: 242.98584 | FX166: 330 | FY166: =330*#REF! -> #REF! | FZ166: =FV166/1553.6723 -> #REF! | GA166: 0 | GC166: 18809.355 | GD166: =GC166/32600 -> 0.57697407 | GE166: 1455.3989 | GF166: =GE166/13478 -> 0.1079833 | GH166: 26700.265 | GI166: 3233.3349 | GK166: 0.257 | GL166: 0.84 | GM166: =-GN166 -> 1517.7758 | GN166: -1517.7758 | GO166: =GM166-1517.77579117 -> 0 | GP166: =GO166/1492.3021 -> 0 | GR166: 27240.467 | GS166: 3136.3065
P167: 165 | Q167: 0 | R167: 0 | S167: 0 | T167: 0 | U167: 0 | V167: 0 | W167: 0 | X167: 0 | Y167: 0 | Z167: 0 | AA167: 0 | AB167: 0 | AC167: 0 | AD167: 0 | AF167: 165 | AG167: 62566.859 | AH167: 2129.8 | AI167: 463 | AJ167: 0.703 | AK167: 0.926 | AL167: 0.926 | AM167: 229.976 | AN167: 2561.592 | AO167: 0.356 | AP167: 0.22 | AQ167: 34877.2 | AR167: 21831.75 | AS167: 0.782 | AT167: 0.93 | AV167: 925.96 | AW167: 0.37599994 | AX167: 1021.498 | AY167: 0.63565526 | AZ167: 1121.478 | BA167: 0.57843924 | BC167: 53641.617 | BD167: 0.7704918 | BF167: 26700.265 | BG167: 0 | BH167: 0 | BI167: 0.81902653 | BJ167: 0 | BK167: 0 | BL167: 0 | BM167: 0 | BN167: 3233.335 | BO167: 0.23989724 | BP167: 0 | BQ167: 7668 | BR167: 0 | BT167: -700 | BU167: 0 | BV167: 4485 | BW167: 4485 | BX167: 0 | BY167: 0 | BZ167: -5000 | CA167: 0 | CB167: -5300 | CC167: 0 | CD167: -4000 | CE167: 0 | CF167: -4800 | CG167: 0 | CH167: 18367.891 | CI167: 18367.891 | CJ167: 22852.891 | CL167: -700 | CM167: 700 | CN167: 4485 | CO167: 0 | CP167: 0 | CQ167: 0 | CR167: -5000 | CS167: 5000 | CT167: -5300 | CU167: 5300 | CV167: -4000 | CW167: 4000 | CX167: -4800 | CY167: 4800 | CZ167: 18367.891 | DA167: 0 | DB167: 19800 | DD167: 38210.756 | DE167: 2319.225 | DF167: 1902.0341 | DG167: 42432.015 | DH167: 9216.625 | DI167: 57668.411 | DJ167: 8661 | DK167: 66329.411 | DM167: 816.726 | DN167: 10537.937 | DO167: 11354.663 | DP167: 1455.3989 | DQ167: 2922.9352 | DR167: 438.20043 | DS167: 3361.1356 | DT167: 162.38529 | DU167: 162.38529 | DW167: 0 | DX167: 6779.661 | DY167: 1447.7401 | DZ167: 0 | EA167: 0 | EB167: 243.44971 | EC167: 0 | ED167: 1271.1864 | EE167: 0 | EF167: 847.5 | EG167: 0 | EH167: 7397.5989 | EI167: 0 | EJ167: 6779.661 | EK167: 243.44971 | EL167: 847.5 | EM167: 735.835 | EN167: 438.20043 | EO167: 10964.025 | EP167: 0 | ER167: 0 | ES167: 0 | ET167: =(ES167+ER167)/($E$2+$E$3) -> 0 | EU167: 0 | EV167: 0 | EW167: =(EU167+EV167)/($J$2+$J$3) -> 0 | EY167: 0 | EZ167: 0 | FA167: =(EY167+EZ167)/($E$12+$E$14) -> 0 | FB167: 3999.9156 | FC167: =FB167/$J$10 -> 0.86709638 | FF167: 2897.4 | FG167: 10423.35 | FH167: =(FF167+FG167)/($E$13+$E$15) -> 1 | FI167: 3837 | FJ167: =FI167/$J$11 -> 1 | FL167: 7873 | FM167: =FL167/$E$11 -> 0.68245451 | FN167: 2591 | FO167: =FN167/$J$9 -> 0.82634349 | FQ167: 0 | FR167: 367.01 | FS167: =(FQ167+FR167)/($J$8+$J$12) -> 0.46568963 | FT167: =FQ167+FR167 -> 367.01 | FV167: =FW167+FX167-FY167-GA167 -> #REF! | FW167: 243.44971 | FX167: 330 | FY167: =330*#REF! -> #REF! | FZ167: =FV167/1553.6723 -> #REF! | GA167: 0 | GC167: 9667.2281 | GD167: =GC167/32600 -> 0.29654074 | GE167: 1455.3989 | GF167: =GE167/13478 -> 0.1079833 | GH167: 27241.19 | GI167: 3574.5305 | GK167: 0.257 | GL167: 0.84 | GM167: =-GN167 -> 1517.7758 | GN167: -1517.7758 | GO167: =GM167-1517.77579117 -> 0 | GP167: =GO167/1492.3021 -> 0 | GR167: 26492.049 | GS167: 3067.5387
P168: 166 | Q168: 0 | R168: 0 | S168: 0 | T168: 0 | U168: 0 | V168: 0 | W168: 0 | X168: 0 | Y168: 0 | Z168: 0 | AA168: 0 | AB168: 0 | AC168: 0 | AD168: 0 | AF168: 166 | AG168: 63812.857 | AH168: 2136.7 | AI168: 464.5 | AJ168: 0.717 | AK168: 0.929 | AL168: 0.929 | AM168: 255.17 | AN168: 2712.9588 | AO168: 0.395 | AP168: 0.233 | AQ168: 35189.4 | AR168: 21385.725 | AS168: 0.789 | AT168: 0.911 | AV168: 928.423 | AW168: 0.37700007 | AX168: 1023.155 | AY168: 0.63668637 | AZ168: 1121.478 | BA168: 0.57843924 | BC168: 53641.617 | BD168: 0.7704918 | BF168: 27241.19 | BG168: 0 | BH168: 0 | BI168: 0.83561933 | BJ168: 0 | BK168: 0 | BL168: 0 | BM168: 0 | BN168: 3574.53 | BO168: 0.2652122 | BP168: 0 | BQ168: 7668 | BR168: 0 | BT168: -700 | BU168: 0 | BV168: 4485 | BW168: 4485 | BX168: 0 | BY168: 0 | BZ168: -5000 | CA168: 0 | CB168: -5300 | CC168: 0 | CD168: -4000 | CE168: 0 | CF168: -4800 | CG168: 0 | CH168: 37664.788 | CI168: 37664.788 | CJ168: 42149.788 | CL168: -700 | CM168: 700 | CN168: 4485 | CO168: 0 | CP168: 0 | CQ168: 0 | CR168: -5000 | CS168: 5000 | CT168: -5300 | CU168: 5300 | CV168: -4000 | CW168: 4000 | CX168: -4800 | CY168: 4800 | CZ168: 37664.788 | DA168: 0 | DB168: 19800 | DD168: 36905.48 | DE168: 2320.026 | DF168: 1827.8689 | DG168: 41053.375 | DH168: 8756.384 | DI168: 55998.411 | DJ168: 8467 | DK168: 64465.411 | DM168: 703.027 | DN168: 10522.091 | DO168: 11225.118 | DP168: 1455.3989 | DQ168: 2914.5856 | DR168: 446.55003 | DS168: 3361.1356 | DT168: 161.92142 | DU168: 161.92142 | DW168: 0 | DX168: 6779.661 | DY168: 1447.7401 | DZ168: 0 | EA168: 0 | EB168: 243.91358 | EC168: 0 | ED168: 1271.1864 | EE168: 0 | EF168: 847.5 | EG168: 0 | EH168: 7397.5989 | EI168: 0 | EJ168: 6779.661 | EK168: 243.91358 | EL168: 847.5 | EM168: 735.835 | EN168: 446.55003 | EO168: 10964.025 | EP168: 0 | ER168: 0 | ES168: 0 | ET168: =(ES168+ER168)/($E$2+$E$3) -> 0 | EU168: 0 | EV168: 0 | EW168: =(EU168+EV168)/($J$2+$J$3) -> 0 | EY168: 0 | EZ168: 0 | FA168: =(EY168+EZ168)/($E$12+$E$14) -> 0 | FB168: 2460.204 | FC168: =FB168/$J$10 -> 0.53331975 | FF168: 2897.4 | FG168: 10423.35 | FH168: =(FF168+FG168)/($E$13+$E$15) -> 1 | FI168: 3837 | FJ168: =FI168/$J$11 -> 1 | FL168: 7873 | FM168: =FL168/$E$11 -> 0.68245451 | FN168: 2591 | FO168: =FN168/$J$9 -> 0.82634349 | FQ168: 278 | FR168: 367.01 | FS168: =(FQ168+FR168)/($J$8+$J$12) -> 0.81843675 | FT168: =FQ168+FR168 -> 645.01 | FV168: =FW168+FX168-FY168-GA168 -> #REF! | FW168: 243.91358 | FX168: 330 | FY168: =330*#REF! -> #REF! | FZ168: =FV168/1553.6723 -> #REF! | GA168: 0 | GC168: 17760.502 | GD168: =GC168/32600 -> 0.54480068 | GE168: 1455.3989 | GF168: =GE168/13478 -> 0.1079833 | GH168: 27874.29 | GI168: 4051.3255 | GK168: 0.257 | GL168: 0.84 | GM168: =-GN168 -> 1517.7758 | GN168: -1517.7758 | GO168: =GM168-1517.77579117 -> 0 | GP168: =GO168/1492.3021 -> 0 | GR168: 26700.265 | GS168: 3233.3349
P169: 167 | Q169: 0 | R169: 0 | S169: 0 | T169: 0 | U169: 0 | V169: 0 | W169: 0 | X169: 0 | Y169: 0 | Z169: 0 | AA169: 0 | AB169: 0 | AC169: 0 | AD169: 0 | AF169: 167 | AG169: 65325.853 | AH169: 2141.3 | AI169: 465.5 | AJ169: 0.734 | AK169: 0.931 | AL169: 0.931 | AM169: 289.408 | AN169: 3225.2772 | AO169: 0.448 | AP169: 0.277 | AQ169: 34788 | AR169: 20423.25 | AS169: 0.78 | AT169: 0.87 | AV169: 918.572 | AW169: 0.37299993 | AX169: 1026.301 | AY169: 0.63864406 | AZ169: 1121.478 | BA169: 0.57843924 | BC169: 53641.617 | BD169: 0.7704918 | BF169: 27874.29 | BG169: 0 | BH169: 0 | BI169: 0.85503957 | BJ169: 0 | BK169: 0 | BL169: 0 | BM169: 0 | BN169: 4051.326 | BO169: 0.30058807 | BP169: 0 | BQ169: 7668 | BR169: 0 | BT169: -700 | BU169: 0 | BV169: 4485 | BW169: 4485 | BX169: 0 | BY169: 0 | BZ169: -5000 | CA169: 0 | CB169: -5300 | CC169: 0 | CD169: -4000 | CE169: 0 | CF169: -4800 | CG169: 0 | CH169: 16650.94 | CI169: 16650.94 | CJ169: 21135.94 | CL169: -700 | CM169: 700 | CN169: 4485 | CO169: 0 | CP169: 0 | CQ169: 0 | CR169: -5000 | CS169: 5000 | CT169: -5300 | CU169: 5300 | CV169: -4000 | CW169: 4000 | CX169: -4800 | CY169: 4800 | CZ169: 16650.94 | DA169: 0 | DB169: 19800 | DD169: 34947.681 | DE169: 2296.602 | DF169: 1840.5668 | DG169: 39084.85 | DH169: 8761.81 | DI169: 62198.411 | DJ169: 8875 | DK169: 71073.411 | DM169: 628.426 | DN169: 10490.399 | DO169: 11118.825 | DP169: 1455.3989 | DQ169: 2897.8864 | DR169: 463.24924 | DS169: 3361.1356 | DT169: 160.99369 | DU169: 160.99369 | DW169: 0 | DX169: 6779.661 | DY169: 1447.7401 | DZ169: 0 | EA169: 0 | EB169: 244.84131 | EC169: 0 | ED169: 1271.1864 | EE169: 0 | EF169: 847.5 | EG169: 0 | EH169: 7397.5989 | EI169: 0 | EJ169: 6779.661 | EK169: 244.84131 | EL169: 847.5 | EM169: 735.835 | EN169: 463.24924 | EO169: 10964.025 | EP169: 0 | ER169: 0 | ES169: 0 | ET169: =(ES169+ER169)/($E$2+$E$3) -> 0 | EU169: 0 | EV169: 0 | EW169: =(EU169+EV169)/($J$2+$J$3) -> 0 | EY169: 9483.5983 | EZ169: 0 | FA169: =(EY169+EZ169)/($E$12+$E$14) -> 0.6971194 | FB169: 4613 | FC169: =FB169/$J$10 -> 1 | FF169: 2897.4 | FG169: 10423.35 | FH169: =(FF169+FG169)/($E$13+$E$15) -> 1 | FI169: 3837 | FJ169: =FI169/$J$11 -> 1 | FL169: 7873 | FM169: =FL169/$E$11 -> 0.68245451 | FN169: 2591 | FO169: =FN169/$J$9 -> 0.82634349 | FQ169: 278 | FR169: 367.01 | FS169: =(FQ169+FR169)/($J$8+$J$12) -> 0.81843675 | FT169: =FQ169+FR169 -> 645.01 | FV169: =FW169+FX169-FY169-GA169 -> #REF! | FW169: 244.84131 | FX169: 330 | FY169: =330*#REF! -> #REF! | FZ169: =FV169/1553.6723 -> #REF! | GA169: 0 | GC169: 9568.4754 | GD169: =GC169/32600 -> 0.29351151 | GE169: 1455.3989 | GF169: =GE169/13478 -> 0.1079833 | GH169: 28610.691 | GI169: 4604.9586 | GK169: 0.257 | GL169: 0.84 | GM169: =-GN169 -> 1517.7758 | GN169: -1517.7758 | GO169: =GM169-1517.77579117 -> 0 | GP169: =GO169/1492.3021 -> 0 | GR169: 27241.19 | GS169: 3574.5305
P170: 168 | Q170: 0 | R170: 0 | S170: 0 | T170: 0 | U170: 0 | V170: 0 | W170: 0 | X170: 0 | Y170: 0 | Z170: 0 | AA170: 0 | AB170: 0 | AC170: 0 | AD170: 0 | AF170: 168 | AG170: 67016.849 | AH170: 2159.7 | AI170: 469.5 | AJ170: 0.753 | AK170: 0.939 | AL170: 0.939 | AM170: 328.814 | AN170: 4063.6164 | AO170: 0.509 | AP170: 0.349 | AQ170: 33673 | AR170: 18803.475 | AS170: 0.755 | AT170: 0.801 | AV170: 908.722 | AW170: 0.36900019 | AX170: 1026.042 | AY170: 0.63848289 | AZ170: 1121.478 | BA170: 0.57843924 | BC170: 53641.617 | BD170: 0.7704918 | BF170: 28610.691 | BG170: 0 | BH170: 0 | BI170: 0.87762856 | BJ170: 0 | BK170: 0 | BL170: 0 | BM170: 0 | BN170: 4604.959 | BO170: 0.34166486 | BP170: 0 | BQ170: 7668 | BR170: 0 | BT170: -700 | BU170: 0 | BV170: 4485 | BW170: 4485 | BX170: 0 | BY170: 0 | BZ170: -5000 | CA170: 0 | CB170: -5300 | CC170: 0 | CD170: -4000 | CE170: 0 | CF170: -4800 | CG170: 0 | CH170: 14539.764 | CI170: 14539.764 | CJ170: 19024.764 | CL170: -700 | CM170: 700 | CN170: 4485 | CO170: 0 | CP170: 0 | CQ170: 0 | CR170: -5000 | CS170: 5000 | CT170: -5300 | CU170: 5300 | CV170: -4000 | CW170: 4000 | CX170: -4800 | CY170: 4800 | CZ170: 14539.764 | DA170: 0 | DB170: 19800 | DD170: 32664.236 | DE170: 2193.31 | DF170: 1545.0016 | DG170: 36402.548 | DH170: 8468.374 | DI170: 59099.411 | DJ170: 9157 | DK170: 68256.411 | DM170: 646.393 | DN170: 10490.399 | DO170: 11136.792 | DP170: 1455.3989 | DQ170: 2897.8864 | DR170: 463.24924 | DS170: 3361.1356 | DT170: 160.99369 | DU170: 160.99369 | DW170: 0 | DX170: 6779.661 | DY170: 1447.7401 | DZ170: 0 | EA170: 0 | EB170: 244.84131 | EC170: 0 | ED170: 1271.1864 | EE170: 0 | EF170: 847.5 | EG170: 0 | EH170: 7397.5989 | EI170: 0 | EJ170: 6779.661 | EK170: 244.84131 | EL170: 847.5 | EM170: 735.835 | EN170: 463.24924 | EO170: 10964.025 | EP170: 0 | ER170: 0 | ES170: 0 | ET170: =(ES170+ER170)/($E$2+$E$3) -> 0 | EU170: 0 | EV170: 0 | EW170: =(EU170+EV170)/($J$2+$J$3) -> 0 | EY170: 0 | EZ170: 0 | FA170: =(EY170+EZ170)/($E$12+$E$14) -> 0 | FB170: 1388.2724 | FC170: =FB170/$J$10 -> 0.30094783 | FF170: 2897.4 | FG170: 10423.35 | FH170: =(FF170+FG170)/($E$13+$E$15) -> 1 | FI170: 0 | FJ170: =FI170/$J$11 -> 0 | FL170: 7873 | FM170: =FL170/$E$11 -> 0.68245451 | FN170: 2591 | FO170: =FN170/$J$9 -> 0.82634349 | FQ170: 278 | FR170: 367.01 | FS170: =(FQ170+FR170)/($J$8+$J$12) -> 0.81843675 | FT170: =FQ170+FR170 -> 645.01 | FV170: =FW170+FX170-FY170-GA170 -> #REF! | FW170: 244.84131 | FX170: 330 | FY170: =330*#REF! -> #REF! | FZ170: =FV170/1553.6723 -> #REF! | GA170: 0 | GC170: 20313.591 | GD170: =GC170/32600 -> 0.62311628 | GE170: 1455.3989 | GF170: =GE170/13478 -> 0.1079833 | GK170: 0.257 | GL170: 0.84 | GM170: =-GN170 -> 1517.7758 | GN170: -1517.7758 | GO170: =GM170-1517.77579117 -> 0 | GP170: =GO170/1492.3021 -> 0 | GR170: 27874.29 | GS170: 4051.3255
GR171: 28610.691 | GS171: 4604.9586

Sheet Obtención Datos Demandas
A1: FRS_hydrogen_storage | B1: FRS_hydrogen_bus | C1: 1241 | D1: 0 | E1: hydrogen | F1: true | AZ1: FRSW_hydrogen_demand
A2: FRSW_hydrogen_storage | B2: FRSW_hydrogen_bus | C2: 331 | D2: 0 | E2: hydrogen | F2: true | AZ2: 0 | BA2: =AZ2/5014.12 -> 0
C3: España Electricidad | N3: España Hidrógeno | S3: Portugal Electricidad | AE3: Portugal Hidrógeno | AZ3: 0 | BA3: =AZ3/5014.12 -> 0
C4: Balance Prosumer | D4: Generador Extra Prosumer | E4: Load Extra Prosumer | F4: Balance Emarket extra | G4: Generador Extra Emarket | H4: Load Extra Emarket | I4: Native Demand | J4: Fixed Demand | K4: DEMANDA TOTAL H2 | L4: GENERADOR EXTRA ES | N4: Native Demand | O4: H2 to eLiquids | P4: H2 Boiler | Q4: DEMANDA TOTAL H2 | T4: Balance Emarket extra | U4: Generador Extra Emarket | V4: Load Extra Emarket | W4: Balance Prosumer | X4: Generador Extra Prosumer | Y4: Load Extra Prosumer | Z4: Native Demand | AA4: Fixed Demand | AB4: DEMANDA TOTAL H2 | AC4: GENERADOR EXTRA PT | AE4: Native Demand | AG4: MA_hydrogen_profile_high | AH4: ES_ccgt_profile | AI4: PT_ccgt_profile | AL4: Resultados TYNDP | AZ4: 0 | BA4: =AZ4/5014.12 -> 0
B5: horas | C5: (Generation-Load) | D5: Generation | E5: Load | F5: (Generation-Load) | G5: Generation | H5: Load | I5: Load | J5: Load | K5: Load | L5: Generation | N5: Load | O5: Load | P5: Load | Q5: Load | S5: horas | T5: (Generation-Load) | U5: Generation | V5: Load | W5: (Generation-Load) | X5: Generation | Y5: Load | Z5: Load | AA5: Load | AB5: Load | AC5: Generation | AE5: Load | AG5: 0.77362126 | AH5: 0 | AI5: 0 | AL5: ES00-FR00 | AM5: FRh2-FRh2S | AN5: FRh2S-FRh2 | AO5: FRh2-FRh2S | AP5: FRh2S-FRh2SW | AQ5: FRh2SW-FRh2S | AR5: FRh2S-FRh2SW | AS5: ESh2-FRh2S | AT5: FRh2S-ESh2 | AU5: ESh2-FRh2S | AV5: ESh2-FRh2SW | AZ5: 0 | BA5: =AZ5/5014.12 -> 0
B6: =1 -> 1 | C6: -5119.2421 | D6: =IF(C6>0,C6,0) -> 0 | E6: =IF(C6<0,-C6,0) -> 5119.2421 | F6: -1766.7149 | G6: =IF(F6>0,F6,0) -> 0 | H6: =IF(F6<0,-F6,0) -> 1766.7149 | I6: 29610.763 | J6: 2130.936 | K6: =E6+H6+I6+J6 -> 38627.656 | L6: =D6+G6 -> 0 | N6: 10493.066 | O6: 1342.407 | P6: 0 | Q6: =N6+O6+P6 -> 11835.473 | S6: 1 | T6: -648.89213 | U6: =IF(T6>0,T6,0) -> 0 | V6: =IF(T6<0,-T6,0) -> 648.89213 | W6: -1404.249 | X6: =IF(W6>0,W6,0) -> 0 | Y6: =IF(W6<0,-W6,0) -> 1404.249 | Z6: 7726.718 | AA6: 0 | AB6: =V6+Y6+Z6 -> 9779.8592 | AC6: =U6+X6 -> 0 | AE6: 1194.7295 | AG6: 0.77362126 | AH6: 0 | AI6: 0 | AL6: -5000 | AM6: -6779.661 | AN6: =IF(AM6<0,-AM6,0) -> 6779.661 | AO6: =IF(AM6>0,AM6,0) -> 0 | AP6: -1553.6723 | AQ6: =IF(AP6<0,-AP6,0) -> 1553.6723 | AR6: =IF(AP6>0,AP6,0) -> 0 | AS6: 4147.071 | AT6: =IF(AS6<0,-AS6,0) -> 0 | AU6: =IF(AS6>0,AS6,0) -> 4147.071 | AV6: 0 | AZ6: 0 | BA6: =AZ6/5014.12 -> 0
B7: =B6+1 -> 2 | C7: -10211.021 | D7: =IF(C7>0,C7,0) -> 0 | E7: =IF(C7<0,-C7,0) -> 10211.021 | F7: -1717.7 | G7: =IF(F7>0,F7,0) -> 0 | H7: =IF(F7<0,-F7,0) -> 1717.7 | I7: 28009.474 | J7: 2090.089 | K7: =E7+H7+I7+J7 -> 42028.284 | L7: =D7+G7 -> 0 | N7: 10493.066 | O7: 1342.407 | P7: 0 | Q7: =N7+O7+P7 -> 11835.473 | S7: 2 | T7: -643.81021 | U7: =IF(T7>0,T7,0) -> 0 | V7: =IF(T7<0,-T7,0) -> 643.81021 | W7: -235.12979 | X7: =IF(W7>0,W7,0) -> 0 | Y7: =IF(W7<0,-W7,0) -> 235.12979 | Z7: 7402.483 | AA7: 0 | AB7: =V7+Y7+Z7 -> 8281.423 | AC7: =U7+X7 -> 0 | AE7: 1194.7295 | AG7: 0.77362126 | AH7: 0 | AI7: 0 | AL7: -5000 | AM7: -6779.661 | AN7: =IF(AM7<0,-AM7,0) -> 6779.661 | AO7: =IF(AM7>0,AM7,0) -> 0 | AP7: -1553.6723 | AQ7: =IF(AP7<0,-AP7,0) -> 1553.6723 | AR7: =IF(AP7>0,AP7,0) -> 0 | AS7: 4147.071 | AT7: =IF(AS7<0,-AS7,0) -> 0 | AU7: =IF(AS7>0,AS7,0) -> 4147.071 | AV7: 0 | AZ7: 0 | BA7: =AZ7/5014.12 -> 0
B8: =B7+1 -> 3 | C8: -10890.72 | D8: =IF(C8>0,C8,0) -> 0 | E8: =IF(C8<0,-C8,0) -> 10890.72 | F8: -1698.5755 | G8: =IF(F8>0,F8,0) -> 0 | H8: =IF(F8<0,-F8,0) -> 1698.5755 | I8: 26842.165 | J8: 2042.995 | K8: =E8+H8+I8+J8 -> 41474.456 | L8: =D8+G8 -> 0 | N8: 10493.066 | O8: 1342.407 | P8: 0 | Q8: =N8+O8+P8 -> 11835.473 | S8: 3 | T8: -619.24532 | U8: =IF(T8>0,T8,0) -> 0 | V8: =IF(T8<0,-T8,0) -> 619.24532 | W8: -177.8117 | X8: =IF(W8>0,W8,0) -> 0 | Y8: =IF(W8<0,-W8,0) -> 177.8117 | Z8: 7034.883 | AA8: 0 | AB8: =V8+Y8+Z8 -> 7831.94 | AC8: =U8+X8 -> 0 | AE8: 1194.7295 | AG8: 0.77362126 | AH8: 0 | AI8: 0 | AL8: -5000 | AM8: -6779.661 | AN8: =IF(AM8<0,-AM8,0) -> 6779.661 | AO8: =IF(AM8>0,AM8,0) -> 0 | AP8: -1553.6723 | AQ8: =IF(AP8<0,-AP8,0) -> 1553.6723 | AR8: =IF(AP8>0,AP8,0) -> 0 | AS8: 4147.071 | AT8: =IF(AS8<0,-AS8,0) -> 0 | AU8: =IF(AS8>0,AS8,0) -> 4147.071 | AV8: 0 | AZ8: 0 | BA8: =AZ8/5014.12 -> 0
B9: =B8+1 -> 4 | C9: -11645.257 | D9: =IF(C9>0,C9,0) -> 0 | E9: =IF(C9<0,-C9,0) -> 11645.257 | F9: -1694.1628 | G9: =IF(F9>0,F9,0) -> 0 | H9: =IF(F9<0,-F9,0) -> 1694.1628 | I9: 26274.437 | J9: 2003.629 | K9: =E9+H9+I9+J9 -> 41617.486 | L9: =D9+G9 -> 0 | N9: 10493.066 | O9: 1342.407 | P9: 0 | Q9: =N9+O9+P9 -> 11835.473 | S9: 4 | T9: -612.32085 | U9: =IF(T9>0,T9,0) -> 0 | V9: =IF(T9<0,-T9,0) -> 612.32085 | W9: -2550.2281 | X9: =IF(W9>0,W9,0) -> 0 | Y9: =IF(W9<0,-W9,0) -> 2550.2281 | Z9: 6846.224 | AA9: 0 | AB9: =V9+Y9+Z9 -> 10008.773 | AC9: =U9+X9 -> 0 | AE9: 1194.7295 | AG9: 0.77362126 | AH9: 0 | AI9: 0 | AL9: -5000 | AM9: -6779.661 | AN9: =IF(AM9<0,-AM9,0) -> 6779.661 | AO9: =IF(AM9>0,AM9,0) -> 0 | AP9: -1553.6723 | AQ9: =IF(AP9<0,-AP9,0) -> 1553.6723 | AR9: =IF(AP9>0,AP9,0) -> 0 | AS9: 4147.071 | AT9: =IF(AS9<0,-AS9,0) -> 0 | AU9: =IF(AS9>0,AS9,0) -> 4147.071 | AV9: 0 | AZ9: 0 | BA9: =AZ9/5014.12 -> 0
B10: =B9+1 -> 5 | C10: -10595.395 | D10: =IF(C10>0,C10,0) -> 0 | E10: =IF(C10<0,-C10,0) -> 10595.395 | F10: -1694.2074 | G10: =IF(F10>0,F10,0) -> 0 | H10: =IF(F10<0,-F10,0) -> 1694.2074 | I10: 26537.633 | J10: 1976.586 | K10: =E10+H10+I10+J10 -> 40803.821 | L10: =D10+G10 -> 0 | N10: 10508.776 | O10: 1342.407 | P10: 0 | Q10: =N10+O10+P10 -> 11851.183 | S10: 5 | T10: -613.75383 | U10: =IF(T10>0,T10,0) -> 0 | V10: =IF(T10<0,-T10,0) -> 613.75383 | W10: -1536.1245 | X10: =IF(W10>0,W10,0) -> 0 | Y10: =IF(W10<0,-W10,0) -> 1536.1245 | Z10: 6811.541 | AA10: 0 | AB10: =V10+Y10+Z10 -> 8961.4193 | AC10: =U10+X10 -> 0 | AE10: 1194.7295 | AG10: 0.77362126 | AH10: 0 | AI10: 0 | AL10: -5000 | AM10: -6779.661 | AN10: =IF(AM10<0,-AM10,0) -> 6779.661 | AO10: =IF(AM10>0,AM10,0) -> 0 | AP10: -1553.6723 | AQ10: =IF(AP10<0,-AP10,0) -> 1553.6723 | AR10: =IF(AP10>0,AP10,0) -> 0 | AS10: 4147.5308 | AT10: =IF(AS10<0,-AS10,0) -> 0 | AU10: =IF(AS10>0,AS10,0) -> 4147.5308 | AV10: 0 | AZ10: 0 | BA10: =AZ10/5014.12 -> 0
B11: =B10+1 -> 6 | C11: -6482.9571 | D11: =IF(C11>0,C11,0) -> 0 | E11: =IF(C11<0,-C11,0) -> 6482.9571 | F11: -1447.1086 | G11: =IF(F11>0,F11,0) -> 0 | H11: =IF(F11<0,-F11,0) -> 1447.1086 | I11: 27552.059 | J11: 1965.631 | K11: =E11+H11+I11+J11 -> 37447.756 | L11: =D11+G11 -> 0 | N11: 10540.196 | O11: 1342.407 | P11: 0 | Q11: =N11+O11+P11 -> 11882.603 | S11: 6 | T11: -531.57613 | U11: =IF(T11>0,T11,0) -> 0 | V11: =IF(T11<0,-T11,0) -> 531.57613 | W11: -1159.7527 | X11: =IF(W11>0,W11,0) -> 0 | Y11: =IF(W11<0,-W11,0) -> 1159.7527 | Z11: 6946.607 | AA11: 0 | AB11: =V11+Y11+Z11 -> 8637.9358 | AC11: =U11+X11 -> 0 | AE11: 1292.686 | AG11: 0.77362126 | AH11: 0 | AI11: 0 | AL11: -5000 | AM11: -6779.661 | AN11: =IF(AM11<0,-AM11,0) -> 6779.661 | AO11: =IF(AM11>0,AM11,0) -> 0 | AP11: -1553.6723 | AQ11: =IF(AP11<0,-AP11,0) -> 1553.6723 | AR11: =IF(AP11>0,AP11,0) -> 0 | AS11: 4148.4506 | AT11: =IF(AS11<0,-AS11,0) -> 0 | AU11: =IF(AS11>0,AS11,0) -> 4148.4506 | AV11: 0 | AZ11: 0 | BA11: =AZ11/5014.12 -> 0
B12: =B11+1 -> 7 | C12: -4743.9164 | D12: =IF(C12>0,C12,0) -> 0 | E12: =IF(C12<0,-C12,0) -> 4743.9164 | F12: -56.535106 | G12: =IF(F12>0,F12,0) -> 0 | H12: =IF(F12<0,-F12,0) -> 56.535106 | I12: 29332.198 | J12: 1971.125 | K12: =E12+H12+I12+J12 -> 36103.774 | L12: =D12+G12 -> 0 | N12: 10555.906 | O12: 1342.407 | P12: 0 | Q12: =N12+O12+P12 -> 11898.313 | S12: 7 | T12: -68.641489 | U12: =IF(T12>0,T12,0) -> 0 | V12: =IF(T12<0,-T12,0) -> 68.641489 | W12: -160.16277 | X12: =IF(W12>0,W12,0) -> 0 | Y12: =IF(W12<0,-W12,0) -> 160.16277 | Z12: 7154.418 | AA12: 0 | AB12: =V12+Y12+Z12 -> 7383.2223 | AC12: =U12+X12 -> 0 | AE12: 1390.6425 | AG12: 0.77362126 | AH12: 0 | AI12: 0 | AL12: -5000 | AM12: -6779.661 | AN12: =IF(AM12<0,-AM12,0) -> 6779.661 | AO12: =IF(AM12>0,AM12,0) -> 0 | AP12: -1553.6723 | AQ12: =IF(AP12<0,-AP12,0) -> 1553.6723 | AR12: =IF(AP12>0,AP12,0) -> 0 | AS12: 4148.9105 | AT12: =IF(AS12<0,-AS12,0) -> 0 | AU12: =IF(AS12>0,AS12,0) -> 4148.9105 | AV12: 0 | AZ12: 651.21893 | BA12: =AZ12/5014.12 -> 0.12987701
B13: =B12+1 -> 8 | C13: -5767.9818 | D13: =IF(C13>0,C13,0) -> 0 | E13: =IF(C13<0,-C13,0) -> 5767.9818 | F13: -217.00319 | G13: =IF(F13>0,F13,0) -> 0 | H13: =IF(F13<0,-F13,0) -> 217.00319 | I13: 31087.021 | J13: 1985.193 | K13: =E13+H13+I13+J13 -> 39057.199 | L13: =D13+G13 -> 0 | N13: 10571.616 | O13: 1342.407 | P13: 0 | Q13: =N13+O13+P13 -> 11914.023 | S13: 8 | T13: -60.732979 | U13: =IF(T13>0,T13,0) -> 0 | V13: =IF(T13<0,-T13,0) -> 60.732979 | W13: -141.71064 | X13: =IF(W13>0,W13,0) -> 0 | Y13: =IF(W13<0,-W13,0) -> 141.71064 | Z13: 7300.096 | AA13: 0 | AB13: =V13+Y13+Z13 -> 7502.5396 | AC13: =U13+X13 -> 0 | AE13: 1483.4434 | AG13: 0.77362126 | AH13: 0 | AI13: 0 | AL13: -5000 | AM13: -6779.661 | AN13: =IF(AM13<0,-AM13,0) -> 6779.661 | AO13: =IF(AM13>0,AM13,0) -> 0 | AP13: -1553.6723 | AQ13: =IF(AP13<0,-AP13,0) -> 1553.6723 | AR13: =IF(AP13>0,AP13,0) -> 0 | AS13: 4149.3704 | AT13: =IF(AS13<0,-AS13,0) -> 0 | AU13: =IF(AS13>0,AS13,0) -> 4149.3704 | AV13: 0 | AZ13: 948.49917 | BA13: =AZ13/5014.12 -> 0.18916563
